Workbook

Sheet Navigation
B2: Claire Studio — FP&A Portfolio Model
B3: Kate Kucherova | Portfolio Project 2026 | CMA Candidate
B5: About This Project
B6: Business: | C6: Claire — Studio of Physical & Aesthetic Development. Children's fitness, dance & martial arts. Bataysk, Russia. Nov 2019 – Jul 2022.
B7: Data source: | C7: This workbook is based on cleaned Claire Studio financial records. Model_Data supports the monthly P&L, dashboard, KPIs, and financial schedules. Ballet shoe COGS uses a weighted-average estimate.
B8: What was built: | C8: Full FP&A model: monthly P&L, KPIs, budget vs actual, variance analysis, unit economics, break-even, management financials, accounting schedules.
B9: Skills shown: | C9: Financial data cleanup, revenue and expense classification, COGS and margin analysis, budgeting, variance explanation, unit economics, and accounting treatment.
B11: Budget Methodology Note
B12: The 2021 management budget was prepared using the late-2020 run-rate, adjusted for second hall expansion rent and utilities, expected program enrollment growth, fixed payroll, and planned merchandise activity.
B14: Tab | C14: What You'll Find
B15: Business_Overview | C15: Business snapshot, programs, pricing, startup investment, key assumptions
B16: Management_Dashboard | C16: KPI summary, revenue trend, program mix, budget check — first visual impression
B17: Monthly_P&L | C17: Month-by-month P&L: class revenue by program, merchandise, COGS, operating expenses, NOI
B18: Annual_KPIs | C18: Annual revenue by program, margins, and KPIs by year
B19: Budget_vs_Actual | C19: 2021 monthly and annual budget vs actual with F/U flags
B20: Variance_Commentary | C20: Plain-English management commentary explaining 2021 results vs budget
B21: Second_Hall_BreakEven | C21: Break-even analysis for the second hall expansion decision
B22: Management_Financials | C22: Income statement, cash flow, and financial position — annual view
B23: Cost_Per_Class_Model | C23: Unit economics: revenue per class, contribution margin, instructor cost logic
B24: Accounting_Treatment | C24: How each category was classified — cash to accrual bridge
B25: Journal_Entries | C25: Representative month-end journal entries with debit/credit/balance check
B26: ——— Supporting Data Tabs ———
B27: Budget_Assumptions | C27: Monthly budget build-up by line item supporting Budget_vs_Actual | D27: Supporting reference
B28: Inventory_Rollforward | C28: Merchandise margin and COGS support schedule | D28: Supporting reference
B29: Fixed_Asset_Depreciation | C29: Straight-line depreciation schedule for equipment and improvements | D29: Supporting reference
B30: Model_Data | C30: Structured monthly source data. Feeds Monthly_PL and all downstream tabs. Do not edit. | D30: Data source
B32: Portfolio Version — 16 tabs | Full model with audit log, correction history, and business valuation available on request.

Sheet Business_Overview
A1: Claire Studio — Business Overview & Key Assumptions
A2: Bataysk | Operating records: Nov 2019 – Jul 2022 | Financial Case Study Portfolio | Amounts shown in $
A3: Claire Children’s Dance Studio was a service-based children’s activity business that generated revenue primarily from recurring class payments for dance, fitness, gymnastics, and karate programs.
A4: Business Snapshot | E4: Founders & Roles | H4: Timeline
A5: Business name | B5: Claire — Studio of Physical & Aesthetic Development | E5: Kate Kucherova | F5: Co-founder, owner, financial manager | H5: Nov 2019 | I5: Studio opened with Hall 1; choreography and gymnastics programs launched
A6: Trade name | B6: Claire | E6: Teaching role | F6: Fitness instructor — no salary drawn | H6: Dec 2019 | I6: First full operating month; setup costs exceeded early revenue
A7: Location | B7: Bataysk, Rostov Oblast, Russia | E7: Finance role | F7: P&L, budgeting, cash flow, payroll, vendors | H7: Jan–Mar 2020 | I7: Enrollment and revenue grew; fitness program added
A8: Business type | B8: Partnership — 2 co-founders | E8: Sveta Strelnikova | F8: Co-founder, choreography partner | H8: Apr–May 2020 | I8: COVID closure period; no operating revenue
A9: Legal form | B9: Sole proprietor, simplified tax regime | E9: Qualification | F9: Master of Sports in Gymnastics | H9: Jun 2020 | I9: Studio reopened; choreography and fitness activity resumed
A10: Industry | B10: Children's fitness, dance & martial arts | E10: Teaching role | F10: Lead choreography — 3 groups | H10: Sep 2020 | I10: Karate program launched; instructor revenue-share model introduced
A11: Currency shown | B11: Presentation currency: $ | E11: Compensation | F11: $750/mo salary + profit distribution | H11: Early 2021 | I11: Hall 2 leased to expand capacity and support subrental income
A12: Data source | B12: Clean Cash Ledger, tax receipts, owner records, owner recollection | E12: Exit | F12: Business operations ended in July 2022 after owner relocation to the United States. | H12: Apr 2021 | I12: Strong spring performance month with revenue above $12K
H13: May 2021 | I13: Fitness pricing increased by 50%
H14: Sep 2021 | I14: Choreography and karate pricing increased by 25%
H15: Jun–Jul 2022 | I15: Business wind-down and transition period
H16: Jul 2022 | I16: Model period ends after business operations transitioned
A18: Program Details & Pricing
A19: Program | B19: Groups | C19: Students/Group | D19: Capacity | E19: Days/Week | F19: Sessions/Mo | G19: Price at Launch ($) | H19: Revised Price ($) | I19: Notes
A20: Choreography | B20: 3 | C20: 15 | D20: 45 | E20: 3 | F20: 36 | G20: $250 | H20: $312.50 (Sep 2021) | I20: Instructor is co-founder, Core revenue stream throughout
A21: Fitness | B21: 2 | C21: 10 | D21: 20 | E21: 2 | F21: 16 | G21: $125 | H21: $187.50 (May 2021) | I21: Instructor is founder, zero direct labor cost
A22: Karate | B22: 2 | C22: 15 | D22: 30 | E22: 3 | F22: 24 | G22: $250 | H22: $312.50 (Sep 2021) | I22: Instructor revenue share: 40% at launch, revised to 50% from Sep 2021
A23: Gymnastics | B23: 1 | C23: 12 | D23: 12 | E23: 2 | F23: 8 | G23: $250 | H23: Discontinued | I23: Nov 2019–Mar 2020. Phased out after COVID
A24: Hall Rental | B24: — | C24: — | D24: — | E24: — | F24: — | G24: Variable | H24: — | I24: Subrental of Hall 2 from early 2021
A26: Startup Investment — Opening Costs (Nov 2019)
A27: Category | B27: Description | C27: Amount ($) | D27: Accounting Treatment | E27: Notes
A28: Equipment & Fixtures | B28: Mirrors, mats, benches, wardrobes, chairs, curtains | C28: 3646 | D28: Capitalize & depreciate | E28: Mirror 7yr; furniture 5yr; mats 3yr
A29: Leasehold Improvements | B29: Flooring, painting, installed lighting | C29: 522 | D29: Amortize over lease | E29: 3-year lease term
A30: Advertising | B30: Print ads, Facebook, flyers, business cards | C30: 724 | D30: Expense at launch | E30: Consumed immediately
A31: Rent first month | B31: Security deposit + first month Hall 1 | C31: 2750 | D31: Prepaid rent / deposit | E31: First month expensed Dec 2019
A32: Office & Signage | B32: Signs, frames, keys, shoe covers, hardware | C32: 704 | D32: Expense at launch | E32: Below capitalization threshold
A33: TOTAL | C33: =SUM(C28:C32) -> 8346 | E33: Opening investment estimate
A35: Key Assumptions & Methodology Notes
A36: Exchange rate | B36: All amounts shown in $ for portfolio presentation.
A37: Missing periods | B37: Apr–May 2020 unavailable — studio closed (COVID lockdown). Excluded from ledger; impact analyzed in Variance Analysis tab.
A38: Payroll classification | B38: Partner fixed salary: $750/mo = Payroll Expense; above fixed salary = Partner Distribution (equity). Karate instructor: revenue share = operating expense.
A39: Reconstructed data | B39: Opening budget and some early 2020 figures reconstructed from owner recollection. All reconstructed items are noted where they appear.
A40: Depreciation | B40: Mirror + install: 7yr straight-line ($27/mo). Other equipment: 5yr ($23/mo). Leasehold improvements: 3yr ($15/mo). Total: ~$65/month from Jan 2020.

Sheet Management_Dashboard
A1: Claire Studio FP&A and Small Business Finance Model — Management Dashboard
A2: Built from real small-business operating records. Source data cleaned and adapted into U.S.-style presentation dollars.
A4: KPI | B4: Value | C4: Interpretation
A5: All-period Revenue | B5: ='Monthly_P&L'!AH26 -> 275336.48 | C5: Total revenue from monthly P&L
A6: All-period NOI | B6: ='Monthly_P&L'!AH48 -> 84989.86 | C6: Net operating income / cash flow before owner items
A7: All-period Margin | B7: ='Monthly_P&L'!AH54 -> 0.30867635 | C7: NOI ÷ Revenue
A8: 2021 Revenue | B8: =Annual_KPIs!D16 -> 120892.1 | C8: Best full-year baseline
A9: 2022 Avg Monthly Revenue | B9: =Annual_KPIs!E37 -> 11518.84 | C9: Partial year run-rate through July
A10: Cumulative Cash After Owners | B10: =Management_Financials!F21 -> 35018.11 | C10: After owner contributions/distributions
A13: Period | B13: Revenue | C13: Net Operating Income | D13: Net Margin % | F13: Expense Driver | G13: All-Period Amount
A14: 2019-11 | B14: =INDEX('Monthly_P&L'!$C$26:$AG$26,1,MATCH($A14,'Monthly_P&L'!$C$3:$AG$3,0)) -> 1800 | C14: =INDEX('Monthly_P&L'!$C$48:$AG$48,1,MATCH($A14,'Monthly_P&L'!$C$3:$AG$3,0)) -> 1237.4 | D14: =IF(B14<>0,C14/B14,"") -> 0.68744444 | F14: Payroll | G14: ='Monthly_P&L'!AH34 -> 41095.62
A15: 2019-12 | B15: =INDEX('Monthly_P&L'!$C$26:$AG$26,1,MATCH($A15,'Monthly_P&L'!$C$3:$AG$3,0)) -> 2775 | C15: =INDEX('Monthly_P&L'!$C$48:$AG$48,1,MATCH($A15,'Monthly_P&L'!$C$3:$AG$3,0)) -> -1163.52 | D15: =IF(B15<>0,C15/B15,"") -> -0.41928649 | F15: Rent | G15: ='Monthly_P&L'!AH40 -> 110229.51
A16: 2020-01 | B16: =INDEX('Monthly_P&L'!$C$26:$AG$26,1,MATCH($A16,'Monthly_P&L'!$C$3:$AG$3,0)) -> 5475 | C16: =INDEX('Monthly_P&L'!$C$48:$AG$48,1,MATCH($A16,'Monthly_P&L'!$C$3:$AG$3,0)) -> 1240.01 | D16: =IF(B16<>0,C16/B16,"") -> 0.22648584 | F16: Utilities | G16: ='Monthly_P&L'!AH41 -> 13436.11
A17: 2020-02 | B17: =INDEX('Monthly_P&L'!$C$26:$AG$26,1,MATCH($A17,'Monthly_P&L'!$C$3:$AG$3,0)) -> 4937.5 | C17: =INDEX('Monthly_P&L'!$C$48:$AG$48,1,MATCH($A17,'Monthly_P&L'!$C$3:$AG$3,0)) -> 1030.59 | D17: =IF(B17<>0,C17/B17,"") -> 0.20872709 | F17: Advertising | G17: ='Monthly_P&L'!AH42 -> 6484.01
A18: 2020-03 | B18: =INDEX('Monthly_P&L'!$C$26:$AG$26,1,MATCH($A18,'Monthly_P&L'!$C$3:$AG$3,0)) -> 5268.75 | C18: =INDEX('Monthly_P&L'!$C$48:$AG$48,1,MATCH($A18,'Monthly_P&L'!$C$3:$AG$3,0)) -> 205.84 | D18: =IF(B18<>0,C18/B18,"") -> 0.03906809 | F18: Tax | G18: ='Monthly_P&L'!AH43 -> 2245.95
A19: 2020-06 | B19: =INDEX('Monthly_P&L'!$C$26:$AG$26,1,MATCH($A19,'Monthly_P&L'!$C$3:$AG$3,0)) -> 5243.75 | C19: =INDEX('Monthly_P&L'!$C$48:$AG$48,1,MATCH($A19,'Monthly_P&L'!$C$3:$AG$3,0)) -> 1713.61 | D19: =IF(B19<>0,C19/B19,"") -> 0.32679094 | F19: COGS | G19: ='Monthly_P&L'!AH31 -> 4213.13
A20: 2020-07 | B20: =INDEX('Monthly_P&L'!$C$26:$AG$26,1,MATCH($A20,'Monthly_P&L'!$C$3:$AG$3,0)) -> 6550 | C20: =INDEX('Monthly_P&L'!$C$48:$AG$48,1,MATCH($A20,'Monthly_P&L'!$C$3:$AG$3,0)) -> 3500.89 | D20: =IF(B20<>0,C20/B20,"") -> 0.53448702 | F20: Other OpEx | G20: ='Monthly_P&L'!AH45 -> 6461.81
A21: 2020-08 | B21: =INDEX('Monthly_P&L'!$C$26:$AG$26,1,MATCH($A21,'Monthly_P&L'!$C$3:$AG$3,0)) -> 6343.75 | C21: =INDEX('Monthly_P&L'!$C$48:$AG$48,1,MATCH($A21,'Monthly_P&L'!$C$3:$AG$3,0)) -> 2446.37 | D21: =IF(B21<>0,C21/B21,"") -> 0.38563468
A22: 2020-09 | B22: =INDEX('Monthly_P&L'!$C$26:$AG$26,1,MATCH($A22,'Monthly_P&L'!$C$3:$AG$3,0)) -> 10837.5 | C22: =INDEX('Monthly_P&L'!$C$48:$AG$48,1,MATCH($A22,'Monthly_P&L'!$C$3:$AG$3,0)) -> 2820.13 | D22: =IF(B22<>0,C22/B22,"") -> 0.26021961
A23: 2020-10 | B23: =INDEX('Monthly_P&L'!$C$26:$AG$26,1,MATCH($A23,'Monthly_P&L'!$C$3:$AG$3,0)) -> 8568.75 | C23: =INDEX('Monthly_P&L'!$C$48:$AG$48,1,MATCH($A23,'Monthly_P&L'!$C$3:$AG$3,0)) -> 4702.37 | D23: =IF(B23<>0,C23/B23,"") -> 0.54878133
A24: 2020-11 | B24: =INDEX('Monthly_P&L'!$C$26:$AG$26,1,MATCH($A24,'Monthly_P&L'!$C$3:$AG$3,0)) -> 7443.75 | C24: =INDEX('Monthly_P&L'!$C$48:$AG$48,1,MATCH($A24,'Monthly_P&L'!$C$3:$AG$3,0)) -> 1951.97 | D24: =IF(B24<>0,C24/B24,"") -> 0.26222939
A25: 2020-12 | B25: =INDEX('Monthly_P&L'!$C$26:$AG$26,1,MATCH($A25,'Monthly_P&L'!$C$3:$AG$3,0)) -> 8568.75 | C25: =INDEX('Monthly_P&L'!$C$48:$AG$48,1,MATCH($A25,'Monthly_P&L'!$C$3:$AG$3,0)) -> 2977.75 | D25: =IF(B25<>0,C25/B25,"") -> 0.34751276
A26: 2021-01 | B26: =INDEX('Monthly_P&L'!$C$26:$AG$26,1,MATCH($A26,'Monthly_P&L'!$C$3:$AG$3,0)) -> 6631.25 | C26: =INDEX('Monthly_P&L'!$C$48:$AG$48,1,MATCH($A26,'Monthly_P&L'!$C$3:$AG$3,0)) -> 2693.8 | D26: =IF(B26<>0,C26/B26,"") -> 0.40622809
A27: 2021-02 | B27: =INDEX('Monthly_P&L'!$C$26:$AG$26,1,MATCH($A27,'Monthly_P&L'!$C$3:$AG$3,0)) -> 6699.24 | C27: =INDEX('Monthly_P&L'!$C$48:$AG$48,1,MATCH($A27,'Monthly_P&L'!$C$3:$AG$3,0)) -> 265.65 | D27: =IF(B27<>0,C27/B27,"") -> 0.039653752
A28: 2021-03 | B28: =INDEX('Monthly_P&L'!$C$26:$AG$26,1,MATCH($A28,'Monthly_P&L'!$C$3:$AG$3,0)) -> 11406.87 | C28: =INDEX('Monthly_P&L'!$C$48:$AG$48,1,MATCH($A28,'Monthly_P&L'!$C$3:$AG$3,0)) -> 3758.72 | D28: =IF(B28<>0,C28/B28,"") -> 0.32951371
A29: 2021-04 | B29: =INDEX('Monthly_P&L'!$C$26:$AG$26,1,MATCH($A29,'Monthly_P&L'!$C$3:$AG$3,0)) -> 12859.37 | C29: =INDEX('Monthly_P&L'!$C$48:$AG$48,1,MATCH($A29,'Monthly_P&L'!$C$3:$AG$3,0)) -> 3549.16 | D29: =IF(B29<>0,C29/B29,"") -> 0.27599797
A30: 2021-05 | B30: =INDEX('Monthly_P&L'!$C$26:$AG$26,1,MATCH($A30,'Monthly_P&L'!$C$3:$AG$3,0)) -> 10931.25 | C30: =INDEX('Monthly_P&L'!$C$48:$AG$48,1,MATCH($A30,'Monthly_P&L'!$C$3:$AG$3,0)) -> 2818.92 | D30: =IF(B30<>0,C30/B30,"") -> 0.25787719
A31: 2021-06 | B31: =INDEX('Monthly_P&L'!$C$26:$AG$26,1,MATCH($A31,'Monthly_P&L'!$C$3:$AG$3,0)) -> 9301.25 | C31: =INDEX('Monthly_P&L'!$C$48:$AG$48,1,MATCH($A31,'Monthly_P&L'!$C$3:$AG$3,0)) -> 2407.81 | D31: =IF(B31<>0,C31/B31,"") -> 0.25886951
A32: 2021-07 | B32: =INDEX('Monthly_P&L'!$C$26:$AG$26,1,MATCH($A32,'Monthly_P&L'!$C$3:$AG$3,0)) -> 7027.5 | C32: =INDEX('Monthly_P&L'!$C$48:$AG$48,1,MATCH($A32,'Monthly_P&L'!$C$3:$AG$3,0)) -> 488.32 | D32: =IF(B32<>0,C32/B32,"") -> 0.069487015
... A44: 2022-07 | B44: =INDEX('Monthly_P&L'!$C$26:$AG$26,1,MATCH($A44,'Monthly_P&L'!$C$3:$AG$3,0)) -> 3987.5 | C44: =INDEX('Monthly_P&L'!$C$48:$AG$48,1,MATCH($A44,'Monthly_P&L'!$C$3:$AG$3,0)) -> 1081.6 | D44: =IF(B44<>0,C44/B44,"") -> 0.27124765
A46: 2021 Budget Check
A47: Budget Revenue | B47: Actual Revenue | C47: Revenue Variance | D47: Budget NOI | E47: Actual NOI | F47: NOI Variance | G47: Comment
A48: =Budget_vs_Actual!B17 -> 117700 | B48: =Budget_vs_Actual!C17 -> 120892.1 | C48: =Budget_vs_Actual!D17 -> 3192.1 | D48: =Budget_vs_Actual!H17 -> 29650 | E48: =Budget_vs_Actual!I17 -> 32068.49 | F48: =Budget_vs_Actual!J17 -> 2418.49 | G48: Actual NOI beat budget; expansion was supported by revenue growth.

Sheet Monthly_P&L
A1: Claire Studio — Monthly P&L Statement
A2: Amounts shown in $ | Source: Model_Data | Apr–May 2020 excluded (COVID closure) | Ballet shoes use weighted-average estimated COGS; gymnastic suits use recorded costs
C3: 2019-11 | D3: 2019-12 | E3: 2020-01 | F3: 2020-02 | G3: 2020-03 | H3: 2020-06 | I3: 2020-07 | J3: 2020-08 | K3: 2020-09 | L3: 2020-10 | M3: 2020-11 | N3: 2020-12 | O3: 2021-01 | P3: 2021-02 | Q3: 2021-03 | R3: 2021-04 | S3: 2021-05 | T3: 2021-06 | U3: 2021-07 | V3: 2021-08 | W3: 2021-09 | X3: 2021-10 | Y3: 2021-11 | Z3: 2021-12 | AA3: 2022-01 | AB3: 2022-02 | AC3: 2022-03 | AD3: 2022-04 | AE3: 2022-05 | AF3: 2022-06 | AG3: 2022-07
C4: 2019 | D4: 2019 | E4: 2020 | F4: 2020 | G4: 2020 | H4: 2020 | I4: 2020 | J4: 2020 | K4: 2020 | L4: 2020 | M4: 2020 | N4: 2020 | O4: 2021 | P4: 2021 | Q4: 2021 | R4: 2021 | S4: 2021 | T4: 2021 | U4: 2021 | V4: 2021 | W4: 2021 | X4: 2021 | Y4: 2021 | Z4: 2021 | AA4: 2022 | AB4: 2022 | AC4: 2022 | AD4: 2022 | AE4: 2022 | AF4: 2022 | AG4: 2022 | AH4: TOTAL
C5: Nov | D5: Dec | E5: Jan | F5: Feb | G5: Mar | H5: Jun | I5: Jul | J5: Aug | K5: Sep | L5: Oct | M5: Nov | N5: Dec | O5: Jan | P5: Feb | Q5: Mar | R5: Apr | S5: May | T5: Jun | U5: Jul | V5: Aug | W5: Sep | X5: Oct | Y5: Nov | Z5: Dec | AA5: Jan | AB5: Feb | AC5: Mar | AD5: Apr | AE5: May | AF5: Jun | AG5: Jul | AH5: All Periods
A6: Class Revenue
A7: Choreography | B7: 4000 | C7: =IFERROR(INDEX(Model_Data!$A$4:$AG$34,MATCH(C$3,Model_Data!$A$4:$A$34,0),MATCH("Revenue - Choreography",Model_Data!$A$3:$AG$3,0)),"") -> 1375 | D7: =IFERROR(INDEX(Model_Data!$A$4:$AG$34,MATCH(D$3,Model_Data!$A$4:$A$34,0),MATCH("Revenue - Choreography",Model_Data!$A$3:$AG$3,0)),"") -> 1875 | E7: =IFERROR(INDEX(Model_Data!$A$4:$AG$34,MATCH(E$3,Model_Data!$A$4:$A$34,0),MATCH("Revenue - Choreography",Model_Data!$A$3:$AG$3,0)),"") -> 3237.5 | F7: =IFERROR(INDEX(Model_Data!$A$4:$AG$34,MATCH(F$3,Model_Data!$A$4:$A$34,0),MATCH("Revenue - Choreography",Model_Data!$A$3:$AG$3,0)),"") -> 3162.5 | G7: =IFERROR(INDEX(Model_Data!$A$4:$AG$34,MATCH(G$3,Model_Data!$A$4:$A$34,0),MATCH("Revenue - Choreography",Model_Data!$A$3:$AG$3,0)),"") -> 2775 | H7: =IFERROR(INDEX(Model_Data!$A$4:$AG$34,MATCH(H$3,Model_Data!$A$4:$A$34,0),MATCH("Revenue - Choreography",Model_Data!$A$3:$AG$3,0)),"") -> 3612.5 | I7: =IFERROR(INDEX(Model_Data!$A$4:$AG$34,MATCH(I$3,Model_Data!$A$4:$A$34,0),MATCH("Revenue - Choreography",Model_Data!$A$3:$AG$3,0)),"") -> 3312.5 | J7: =IFERROR(INDEX(Model_Data!$A$4:$AG$34,MATCH(J$3,Model_Data!$A$4:$A$34,0),MATCH("Revenue - Choreography",Model_Data!$A$3:$AG$3,0)),"") -> 3006.25 | ... AG7: =IFERROR(INDEX(Model_Data!$A$4:$AG$34,MATCH(AG$3,Model_Data!$A$4:$A$34,0),MATCH("Revenue - Choreography",Model_Data!$A$3:$AG$3,0)),"") -> 3312.5 | AH7: =SUM(C7:AG7) -> 140806.12
A8: Fitness | B8: 4010 | C8: =IFERROR(INDEX(Model_Data!$A$4:$AG$34,MATCH(C$3,Model_Data!$A$4:$A$34,0),MATCH("Revenue - Fitness",Model_Data!$A$3:$AG$3,0)),"") -> 0 | D8: =IFERROR(INDEX(Model_Data!$A$4:$AG$34,MATCH(D$3,Model_Data!$A$4:$A$34,0),MATCH("Revenue - Fitness",Model_Data!$A$3:$AG$3,0)),"") -> 0 | E8: =IFERROR(INDEX(Model_Data!$A$4:$AG$34,MATCH(E$3,Model_Data!$A$4:$A$34,0),MATCH("Revenue - Fitness",Model_Data!$A$3:$AG$3,0)),"") -> 0 | F8: =IFERROR(INDEX(Model_Data!$A$4:$AG$34,MATCH(F$3,Model_Data!$A$4:$A$34,0),MATCH("Revenue - Fitness",Model_Data!$A$3:$AG$3,0)),"") -> 0 | G8: =IFERROR(INDEX(Model_Data!$A$4:$AG$34,MATCH(G$3,Model_Data!$A$4:$A$34,0),MATCH("Revenue - Fitness",Model_Data!$A$3:$AG$3,0)),"") -> 656.25 | H8: =IFERROR(INDEX(Model_Data!$A$4:$AG$34,MATCH(H$3,Model_Data!$A$4:$A$34,0),MATCH("Revenue - Fitness",Model_Data!$A$3:$AG$3,0)),"") -> 1037.5 | I8: =IFERROR(INDEX(Model_Data!$A$4:$AG$34,MATCH(I$3,Model_Data!$A$4:$A$34,0),MATCH("Revenue - Fitness",Model_Data!$A$3:$AG$3,0)),"") -> 1762.5 | J8: =IFERROR(INDEX(Model_Data!$A$4:$AG$34,MATCH(J$3,Model_Data!$A$4:$A$34,0),MATCH("Revenue - Fitness",Model_Data!$A$3:$AG$3,0)),"") -> 2206.25 | ... AG8: =IFERROR(INDEX(Model_Data!$A$4:$AG$34,MATCH(AG$3,Model_Data!$A$4:$A$34,0),MATCH("Revenue - Fitness",Model_Data!$A$3:$AG$3,0)),"") -> 0 | AH8: =SUM(C8:AG8) -> 37925
A9: Karate | B9: 4020 | C9: =IFERROR(INDEX(Model_Data!$A$4:$AG$34,MATCH(C$3,Model_Data!$A$4:$A$34,0),MATCH("Revenue - Karate",Model_Data!$A$3:$AG$3,0)),"") -> 0 | D9: =IFERROR(INDEX(Model_Data!$A$4:$AG$34,MATCH(D$3,Model_Data!$A$4:$A$34,0),MATCH("Revenue - Karate",Model_Data!$A$3:$AG$3,0)),"") -> 0 | E9: =IFERROR(INDEX(Model_Data!$A$4:$AG$34,MATCH(E$3,Model_Data!$A$4:$A$34,0),MATCH("Revenue - Karate",Model_Data!$A$3:$AG$3,0)),"") -> 0 | F9: =IFERROR(INDEX(Model_Data!$A$4:$AG$34,MATCH(F$3,Model_Data!$A$4:$A$34,0),MATCH("Revenue - Karate",Model_Data!$A$3:$AG$3,0)),"") -> 0 | G9: =IFERROR(INDEX(Model_Data!$A$4:$AG$34,MATCH(G$3,Model_Data!$A$4:$A$34,0),MATCH("Revenue - Karate",Model_Data!$A$3:$AG$3,0)),"") -> 0 | H9: =IFERROR(INDEX(Model_Data!$A$4:$AG$34,MATCH(H$3,Model_Data!$A$4:$A$34,0),MATCH("Revenue - Karate",Model_Data!$A$3:$AG$3,0)),"") -> 0 | I9: =IFERROR(INDEX(Model_Data!$A$4:$AG$34,MATCH(I$3,Model_Data!$A$4:$A$34,0),MATCH("Revenue - Karate",Model_Data!$A$3:$AG$3,0)),"") -> 0 | J9: =IFERROR(INDEX(Model_Data!$A$4:$AG$34,MATCH(J$3,Model_Data!$A$4:$A$34,0),MATCH("Revenue - Karate",Model_Data!$A$3:$AG$3,0)),"") -> 0 | ... AG9: =IFERROR(INDEX(Model_Data!$A$4:$AG$34,MATCH(AG$3,Model_Data!$A$4:$A$34,0),MATCH("Revenue - Karate",Model_Data!$A$3:$AG$3,0)),"") -> 625 | AH9: =SUM(C9:AG9) -> 58418.75
A10: Gymnastics | B10: 4030 | C10: =IFERROR(INDEX(Model_Data!$A$4:$AG$34,MATCH(C$3,Model_Data!$A$4:$A$34,0),MATCH("Revenue - Gymnastics",Model_Data!$A$3:$AG$3,0)),"") -> 300 | D10: =IFERROR(INDEX(Model_Data!$A$4:$AG$34,MATCH(D$3,Model_Data!$A$4:$A$34,0),MATCH("Revenue - Gymnastics",Model_Data!$A$3:$AG$3,0)),"") -> 900 | E10: =IFERROR(INDEX(Model_Data!$A$4:$AG$34,MATCH(E$3,Model_Data!$A$4:$A$34,0),MATCH("Revenue - Gymnastics",Model_Data!$A$3:$AG$3,0)),"") -> 1437.5 | F10: =IFERROR(INDEX(Model_Data!$A$4:$AG$34,MATCH(F$3,Model_Data!$A$4:$A$34,0),MATCH("Revenue - Gymnastics",Model_Data!$A$3:$AG$3,0)),"") -> 1075 | G10: =IFERROR(INDEX(Model_Data!$A$4:$AG$34,MATCH(G$3,Model_Data!$A$4:$A$34,0),MATCH("Revenue - Gymnastics",Model_Data!$A$3:$AG$3,0)),"") -> 1475 | H10: =IFERROR(INDEX(Model_Data!$A$4:$AG$34,MATCH(H$3,Model_Data!$A$4:$A$34,0),MATCH("Revenue - Gymnastics",Model_Data!$A$3:$AG$3,0)),"") -> 593.75 | I10: =IFERROR(INDEX(Model_Data!$A$4:$AG$34,MATCH(I$3,Model_Data!$A$4:$A$34,0),MATCH("Revenue - Gymnastics",Model_Data!$A$3:$AG$3,0)),"") -> 1162.5 | J10: =IFERROR(INDEX(Model_Data!$A$4:$AG$34,MATCH(J$3,Model_Data!$A$4:$A$34,0),MATCH("Revenue - Gymnastics",Model_Data!$A$3:$AG$3,0)),"") -> 875 | ... AG10: =IFERROR(INDEX(Model_Data!$A$4:$AG$34,MATCH(AG$3,Model_Data!$A$4:$A$34,0),MATCH("Revenue - Gymnastics",Model_Data!$A$3:$AG$3,0)),"") -> 0 | AH10: =SUM(C10:AG10) -> 7818.75
A11: Total Class Revenue | C11: =SUM(C7:C10) -> 1675 | D11: =SUM(D7:D10) -> 2775 | E11: =SUM(E7:E10) -> 4675 | F11: =SUM(F7:F10) -> 4237.5 | G11: =SUM(G7:G10) -> 4906.25 | H11: =SUM(H7:H10) -> 5243.75 | I11: =SUM(I7:I10) -> 6237.5 | J11: =SUM(J7:J10) -> 6087.5 | ... AH11: =SUM(AH7:AH10) -> 244968.62
A13: Merchandise Revenue
A14: Ballet Shoes | B14: 4060a | C14: =IFERROR(INDEX(Model_Data!$A$4:$AG$34,MATCH(C$3,Model_Data!$A$4:$A$34,0),MATCH("Revenue - Ballet Shoes",Model_Data!$A$3:$AG$3,0)),"") -> 0 | D14: =IFERROR(INDEX(Model_Data!$A$4:$AG$34,MATCH(D$3,Model_Data!$A$4:$A$34,0),MATCH("Revenue - Ballet Shoes",Model_Data!$A$3:$AG$3,0)),"") -> 0 | E14: =IFERROR(INDEX(Model_Data!$A$4:$AG$34,MATCH(E$3,Model_Data!$A$4:$A$34,0),MATCH("Revenue - Ballet Shoes",Model_Data!$A$3:$AG$3,0)),"") -> 225 | F14: =IFERROR(INDEX(Model_Data!$A$4:$AG$34,MATCH(F$3,Model_Data!$A$4:$A$34,0),MATCH("Revenue - Ballet Shoes",Model_Data!$A$3:$AG$3,0)),"") -> 50 | G14: =IFERROR(INDEX(Model_Data!$A$4:$AG$34,MATCH(G$3,Model_Data!$A$4:$A$34,0),MATCH("Revenue - Ballet Shoes",Model_Data!$A$3:$AG$3,0)),"") -> 50 | H14: =IFERROR(INDEX(Model_Data!$A$4:$AG$34,MATCH(H$3,Model_Data!$A$4:$A$34,0),MATCH("Revenue - Ballet Shoes",Model_Data!$A$3:$AG$3,0)),"") -> 0 | I14: =IFERROR(INDEX(Model_Data!$A$4:$AG$34,MATCH(I$3,Model_Data!$A$4:$A$34,0),MATCH("Revenue - Ballet Shoes",Model_Data!$A$3:$AG$3,0)),"") -> 87.5 | J14: =IFERROR(INDEX(Model_Data!$A$4:$AG$34,MATCH(J$3,Model_Data!$A$4:$A$34,0),MATCH("Revenue - Ballet Shoes",Model_Data!$A$3:$AG$3,0)),"") -> 0 | ... AG14: =IFERROR(INDEX(Model_Data!$A$4:$AG$34,MATCH(AG$3,Model_Data!$A$4:$A$34,0),MATCH("Revenue - Ballet Shoes",Model_Data!$A$3:$AG$3,0)),"") -> 0 | AH14: =SUM(C14:AG14) -> 1651.25
A15: Gymnastic Suits | B15: 4060b | C15: =IFERROR(INDEX(Model_Data!$A$4:$AG$34,MATCH(C$3,Model_Data!$A$4:$A$34,0),MATCH("Revenue - Gymnastic Suits",Model_Data!$A$3:$AG$3,0)),"") -> 0 | D15: =IFERROR(INDEX(Model_Data!$A$4:$AG$34,MATCH(D$3,Model_Data!$A$4:$A$34,0),MATCH("Revenue - Gymnastic Suits",Model_Data!$A$3:$AG$3,0)),"") -> 0 | E15: =IFERROR(INDEX(Model_Data!$A$4:$AG$34,MATCH(E$3,Model_Data!$A$4:$A$34,0),MATCH("Revenue - Gymnastic Suits",Model_Data!$A$3:$AG$3,0)),"") -> 375 | F15: =IFERROR(INDEX(Model_Data!$A$4:$AG$34,MATCH(F$3,Model_Data!$A$4:$A$34,0),MATCH("Revenue - Gymnastic Suits",Model_Data!$A$3:$AG$3,0)),"") -> 250 | G15: =IFERROR(INDEX(Model_Data!$A$4:$AG$34,MATCH(G$3,Model_Data!$A$4:$A$34,0),MATCH("Revenue - Gymnastic Suits",Model_Data!$A$3:$AG$3,0)),"") -> 312.5 | H15: =IFERROR(INDEX(Model_Data!$A$4:$AG$34,MATCH(H$3,Model_Data!$A$4:$A$34,0),MATCH("Revenue - Gymnastic Suits",Model_Data!$A$3:$AG$3,0)),"") -> 0 | I15: =IFERROR(INDEX(Model_Data!$A$4:$AG$34,MATCH(I$3,Model_Data!$A$4:$A$34,0),MATCH("Revenue - Gymnastic Suits",Model_Data!$A$3:$AG$3,0)),"") -> 0 | J15: =IFERROR(INDEX(Model_Data!$A$4:$AG$34,MATCH(J$3,Model_Data!$A$4:$A$34,0),MATCH("Revenue - Gymnastic Suits",Model_Data!$A$3:$AG$3,0)),"") -> 243.75 | ... AG15: =IFERROR(INDEX(Model_Data!$A$4:$AG$34,MATCH(AG$3,Model_Data!$A$4:$A$34,0),MATCH("Revenue - Gymnastic Suits",Model_Data!$A$3:$AG$3,0)),"") -> 0 | AH15: =SUM(C15:AG15) -> 4568.75
A16: Merchandise — Other | B16: 4060c | C16: =IFERROR(INDEX(Model_Data!$A$4:$AG$34,MATCH(C$3,Model_Data!$A$4:$A$34,0),MATCH("Revenue - Merchandise - Other",Model_Data!$A$3:$AG$3,0)),"") -> 0 | D16: =IFERROR(INDEX(Model_Data!$A$4:$AG$34,MATCH(D$3,Model_Data!$A$4:$A$34,0),MATCH("Revenue - Merchandise - Other",Model_Data!$A$3:$AG$3,0)),"") -> 0 | E16: =IFERROR(INDEX(Model_Data!$A$4:$AG$34,MATCH(E$3,Model_Data!$A$4:$A$34,0),MATCH("Revenue - Merchandise - Other",Model_Data!$A$3:$AG$3,0)),"") -> 0 | F16: =IFERROR(INDEX(Model_Data!$A$4:$AG$34,MATCH(F$3,Model_Data!$A$4:$A$34,0),MATCH("Revenue - Merchandise - Other",Model_Data!$A$3:$AG$3,0)),"") -> 0 | G16: =IFERROR(INDEX(Model_Data!$A$4:$AG$34,MATCH(G$3,Model_Data!$A$4:$A$34,0),MATCH("Revenue - Merchandise - Other",Model_Data!$A$3:$AG$3,0)),"") -> 0 | H16: =IFERROR(INDEX(Model_Data!$A$4:$AG$34,MATCH(H$3,Model_Data!$A$4:$A$34,0),MATCH("Revenue - Merchandise - Other",Model_Data!$A$3:$AG$3,0)),"") -> 0 | I16: =IFERROR(INDEX(Model_Data!$A$4:$AG$34,MATCH(I$3,Model_Data!$A$4:$A$34,0),MATCH("Revenue - Merchandise - Other",Model_Data!$A$3:$AG$3,0)),"") -> 0 | J16: =IFERROR(INDEX(Model_Data!$A$4:$AG$34,MATCH(J$3,Model_Data!$A$4:$A$34,0),MATCH("Revenue - Merchandise - Other",Model_Data!$A$3:$AG$3,0)),"") -> 0 | ... AG16: =IFERROR(INDEX(Model_Data!$A$4:$AG$34,MATCH(AG$3,Model_Data!$A$4:$A$34,0),MATCH("Revenue - Merchandise - Other",Model_Data!$A$3:$AG$3,0)),"") -> 0 | AH16: =SUM(C16:AG16) -> 0
A17: Total Merchandise Revenue | C17: =SUM(C14:C16) -> 0 | D17: =SUM(D14:D16) -> 0 | E17: =SUM(E14:E16) -> 600 | F17: =SUM(F14:F16) -> 300 | G17: =SUM(G14:G16) -> 362.5 | H17: =SUM(H14:H16) -> 0 | I17: =SUM(I14:I16) -> 87.5 | J17: =SUM(J14:J16) -> 243.75 | ... AH17: =SUM(AH14:AH16) -> 6220
A19: Other Revenue
A20: Hall Rental | B20: 4040 | C20: =IFERROR(INDEX(Model_Data!$A$4:$AG$34,MATCH(C$3,Model_Data!$A$4:$A$34,0),MATCH("Revenue - Hall Rental Income",Model_Data!$A$3:$AG$3,0)),"") -> 0 | D20: =IFERROR(INDEX(Model_Data!$A$4:$AG$34,MATCH(D$3,Model_Data!$A$4:$A$34,0),MATCH("Revenue - Hall Rental Income",Model_Data!$A$3:$AG$3,0)),"") -> 0 | E20: =IFERROR(INDEX(Model_Data!$A$4:$AG$34,MATCH(E$3,Model_Data!$A$4:$A$34,0),MATCH("Revenue - Hall Rental Income",Model_Data!$A$3:$AG$3,0)),"") -> 0 | F20: =IFERROR(INDEX(Model_Data!$A$4:$AG$34,MATCH(F$3,Model_Data!$A$4:$A$34,0),MATCH("Revenue - Hall Rental Income",Model_Data!$A$3:$AG$3,0)),"") -> 0 | G20: =IFERROR(INDEX(Model_Data!$A$4:$AG$34,MATCH(G$3,Model_Data!$A$4:$A$34,0),MATCH("Revenue - Hall Rental Income",Model_Data!$A$3:$AG$3,0)),"") -> 0 | H20: =IFERROR(INDEX(Model_Data!$A$4:$AG$34,MATCH(H$3,Model_Data!$A$4:$A$34,0),MATCH("Revenue - Hall Rental Income",Model_Data!$A$3:$AG$3,0)),"") -> 0 | I20: =IFERROR(INDEX(Model_Data!$A$4:$AG$34,MATCH(I$3,Model_Data!$A$4:$A$34,0),MATCH("Revenue - Hall Rental Income",Model_Data!$A$3:$AG$3,0)),"") -> 0 | J20: =IFERROR(INDEX(Model_Data!$A$4:$AG$34,MATCH(J$3,Model_Data!$A$4:$A$34,0),MATCH("Revenue - Hall Rental Income",Model_Data!$A$3:$AG$3,0)),"") -> 0 | ... AG20: =IFERROR(INDEX(Model_Data!$A$4:$AG$34,MATCH(AG$3,Model_Data!$A$4:$A$34,0),MATCH("Revenue - Hall Rental Income",Model_Data!$A$3:$AG$3,0)),"") -> 50 | AH20: =SUM(C20:AG20) -> 20166.62
A21: Utilities Reimb. | B21: 4050 | C21: =IFERROR(INDEX(Model_Data!$A$4:$AG$34,MATCH(C$3,Model_Data!$A$4:$A$34,0),MATCH("Revenue - Utilities Reimbursement",Model_Data!$A$3:$AG$3,0)),"") -> 0 | D21: =IFERROR(INDEX(Model_Data!$A$4:$AG$34,MATCH(D$3,Model_Data!$A$4:$A$34,0),MATCH("Revenue - Utilities Reimbursement",Model_Data!$A$3:$AG$3,0)),"") -> 0 | E21: =IFERROR(INDEX(Model_Data!$A$4:$AG$34,MATCH(E$3,Model_Data!$A$4:$A$34,0),MATCH("Revenue - Utilities Reimbursement",Model_Data!$A$3:$AG$3,0)),"") -> 0 | F21: =IFERROR(INDEX(Model_Data!$A$4:$AG$34,MATCH(F$3,Model_Data!$A$4:$A$34,0),MATCH("Revenue - Utilities Reimbursement",Model_Data!$A$3:$AG$3,0)),"") -> 0 | G21: =IFERROR(INDEX(Model_Data!$A$4:$AG$34,MATCH(G$3,Model_Data!$A$4:$A$34,0),MATCH("Revenue - Utilities Reimbursement",Model_Data!$A$3:$AG$3,0)),"") -> 0 | H21: =IFERROR(INDEX(Model_Data!$A$4:$AG$34,MATCH(H$3,Model_Data!$A$4:$A$34,0),MATCH("Revenue - Utilities Reimbursement",Model_Data!$A$3:$AG$3,0)),"") -> 0 | I21: =IFERROR(INDEX(Model_Data!$A$4:$AG$34,MATCH(I$3,Model_Data!$A$4:$A$34,0),MATCH("Revenue - Utilities Reimbursement",Model_Data!$A$3:$AG$3,0)),"") -> 0 | J21: =IFERROR(INDEX(Model_Data!$A$4:$AG$34,MATCH(J$3,Model_Data!$A$4:$A$34,0),MATCH("Revenue - Utilities Reimbursement",Model_Data!$A$3:$AG$3,0)),"") -> 0 | ... AG21: =IFERROR(INDEX(Model_Data!$A$4:$AG$34,MATCH(AG$3,Model_Data!$A$4:$A$34,0),MATCH("Revenue - Utilities Reimbursement",Model_Data!$A$3:$AG$3,0)),"") -> 0 | AH21: =SUM(C21:AG21) -> 193.75
A22: Events & Photos | B22: 4070 | C22: =IFERROR(INDEX(Model_Data!$A$4:$AG$34,MATCH(C$3,Model_Data!$A$4:$A$34,0),MATCH("Revenue - Event / Photo Revenue",Model_Data!$A$3:$AG$3,0)),"") -> 0 | D22: =IFERROR(INDEX(Model_Data!$A$4:$AG$34,MATCH(D$3,Model_Data!$A$4:$A$34,0),MATCH("Revenue - Event / Photo Revenue",Model_Data!$A$3:$AG$3,0)),"") -> 0 | E22: =IFERROR(INDEX(Model_Data!$A$4:$AG$34,MATCH(E$3,Model_Data!$A$4:$A$34,0),MATCH("Revenue - Event / Photo Revenue",Model_Data!$A$3:$AG$3,0)),"") -> 0 | F22: =IFERROR(INDEX(Model_Data!$A$4:$AG$34,MATCH(F$3,Model_Data!$A$4:$A$34,0),MATCH("Revenue - Event / Photo Revenue",Model_Data!$A$3:$AG$3,0)),"") -> 0 | G22: =IFERROR(INDEX(Model_Data!$A$4:$AG$34,MATCH(G$3,Model_Data!$A$4:$A$34,0),MATCH("Revenue - Event / Photo Revenue",Model_Data!$A$3:$AG$3,0)),"") -> 0 | H22: =IFERROR(INDEX(Model_Data!$A$4:$AG$34,MATCH(H$3,Model_Data!$A$4:$A$34,0),MATCH("Revenue - Event / Photo Revenue",Model_Data!$A$3:$AG$3,0)),"") -> 0 | I22: =IFERROR(INDEX(Model_Data!$A$4:$AG$34,MATCH(I$3,Model_Data!$A$4:$A$34,0),MATCH("Revenue - Event / Photo Revenue",Model_Data!$A$3:$AG$3,0)),"") -> 0 | J22: =IFERROR(INDEX(Model_Data!$A$4:$AG$34,MATCH(J$3,Model_Data!$A$4:$A$34,0),MATCH("Revenue - Event / Photo Revenue",Model_Data!$A$3:$AG$3,0)),"") -> 0 | ... AG22: =IFERROR(INDEX(Model_Data!$A$4:$AG$34,MATCH(AG$3,Model_Data!$A$4:$A$34,0),MATCH("Revenue - Event / Photo Revenue",Model_Data!$A$3:$AG$3,0)),"") -> 0 | AH22: =SUM(C22:AG22) -> 1490.74
A23: Other | B23: 4080 | C23: =IFERROR(INDEX(Model_Data!$A$4:$AG$34,MATCH(C$3,Model_Data!$A$4:$A$34,0),MATCH("Revenue - Other",Model_Data!$A$3:$AG$3,0)),"") -> 125 | D23: =IFERROR(INDEX(Model_Data!$A$4:$AG$34,MATCH(D$3,Model_Data!$A$4:$A$34,0),MATCH("Revenue - Other",Model_Data!$A$3:$AG$3,0)),"") -> 0 | E23: =IFERROR(INDEX(Model_Data!$A$4:$AG$34,MATCH(E$3,Model_Data!$A$4:$A$34,0),MATCH("Revenue - Other",Model_Data!$A$3:$AG$3,0)),"") -> 200 | F23: =IFERROR(INDEX(Model_Data!$A$4:$AG$34,MATCH(F$3,Model_Data!$A$4:$A$34,0),MATCH("Revenue - Other",Model_Data!$A$3:$AG$3,0)),"") -> 400 | G23: =IFERROR(INDEX(Model_Data!$A$4:$AG$34,MATCH(G$3,Model_Data!$A$4:$A$34,0),MATCH("Revenue - Other",Model_Data!$A$3:$AG$3,0)),"") -> 0 | H23: =IFERROR(INDEX(Model_Data!$A$4:$AG$34,MATCH(H$3,Model_Data!$A$4:$A$34,0),MATCH("Revenue - Other",Model_Data!$A$3:$AG$3,0)),"") -> 0 | I23: =IFERROR(INDEX(Model_Data!$A$4:$AG$34,MATCH(I$3,Model_Data!$A$4:$A$34,0),MATCH("Revenue - Other",Model_Data!$A$3:$AG$3,0)),"") -> 225 | J23: =IFERROR(INDEX(Model_Data!$A$4:$AG$34,MATCH(J$3,Model_Data!$A$4:$A$34,0),MATCH("Revenue - Other",Model_Data!$A$3:$AG$3,0)),"") -> 12.5 | ... AG23: =IFERROR(INDEX(Model_Data!$A$4:$AG$34,MATCH(AG$3,Model_Data!$A$4:$A$34,0),MATCH("Revenue - Other",Model_Data!$A$3:$AG$3,0)),"") -> 0 | AH23: =SUM(C23:AG23) -> 2296.75
A24: Total Other Revenue | C24: =SUM(C20:C23) -> 125 | D24: =SUM(D20:D23) -> 0 | E24: =SUM(E20:E23) -> 200 | F24: =SUM(F20:F23) -> 400 | G24: =SUM(G20:G23) -> 0 | H24: =SUM(H20:H23) -> 0 | I24: =SUM(I20:I23) -> 225 | J24: =SUM(J20:J23) -> 12.5 | ... AH24: =SUM(AH20:AH23) -> 24147.86
A26: TOTAL REVENUE | C26: =SUM(C11,C17,C24) -> 1800 | D26: =SUM(D11,D17,D24) -> 2775 | E26: =SUM(E11,E17,E24) -> 5475 | F26: =SUM(F11,F17,F24) -> 4937.5 | G26: =SUM(G11,G17,G24) -> 5268.75 | H26: =SUM(H11,H17,H24) -> 5243.75 | I26: =SUM(I11,I17,I24) -> 6550 | J26: =SUM(J11,J17,J24) -> 6343.75 | ... AH26: =SUM(AH11,AH17,AH24) -> 275336.48
A28: Cost of Goods Sold (inventory items only)
A29: Ballet Shoes — COGS | B29: 5050 | C29: =IFERROR(INDEX(Model_Data!$A$4:$AG$34,MATCH(C$3,Model_Data!$A$4:$A$34,0),MATCH("Expense - Ballet Shoe Cost",Model_Data!$A$3:$AG$3,0)),"") -> 0 | D29: =IFERROR(INDEX(Model_Data!$A$4:$AG$34,MATCH(D$3,Model_Data!$A$4:$A$34,0),MATCH("Expense - Ballet Shoe Cost",Model_Data!$A$3:$AG$3,0)),"") -> 0 | E29: =IFERROR(INDEX(Model_Data!$A$4:$AG$34,MATCH(E$3,Model_Data!$A$4:$A$34,0),MATCH("Expense - Ballet Shoe Cost",Model_Data!$A$3:$AG$3,0)),"") -> 146.99 | F29: =IFERROR(INDEX(Model_Data!$A$4:$AG$34,MATCH(F$3,Model_Data!$A$4:$A$34,0),MATCH("Expense - Ballet Shoe Cost",Model_Data!$A$3:$AG$3,0)),"") -> 32.66 | G29: =IFERROR(INDEX(Model_Data!$A$4:$AG$34,MATCH(G$3,Model_Data!$A$4:$A$34,0),MATCH("Expense - Ballet Shoe Cost",Model_Data!$A$3:$AG$3,0)),"") -> 32.66 | H29: =IFERROR(INDEX(Model_Data!$A$4:$AG$34,MATCH(H$3,Model_Data!$A$4:$A$34,0),MATCH("Expense - Ballet Shoe Cost",Model_Data!$A$3:$AG$3,0)),"") -> 0 | I29: =IFERROR(INDEX(Model_Data!$A$4:$AG$34,MATCH(I$3,Model_Data!$A$4:$A$34,0),MATCH("Expense - Ballet Shoe Cost",Model_Data!$A$3:$AG$3,0)),"") -> 57.16 | J29: =IFERROR(INDEX(Model_Data!$A$4:$AG$34,MATCH(J$3,Model_Data!$A$4:$A$34,0),MATCH("Expense - Ballet Shoe Cost",Model_Data!$A$3:$AG$3,0)),"") -> 0 | ... AG29: =IFERROR(INDEX(Model_Data!$A$4:$AG$34,MATCH(AG$3,Model_Data!$A$4:$A$34,0),MATCH("Expense - Ballet Shoe Cost",Model_Data!$A$3:$AG$3,0)),"") -> 0 | AH29: =SUM(C29:AG29) -> 1078.75
A30: Gymnastic Suits — COGS | B30: 5010 | C30: =IFERROR(INDEX(Model_Data!$A$4:$AG$34,MATCH(C$3,Model_Data!$A$4:$A$34,0),MATCH("Expense - Gymnastic Suit Cost",Model_Data!$A$3:$AG$3,0)),"") -> 0 | D30: =IFERROR(INDEX(Model_Data!$A$4:$AG$34,MATCH(D$3,Model_Data!$A$4:$A$34,0),MATCH("Expense - Gymnastic Suit Cost",Model_Data!$A$3:$AG$3,0)),"") -> 0 | E30: =IFERROR(INDEX(Model_Data!$A$4:$AG$34,MATCH(E$3,Model_Data!$A$4:$A$34,0),MATCH("Expense - Gymnastic Suit Cost",Model_Data!$A$3:$AG$3,0)),"") -> 234.38 | F30: =IFERROR(INDEX(Model_Data!$A$4:$AG$34,MATCH(F$3,Model_Data!$A$4:$A$34,0),MATCH("Expense - Gymnastic Suit Cost",Model_Data!$A$3:$AG$3,0)),"") -> 0 | G30: =IFERROR(INDEX(Model_Data!$A$4:$AG$34,MATCH(G$3,Model_Data!$A$4:$A$34,0),MATCH("Expense - Gymnastic Suit Cost",Model_Data!$A$3:$AG$3,0)),"") -> 81.25 | H30: =IFERROR(INDEX(Model_Data!$A$4:$AG$34,MATCH(H$3,Model_Data!$A$4:$A$34,0),MATCH("Expense - Gymnastic Suit Cost",Model_Data!$A$3:$AG$3,0)),"") -> 0 | I30: =IFERROR(INDEX(Model_Data!$A$4:$AG$34,MATCH(I$3,Model_Data!$A$4:$A$34,0),MATCH("Expense - Gymnastic Suit Cost",Model_Data!$A$3:$AG$3,0)),"") -> 531.25 | J30: =IFERROR(INDEX(Model_Data!$A$4:$AG$34,MATCH(J$3,Model_Data!$A$4:$A$34,0),MATCH("Expense - Gymnastic Suit Cost",Model_Data!$A$3:$AG$3,0)),"") -> 0 | ... AG30: =IFERROR(INDEX(Model_Data!$A$4:$AG$34,MATCH(AG$3,Model_Data!$A$4:$A$34,0),MATCH("Expense - Gymnastic Suit Cost",Model_Data!$A$3:$AG$3,0)),"") -> 0 | AH30: =SUM(C30:AG30) -> 3134.38
A31: Total COGS | C31: =SUM(C29:C30) -> 0 | D31: =SUM(D29:D30) -> 0 | E31: =SUM(E29:E30) -> 381.37 | F31: =SUM(F29:F30) -> 32.66 | G31: =SUM(G29:G30) -> 113.91 | H31: =SUM(H29:H30) -> 0 | I31: =SUM(I29:I30) -> 588.41 | J31: =SUM(J29:J30) -> 0 | ... AH31: =SUM(AH29:AH30) -> 4213.13
A33: Cost of Services
A34: Payroll — Co-Founder salary + Karate Instructor rev share + substitutes | B34: 5000 | C34: =IFERROR(INDEX(Model_Data!$A$4:$AG$34,MATCH(C$3,Model_Data!$A$4:$A$34,0),MATCH("Expense - Payroll",Model_Data!$A$3:$AG$3,0)),"") -> 0 | D34: =IFERROR(INDEX(Model_Data!$A$4:$AG$34,MATCH(D$3,Model_Data!$A$4:$A$34,0),MATCH("Expense - Payroll",Model_Data!$A$3:$AG$3,0)),"") -> 0 | E34: =IFERROR(INDEX(Model_Data!$A$4:$AG$34,MATCH(E$3,Model_Data!$A$4:$A$34,0),MATCH("Expense - Payroll",Model_Data!$A$3:$AG$3,0)),"") -> 462.5 | F34: =IFERROR(INDEX(Model_Data!$A$4:$AG$34,MATCH(F$3,Model_Data!$A$4:$A$34,0),MATCH("Expense - Payroll",Model_Data!$A$3:$AG$3,0)),"") -> 412.5 | G34: =IFERROR(INDEX(Model_Data!$A$4:$AG$34,MATCH(G$3,Model_Data!$A$4:$A$34,0),MATCH("Expense - Payroll",Model_Data!$A$3:$AG$3,0)),"") -> 150 | H34: =IFERROR(INDEX(Model_Data!$A$4:$AG$34,MATCH(H$3,Model_Data!$A$4:$A$34,0),MATCH("Expense - Payroll",Model_Data!$A$3:$AG$3,0)),"") -> 625 | I34: =IFERROR(INDEX(Model_Data!$A$4:$AG$34,MATCH(I$3,Model_Data!$A$4:$A$34,0),MATCH("Expense - Payroll",Model_Data!$A$3:$AG$3,0)),"") -> 862.5 | J34: =IFERROR(INDEX(Model_Data!$A$4:$AG$34,MATCH(J$3,Model_Data!$A$4:$A$34,0),MATCH("Expense - Payroll",Model_Data!$A$3:$AG$3,0)),"") -> 750 | ... AG34: =IFERROR(INDEX(Model_Data!$A$4:$AG$34,MATCH(AG$3,Model_Data!$A$4:$A$34,0),MATCH("Expense - Payroll",Model_Data!$A$3:$AG$3,0)),"") -> 0 | AH34: =SUM(C34:AG34) -> 41095.62
A35: Class Supplies | B35: 5030 | C35: =IFERROR(INDEX(Model_Data!$A$4:$AG$34,MATCH(C$3,Model_Data!$A$4:$A$34,0),MATCH("Expense - Class Supplies",Model_Data!$A$3:$AG$3,0)),"") -> 0 | D35: =IFERROR(INDEX(Model_Data!$A$4:$AG$34,MATCH(D$3,Model_Data!$A$4:$A$34,0),MATCH("Expense - Class Supplies",Model_Data!$A$3:$AG$3,0)),"") -> 0 | E35: =IFERROR(INDEX(Model_Data!$A$4:$AG$34,MATCH(E$3,Model_Data!$A$4:$A$34,0),MATCH("Expense - Class Supplies",Model_Data!$A$3:$AG$3,0)),"") -> 0 | F35: =IFERROR(INDEX(Model_Data!$A$4:$AG$34,MATCH(F$3,Model_Data!$A$4:$A$34,0),MATCH("Expense - Class Supplies",Model_Data!$A$3:$AG$3,0)),"") -> 50 | G35: =IFERROR(INDEX(Model_Data!$A$4:$AG$34,MATCH(G$3,Model_Data!$A$4:$A$34,0),MATCH("Expense - Class Supplies",Model_Data!$A$3:$AG$3,0)),"") -> 131.25 | H35: =IFERROR(INDEX(Model_Data!$A$4:$AG$34,MATCH(H$3,Model_Data!$A$4:$A$34,0),MATCH("Expense - Class Supplies",Model_Data!$A$3:$AG$3,0)),"") -> 0 | I35: =IFERROR(INDEX(Model_Data!$A$4:$AG$34,MATCH(I$3,Model_Data!$A$4:$A$34,0),MATCH("Expense - Class Supplies",Model_Data!$A$3:$AG$3,0)),"") -> 0 | J35: =IFERROR(INDEX(Model_Data!$A$4:$AG$34,MATCH(J$3,Model_Data!$A$4:$A$34,0),MATCH("Expense - Class Supplies",Model_Data!$A$3:$AG$3,0)),"") -> 87.5 | ... AG35: =IFERROR(INDEX(Model_Data!$A$4:$AG$34,MATCH(AG$3,Model_Data!$A$4:$A$34,0),MATCH("Expense - Class Supplies",Model_Data!$A$3:$AG$3,0)),"") -> 0 | AH35: =SUM(C35:AG35) -> 775
A36: Event & Competition Costs | B36: 5040 | C36: =IFERROR(INDEX(Model_Data!$A$4:$AG$34,MATCH(C$3,Model_Data!$A$4:$A$34,0),MATCH("Expense - Events and Competitions",Model_Data!$A$3:$AG$3,0)),"") -> 0 | D36: =IFERROR(INDEX(Model_Data!$A$4:$AG$34,MATCH(D$3,Model_Data!$A$4:$A$34,0),MATCH("Expense - Events and Competitions",Model_Data!$A$3:$AG$3,0)),"") -> 0 | E36: =IFERROR(INDEX(Model_Data!$A$4:$AG$34,MATCH(E$3,Model_Data!$A$4:$A$34,0),MATCH("Expense - Events and Competitions",Model_Data!$A$3:$AG$3,0)),"") -> 0 | F36: =IFERROR(INDEX(Model_Data!$A$4:$AG$34,MATCH(F$3,Model_Data!$A$4:$A$34,0),MATCH("Expense - Events and Competitions",Model_Data!$A$3:$AG$3,0)),"") -> 0 | G36: =IFERROR(INDEX(Model_Data!$A$4:$AG$34,MATCH(G$3,Model_Data!$A$4:$A$34,0),MATCH("Expense - Events and Competitions",Model_Data!$A$3:$AG$3,0)),"") -> 0 | H36: =IFERROR(INDEX(Model_Data!$A$4:$AG$34,MATCH(H$3,Model_Data!$A$4:$A$34,0),MATCH("Expense - Events and Competitions",Model_Data!$A$3:$AG$3,0)),"") -> 0 | I36: =IFERROR(INDEX(Model_Data!$A$4:$AG$34,MATCH(I$3,Model_Data!$A$4:$A$34,0),MATCH("Expense - Events and Competitions",Model_Data!$A$3:$AG$3,0)),"") -> 0 | J36: =IFERROR(INDEX(Model_Data!$A$4:$AG$34,MATCH(J$3,Model_Data!$A$4:$A$34,0),MATCH("Expense - Events and Competitions",Model_Data!$A$3:$AG$3,0)),"") -> 0 | ... AG36: =IFERROR(INDEX(Model_Data!$A$4:$AG$34,MATCH(AG$3,Model_Data!$A$4:$A$34,0),MATCH("Expense - Events and Competitions",Model_Data!$A$3:$AG$3,0)),"") -> 0 | AH36: =SUM(C36:AG36) -> 197.25
A37: Total Cost of Services | C37: =SUM(C34:C36) -> 0 | D37: =SUM(D34:D36) -> 0 | E37: =SUM(E34:E36) -> 462.5 | F37: =SUM(F34:F36) -> 462.5 | G37: =SUM(G34:G36) -> 281.25 | H37: =SUM(H34:H36) -> 625 | I37: =SUM(I34:I36) -> 862.5 | J37: =SUM(J34:J36) -> 837.5 | ... AH37: =SUM(AH34:AH36) -> 42067.87
A39: Operating Expenses
A40: Rent | B40: 6000 | C40: =IFERROR(INDEX(Model_Data!$A$4:$AG$34,MATCH(C$3,Model_Data!$A$4:$A$34,0),MATCH("Expense - Rent",Model_Data!$A$3:$AG$3,0)),"") -> 0 | D40: =IFERROR(INDEX(Model_Data!$A$4:$AG$34,MATCH(D$3,Model_Data!$A$4:$A$34,0),MATCH("Expense - Rent",Model_Data!$A$3:$AG$3,0)),"") -> 2775 | E40: =IFERROR(INDEX(Model_Data!$A$4:$AG$34,MATCH(E$3,Model_Data!$A$4:$A$34,0),MATCH("Expense - Rent",Model_Data!$A$3:$AG$3,0)),"") -> 2800 | F40: =IFERROR(INDEX(Model_Data!$A$4:$AG$34,MATCH(F$3,Model_Data!$A$4:$A$34,0),MATCH("Expense - Rent",Model_Data!$A$3:$AG$3,0)),"") -> 2800 | G40: =IFERROR(INDEX(Model_Data!$A$4:$AG$34,MATCH(G$3,Model_Data!$A$4:$A$34,0),MATCH("Expense - Rent",Model_Data!$A$3:$AG$3,0)),"") -> 2800 | H40: =IFERROR(INDEX(Model_Data!$A$4:$AG$34,MATCH(H$3,Model_Data!$A$4:$A$34,0),MATCH("Expense - Rent",Model_Data!$A$3:$AG$3,0)),"") -> 1401.38 | I40: =IFERROR(INDEX(Model_Data!$A$4:$AG$34,MATCH(I$3,Model_Data!$A$4:$A$34,0),MATCH("Expense - Rent",Model_Data!$A$3:$AG$3,0)),"") -> 1401.38 | J40: =IFERROR(INDEX(Model_Data!$A$4:$AG$34,MATCH(J$3,Model_Data!$A$4:$A$34,0),MATCH("Expense - Rent",Model_Data!$A$3:$AG$3,0)),"") -> 2800 | ... AG40: =IFERROR(INDEX(Model_Data!$A$4:$AG$34,MATCH(AG$3,Model_Data!$A$4:$A$34,0),MATCH("Expense - Rent",Model_Data!$A$3:$AG$3,0)),"") -> 2441.25 | AH40: =SUM(C40:AG40) -> 110229.51
A41: Utilities | B41: 6010 | C41: =IFERROR(INDEX(Model_Data!$A$4:$AG$34,MATCH(C$3,Model_Data!$A$4:$A$34,0),MATCH("Expense - Utilities",Model_Data!$A$3:$AG$3,0)),"") -> 562.6 | D41: =IFERROR(INDEX(Model_Data!$A$4:$AG$34,MATCH(D$3,Model_Data!$A$4:$A$34,0),MATCH("Expense - Utilities",Model_Data!$A$3:$AG$3,0)),"") -> 702.27 | E41: =IFERROR(INDEX(Model_Data!$A$4:$AG$34,MATCH(E$3,Model_Data!$A$4:$A$34,0),MATCH("Expense - Utilities",Model_Data!$A$3:$AG$3,0)),"") -> 399 | F41: =IFERROR(INDEX(Model_Data!$A$4:$AG$34,MATCH(F$3,Model_Data!$A$4:$A$34,0),MATCH("Expense - Utilities",Model_Data!$A$3:$AG$3,0)),"") -> 299.5 | G41: =IFERROR(INDEX(Model_Data!$A$4:$AG$34,MATCH(G$3,Model_Data!$A$4:$A$34,0),MATCH("Expense - Utilities",Model_Data!$A$3:$AG$3,0)),"") -> 612 | H41: =IFERROR(INDEX(Model_Data!$A$4:$AG$34,MATCH(H$3,Model_Data!$A$4:$A$34,0),MATCH("Expense - Utilities",Model_Data!$A$3:$AG$3,0)),"") -> 183.27 | I41: =IFERROR(INDEX(Model_Data!$A$4:$AG$34,MATCH(I$3,Model_Data!$A$4:$A$34,0),MATCH("Expense - Utilities",Model_Data!$A$3:$AG$3,0)),"") -> 30.45 | J41: =IFERROR(INDEX(Model_Data!$A$4:$AG$34,MATCH(J$3,Model_Data!$A$4:$A$34,0),MATCH("Expense - Utilities",Model_Data!$A$3:$AG$3,0)),"") -> 91.13 | ... AG41: =IFERROR(INDEX(Model_Data!$A$4:$AG$34,MATCH(AG$3,Model_Data!$A$4:$A$34,0),MATCH("Expense - Utilities",Model_Data!$A$3:$AG$3,0)),"") -> 379.37 | AH41: =SUM(C41:AG41) -> 13436.11
A42: Advertising | B42: 6020 | C42: =IFERROR(INDEX(Model_Data!$A$4:$AG$34,MATCH(C$3,Model_Data!$A$4:$A$34,0),MATCH("Expense - Advertising",Model_Data!$A$3:$AG$3,0)),"") -> 0 | D42: =IFERROR(INDEX(Model_Data!$A$4:$AG$34,MATCH(D$3,Model_Data!$A$4:$A$34,0),MATCH("Expense - Advertising",Model_Data!$A$3:$AG$3,0)),"") -> 50 | E42: =IFERROR(INDEX(Model_Data!$A$4:$AG$34,MATCH(E$3,Model_Data!$A$4:$A$34,0),MATCH("Expense - Advertising",Model_Data!$A$3:$AG$3,0)),"") -> 75 | F42: =IFERROR(INDEX(Model_Data!$A$4:$AG$34,MATCH(F$3,Model_Data!$A$4:$A$34,0),MATCH("Expense - Advertising",Model_Data!$A$3:$AG$3,0)),"") -> 112.5 | G42: =IFERROR(INDEX(Model_Data!$A$4:$AG$34,MATCH(G$3,Model_Data!$A$4:$A$34,0),MATCH("Expense - Advertising",Model_Data!$A$3:$AG$3,0)),"") -> 125 | H42: =IFERROR(INDEX(Model_Data!$A$4:$AG$34,MATCH(H$3,Model_Data!$A$4:$A$34,0),MATCH("Expense - Advertising",Model_Data!$A$3:$AG$3,0)),"") -> 150 | I42: =IFERROR(INDEX(Model_Data!$A$4:$AG$34,MATCH(I$3,Model_Data!$A$4:$A$34,0),MATCH("Expense - Advertising",Model_Data!$A$3:$AG$3,0)),"") -> 125 | J42: =IFERROR(INDEX(Model_Data!$A$4:$AG$34,MATCH(J$3,Model_Data!$A$4:$A$34,0),MATCH("Expense - Advertising",Model_Data!$A$3:$AG$3,0)),"") -> 168.75 | ... AG42: =IFERROR(INDEX(Model_Data!$A$4:$AG$34,MATCH(AG$3,Model_Data!$A$4:$A$34,0),MATCH("Expense - Advertising",Model_Data!$A$3:$AG$3,0)),"") -> 0 | AH42: =SUM(C42:AG42) -> 6484.01
A43: Business Tax | B43: 6030 | C43: =IFERROR(INDEX(Model_Data!$A$4:$AG$34,MATCH(C$3,Model_Data!$A$4:$A$34,0),MATCH("Expense - Taxes",Model_Data!$A$3:$AG$3,0)),"") -> 0 | D43: =IFERROR(INDEX(Model_Data!$A$4:$AG$34,MATCH(D$3,Model_Data!$A$4:$A$34,0),MATCH("Expense - Taxes",Model_Data!$A$3:$AG$3,0)),"") -> 0 | E43: =IFERROR(INDEX(Model_Data!$A$4:$AG$34,MATCH(E$3,Model_Data!$A$4:$A$34,0),MATCH("Expense - Taxes",Model_Data!$A$3:$AG$3,0)),"") -> 0 | F43: =IFERROR(INDEX(Model_Data!$A$4:$AG$34,MATCH(F$3,Model_Data!$A$4:$A$34,0),MATCH("Expense - Taxes",Model_Data!$A$3:$AG$3,0)),"") -> 0 | G43: =IFERROR(INDEX(Model_Data!$A$4:$AG$34,MATCH(G$3,Model_Data!$A$4:$A$34,0),MATCH("Expense - Taxes",Model_Data!$A$3:$AG$3,0)),"") -> 57.75 | H43: =IFERROR(INDEX(Model_Data!$A$4:$AG$34,MATCH(H$3,Model_Data!$A$4:$A$34,0),MATCH("Expense - Taxes",Model_Data!$A$3:$AG$3,0)),"") -> 22.5 | I43: =IFERROR(INDEX(Model_Data!$A$4:$AG$34,MATCH(I$3,Model_Data!$A$4:$A$34,0),MATCH("Expense - Taxes",Model_Data!$A$3:$AG$3,0)),"") -> 0 | J43: =IFERROR(INDEX(Model_Data!$A$4:$AG$34,MATCH(J$3,Model_Data!$A$4:$A$34,0),MATCH("Expense - Taxes",Model_Data!$A$3:$AG$3,0)),"") -> 0 | ... AG43: =IFERROR(INDEX(Model_Data!$A$4:$AG$34,MATCH(AG$3,Model_Data!$A$4:$A$34,0),MATCH("Expense - Taxes",Model_Data!$A$3:$AG$3,0)),"") -> 85.28 | AH43: =SUM(C43:AG43) -> 2245.95
A44: Equipment & Supplies | B44: 6040 | C44: =IFERROR(INDEX(Model_Data!$A$4:$AG$34,MATCH(C$3,Model_Data!$A$4:$A$34,0),MATCH("Equipment / Supplies Purchase",Model_Data!$A$3:$AG$3,0)),"") -> 0 | D44: =IFERROR(INDEX(Model_Data!$A$4:$AG$34,MATCH(D$3,Model_Data!$A$4:$A$34,0),MATCH("Equipment / Supplies Purchase",Model_Data!$A$3:$AG$3,0)),"") -> 200 | E44: =IFERROR(INDEX(Model_Data!$A$4:$AG$34,MATCH(E$3,Model_Data!$A$4:$A$34,0),MATCH("Equipment / Supplies Purchase",Model_Data!$A$3:$AG$3,0)),"") -> 0 | F44: =IFERROR(INDEX(Model_Data!$A$4:$AG$34,MATCH(F$3,Model_Data!$A$4:$A$34,0),MATCH("Equipment / Supplies Purchase",Model_Data!$A$3:$AG$3,0)),"") -> 0 | G44: =IFERROR(INDEX(Model_Data!$A$4:$AG$34,MATCH(G$3,Model_Data!$A$4:$A$34,0),MATCH("Equipment / Supplies Purchase",Model_Data!$A$3:$AG$3,0)),"") -> 974.25 | H44: =IFERROR(INDEX(Model_Data!$A$4:$AG$34,MATCH(H$3,Model_Data!$A$4:$A$34,0),MATCH("Equipment / Supplies Purchase",Model_Data!$A$3:$AG$3,0)),"") -> 686.87 | I44: =IFERROR(INDEX(Model_Data!$A$4:$AG$34,MATCH(I$3,Model_Data!$A$4:$A$34,0),MATCH("Equipment / Supplies Purchase",Model_Data!$A$3:$AG$3,0)),"") -> 0 | J44: =IFERROR(INDEX(Model_Data!$A$4:$AG$34,MATCH(J$3,Model_Data!$A$4:$A$34,0),MATCH("Equipment / Supplies Purchase",Model_Data!$A$3:$AG$3,0)),"") -> 0 | ... AG44: =IFERROR(INDEX(Model_Data!$A$4:$AG$34,MATCH(AG$3,Model_Data!$A$4:$A$34,0),MATCH("Equipment / Supplies Purchase",Model_Data!$A$3:$AG$3,0)),"") -> 0 | AH44: =SUM(C44:AG44) -> 5208.23
A45: Other Operating | B45: 6070 | C45: =IFERROR(INDEX(Model_Data!$A$4:$AG$34,MATCH(C$3,Model_Data!$A$4:$A$34,0),MATCH("Expense - Other Operating Expense",Model_Data!$A$3:$AG$3,0)),"") -> 0 | D45: =IFERROR(INDEX(Model_Data!$A$4:$AG$34,MATCH(D$3,Model_Data!$A$4:$A$34,0),MATCH("Expense - Other Operating Expense",Model_Data!$A$3:$AG$3,0)),"") -> 211.25 | E45: =IFERROR(INDEX(Model_Data!$A$4:$AG$34,MATCH(E$3,Model_Data!$A$4:$A$34,0),MATCH("Expense - Other Operating Expense",Model_Data!$A$3:$AG$3,0)),"") -> 117.12 | F45: =IFERROR(INDEX(Model_Data!$A$4:$AG$34,MATCH(F$3,Model_Data!$A$4:$A$34,0),MATCH("Expense - Other Operating Expense",Model_Data!$A$3:$AG$3,0)),"") -> 199.75 | G45: =IFERROR(INDEX(Model_Data!$A$4:$AG$34,MATCH(G$3,Model_Data!$A$4:$A$34,0),MATCH("Expense - Other Operating Expense",Model_Data!$A$3:$AG$3,0)),"") -> 98.75 | H45: =IFERROR(INDEX(Model_Data!$A$4:$AG$34,MATCH(H$3,Model_Data!$A$4:$A$34,0),MATCH("Expense - Other Operating Expense",Model_Data!$A$3:$AG$3,0)),"") -> 461.12 | I45: =IFERROR(INDEX(Model_Data!$A$4:$AG$34,MATCH(I$3,Model_Data!$A$4:$A$34,0),MATCH("Expense - Other Operating Expense",Model_Data!$A$3:$AG$3,0)),"") -> 41.37 | J45: =IFERROR(INDEX(Model_Data!$A$4:$AG$34,MATCH(J$3,Model_Data!$A$4:$A$34,0),MATCH("Expense - Other Operating Expense",Model_Data!$A$3:$AG$3,0)),"") -> 0 | ... AG45: =IFERROR(INDEX(Model_Data!$A$4:$AG$34,MATCH(AG$3,Model_Data!$A$4:$A$34,0),MATCH("Expense - Other Operating Expense",Model_Data!$A$3:$AG$3,0)),"") -> 0 | AH45: =SUM(C45:AG45) -> 6461.81
A46: Total Operating Expenses | C46: =SUM(C40:C45) -> 562.6 | D46: =SUM(D40:D45) -> 3938.52 | E46: =SUM(E40:E45) -> 3391.12 | F46: =SUM(F40:F45) -> 3411.75 | G46: =SUM(G40:G45) -> 4667.75 | H46: =SUM(H40:H45) -> 2905.14 | I46: =SUM(I40:I45) -> 1598.2 | J46: =SUM(J40:J45) -> 3059.88 | ... AH46: =SUM(AH40:AH45) -> 144065.62
A48: NET OPERATING INCOME | C48: =C26-C31-C37-C46 -> 1237.4 | D48: =D26-D31-D37-D46 -> -1163.52 | E48: =E26-E31-E37-E46 -> 1240.01 | F48: =F26-F31-F37-F46 -> 1030.59 | G48: =G26-G31-G37-G46 -> 205.84 | H48: =H26-H31-H37-H46 -> 1713.61 | I48: =I26-I31-I37-I46 -> 3500.89 | J48: =J26-J31-J37-J46 -> 2446.37 | ... AH48: =AH26-AH31-AH37-AH46 -> 84989.86
A50: Owner Items (equity — not expenses)
A51: Owner / Partner Distributions | B51: 3100 | C51: =IFERROR(INDEX(Model_Data!$A$4:$AG$34,MATCH(C$3,Model_Data!$A$4:$A$34,0),MATCH("Owner / Partner Distribution",Model_Data!$A$3:$AG$3,0)),"") -> 0 | D51: =IFERROR(INDEX(Model_Data!$A$4:$AG$34,MATCH(D$3,Model_Data!$A$4:$A$34,0),MATCH("Owner / Partner Distribution",Model_Data!$A$3:$AG$3,0)),"") -> 0 | E51: =IFERROR(INDEX(Model_Data!$A$4:$AG$34,MATCH(E$3,Model_Data!$A$4:$A$34,0),MATCH("Owner / Partner Distribution",Model_Data!$A$3:$AG$3,0)),"") -> 150 | F51: =IFERROR(INDEX(Model_Data!$A$4:$AG$34,MATCH(F$3,Model_Data!$A$4:$A$34,0),MATCH("Owner / Partner Distribution",Model_Data!$A$3:$AG$3,0)),"") -> 537.5 | G51: =IFERROR(INDEX(Model_Data!$A$4:$AG$34,MATCH(G$3,Model_Data!$A$4:$A$34,0),MATCH("Owner / Partner Distribution",Model_Data!$A$3:$AG$3,0)),"") -> 150 | H51: =IFERROR(INDEX(Model_Data!$A$4:$AG$34,MATCH(H$3,Model_Data!$A$4:$A$34,0),MATCH("Owner / Partner Distribution",Model_Data!$A$3:$AG$3,0)),"") -> 625 | I51: =IFERROR(INDEX(Model_Data!$A$4:$AG$34,MATCH(I$3,Model_Data!$A$4:$A$34,0),MATCH("Owner / Partner Distribution",Model_Data!$A$3:$AG$3,0)),"") -> 1750 | J51: =IFERROR(INDEX(Model_Data!$A$4:$AG$34,MATCH(J$3,Model_Data!$A$4:$A$34,0),MATCH("Owner / Partner Distribution",Model_Data!$A$3:$AG$3,0)),"") -> 5312.5 | ... AG51: =IFERROR(INDEX(Model_Data!$A$4:$AG$34,MATCH(AG$3,Model_Data!$A$4:$A$34,0),MATCH("Owner / Partner Distribution",Model_Data!$A$3:$AG$3,0)),"") -> 0 | AH51: =SUM(C51:AG51) -> 55846.75
A52: Owner Contribution (opening capital) | B52: 3000 | C52: =IFERROR(INDEX(Model_Data!$A$4:$AG$34,MATCH(C$3,Model_Data!$A$4:$A$34,0),MATCH("Owner Contribution",Model_Data!$A$3:$AG$3,0)),"") -> 0 | D52: =IFERROR(INDEX(Model_Data!$A$4:$AG$34,MATCH(D$3,Model_Data!$A$4:$A$34,0),MATCH("Owner Contribution",Model_Data!$A$3:$AG$3,0)),"") -> 0 | E52: =IFERROR(INDEX(Model_Data!$A$4:$AG$34,MATCH(E$3,Model_Data!$A$4:$A$34,0),MATCH("Owner Contribution",Model_Data!$A$3:$AG$3,0)),"") -> 0 | F52: =IFERROR(INDEX(Model_Data!$A$4:$AG$34,MATCH(F$3,Model_Data!$A$4:$A$34,0),MATCH("Owner Contribution",Model_Data!$A$3:$AG$3,0)),"") -> 0 | G52: =IFERROR(INDEX(Model_Data!$A$4:$AG$34,MATCH(G$3,Model_Data!$A$4:$A$34,0),MATCH("Owner Contribution",Model_Data!$A$3:$AG$3,0)),"") -> 0 | H52: =IFERROR(INDEX(Model_Data!$A$4:$AG$34,MATCH(H$3,Model_Data!$A$4:$A$34,0),MATCH("Owner Contribution",Model_Data!$A$3:$AG$3,0)),"") -> 0 | I52: =IFERROR(INDEX(Model_Data!$A$4:$AG$34,MATCH(I$3,Model_Data!$A$4:$A$34,0),MATCH("Owner Contribution",Model_Data!$A$3:$AG$3,0)),"") -> 0 | J52: =IFERROR(INDEX(Model_Data!$A$4:$AG$34,MATCH(J$3,Model_Data!$A$4:$A$34,0),MATCH("Owner Contribution",Model_Data!$A$3:$AG$3,0)),"") -> 0 | ... AG52: =IFERROR(INDEX(Model_Data!$A$4:$AG$34,MATCH(AG$3,Model_Data!$A$4:$A$34,0),MATCH("Owner Contribution",Model_Data!$A$3:$AG$3,0)),"") -> 0 | AH52: =SUM(C52:AG52) -> 5875
A54: Net Operating Margin % | C54: =IF(C26<>0,C48/C26,"") -> 0.68744444 | D54: =IF(D26<>0,D48/D26,"") -> -0.41928649 | E54: =IF(E26<>0,E48/E26,"") -> 0.22648584 | F54: =IF(F26<>0,F48/F26,"") -> 0.20872709 | G54: =IF(G26<>0,G48/G26,"") -> 0.03906809 | H54: =IF(H26<>0,H48/H26,"") -> 0.32679094 | I54: =IF(I26<>0,I48/I26,"") -> 0.53448702 | J54: =IF(J26<>0,J48/J26,"") -> 0.38563468 | ... AH54: =IF(AH26<>0,AH48/AH26,"") -> 0.30867635
A55: Source: Cleaned cash-ledger transaction records | Ballet shoes and gymnastic suits on inventory/COGS basis | Payroll/distributions cleaned; owner distributions treated as equity items

Sheet Annual_KPIs
A1: Claire Studio — Annual Summary & KPIs
A2: Amounts shown in $ | Source: Cleaned cash-ledger transaction records via Monthly P&L | 2019=2mo | 2020=10mo | 2021=12mo | 2022=7mo (through July)
B4: 2019 | C4: 2020 | D4: 2021 | E4: 2022 | F4: Notes / Context
A5: Revenue Summary
A6: Months of operation | B6: =COUNTIF('Monthly_P&L'!$C$4:$AG$4,B$4) -> 2 | C6: =COUNTIF('Monthly_P&L'!$C$4:$AG$4,C$4) -> 10 | D6: =COUNTIF('Monthly_P&L'!$C$4:$AG$4,D$4) -> 12 | E6: =COUNTIF('Monthly_P&L'!$C$4:$AG$4,E$4) -> 7 | F6: 2019: Nov–Dec | 2020: Apr–May excluded (COVID) | 2022: Jan–Jul
A7: Choreography | B7: =SUMIFS('Monthly_P&L'!$C$7:$AG$7,'Monthly_P&L'!$C$4:$AG$4,B$4) -> 3250 | C7: =SUMIFS('Monthly_P&L'!$C$7:$AG$7,'Monthly_P&L'!$C$4:$AG$4,C$4) -> 38162.5 | D7: =SUMIFS('Monthly_P&L'!$C$7:$AG$7,'Monthly_P&L'!$C$4:$AG$4,D$4) -> 62811.87 | E7: =SUMIFS('Monthly_P&L'!$C$7:$AG$7,'Monthly_P&L'!$C$4:$AG$4,E$4) -> 36581.75 | F7: Core program throughout
A8: Fitness | B8: =SUMIFS('Monthly_P&L'!$C$8:$AG$8,'Monthly_P&L'!$C$4:$AG$4,B$4) -> 0 | C8: =SUMIFS('Monthly_P&L'!$C$8:$AG$8,'Monthly_P&L'!$C$4:$AG$4,C$4) -> 13956.25 | D8: =SUMIFS('Monthly_P&L'!$C$8:$AG$8,'Monthly_P&L'!$C$4:$AG$4,D$4) -> 16656.25 | E8: =SUMIFS('Monthly_P&L'!$C$8:$AG$8,'Monthly_P&L'!$C$4:$AG$4,E$4) -> 7312.5 | F8: Owner = instructor, zero labor cost
A9: Karate | B9: =SUMIFS('Monthly_P&L'!$C$9:$AG$9,'Monthly_P&L'!$C$4:$AG$4,B$4) -> 0 | C9: =SUMIFS('Monthly_P&L'!$C$9:$AG$9,'Monthly_P&L'!$C$4:$AG$4,C$4) -> 7000 | D9: =SUMIFS('Monthly_P&L'!$C$9:$AG$9,'Monthly_P&L'!$C$4:$AG$4,D$4) -> 30531.25 | E9: =SUMIFS('Monthly_P&L'!$C$9:$AG$9,'Monthly_P&L'!$C$4:$AG$4,E$4) -> 20887.5 | F9: Launched Sep 2020. Revenue share with Karate Instructor
A10: Gymnastics | B10: =SUMIFS('Monthly_P&L'!$C$10:$AG$10,'Monthly_P&L'!$C$4:$AG$4,B$4) -> 1200 | C10: =SUMIFS('Monthly_P&L'!$C$10:$AG$10,'Monthly_P&L'!$C$4:$AG$4,C$4) -> 6618.75 | D10: =SUMIFS('Monthly_P&L'!$C$10:$AG$10,'Monthly_P&L'!$C$4:$AG$4,D$4) -> 0 | E10: =SUMIFS('Monthly_P&L'!$C$10:$AG$10,'Monthly_P&L'!$C$4:$AG$4,E$4) -> 0 | F10: Early program. Discontinued after COVID
A11: Hall Rental | B11: =SUMIFS('Monthly_P&L'!$C$20:$AG$20,'Monthly_P&L'!$C$4:$AG$4,B$4) -> 0 | C11: =SUMIFS('Monthly_P&L'!$C$20:$AG$20,'Monthly_P&L'!$C$4:$AG$4,C$4) -> 0 | D11: =SUMIFS('Monthly_P&L'!$C$20:$AG$20,'Monthly_P&L'!$C$4:$AG$4,D$4) -> 5829.12 | E11: =SUMIFS('Monthly_P&L'!$C$20:$AG$20,'Monthly_P&L'!$C$4:$AG$4,E$4) -> 14337.5 | F11: Hall 2 subrental from early 2021
A12: Ballet Shoes | B12: =SUMIFS('Monthly_P&L'!$C$14:$AG$14,'Monthly_P&L'!$C$4:$AG$4,B$4) -> 0 | C12: =SUMIFS('Monthly_P&L'!$C$14:$AG$14,'Monthly_P&L'!$C$4:$AG$4,C$4) -> 568.75 | D12: =SUMIFS('Monthly_P&L'!$C$14:$AG$14,'Monthly_P&L'!$C$4:$AG$4,D$4) -> 926.25 | E12: =SUMIFS('Monthly_P&L'!$C$14:$AG$14,'Monthly_P&L'!$C$4:$AG$4,E$4) -> 156.25 | F12: Inventory resale. 54 pairs. Cost range based on source records
A13: Gymnastic Suits | B13: =SUMIFS('Monthly_P&L'!$C$15:$AG$15,'Monthly_P&L'!$C$4:$AG$4,B$4) -> 0 | C13: =SUMIFS('Monthly_P&L'!$C$15:$AG$15,'Monthly_P&L'!$C$4:$AG$4,C$4) -> 2075 | D13: =SUMIFS('Monthly_P&L'!$C$15:$AG$15,'Monthly_P&L'!$C$4:$AG$4,D$4) -> 2068.75 | E13: =SUMIFS('Monthly_P&L'!$C$15:$AG$15,'Monthly_P&L'!$C$4:$AG$4,E$4) -> 425 | F13: 53 suits. Owner sewed (2020), tailor from Dec 2020
A14: Events & Photos | B14: =SUMIFS('Monthly_P&L'!$C$22:$AG$22,'Monthly_P&L'!$C$4:$AG$4,B$4) -> 0 | C14: =SUMIFS('Monthly_P&L'!$C$22:$AG$22,'Monthly_P&L'!$C$4:$AG$4,C$4) -> 0 | D14: =SUMIFS('Monthly_P&L'!$C$22:$AG$22,'Monthly_P&L'!$C$4:$AG$4,D$4) -> 878.11 | E14: =SUMIFS('Monthly_P&L'!$C$22:$AG$22,'Monthly_P&L'!$C$4:$AG$4,E$4) -> 612.63 | F14: Competition entry fees, performance photos
A15: Other Revenue | B15: =SUMIFS('Monthly_P&L'!$C$23:$AG$23,'Monthly_P&L'!$C$4:$AG$4,B$4) -> 125 | C15: =SUMIFS('Monthly_P&L'!$C$23:$AG$23,'Monthly_P&L'!$C$4:$AG$4,C$4) -> 856.25 | D15: =SUMIFS('Monthly_P&L'!$C$23:$AG$23,'Monthly_P&L'!$C$4:$AG$4,D$4) -> 1190.5 | E15: =SUMIFS('Monthly_P&L'!$C$23:$AG$23,'Monthly_P&L'!$C$4:$AG$4,E$4) -> 125
A16: TOTAL REVENUE | B16: =SUMIFS('Monthly_P&L'!$C$26:$AG$26,'Monthly_P&L'!$C$4:$AG$4,B$4) -> 4575 | C16: =SUMIFS('Monthly_P&L'!$C$26:$AG$26,'Monthly_P&L'!$C$4:$AG$4,C$4) -> 69237.5 | D16: =SUMIFS('Monthly_P&L'!$C$26:$AG$26,'Monthly_P&L'!$C$4:$AG$4,D$4) -> 120892.1 | E16: =SUMIFS('Monthly_P&L'!$C$26:$AG$26,'Monthly_P&L'!$C$4:$AG$4,E$4) -> 80631.88 | F16: FY2021 peak full year; 2022 is partial through July.
A18: Cost of Goods Sold
A19: Ballet Shoes COGS | B19: =SUMIFS('Monthly_P&L'!$C$29:$AG$29,'Monthly_P&L'!$C$4:$AG$4,B$4) -> 0 | C19: =SUMIFS('Monthly_P&L'!$C$29:$AG$29,'Monthly_P&L'!$C$4:$AG$4,C$4) -> 371.55 | D19: =SUMIFS('Monthly_P&L'!$C$29:$AG$29,'Monthly_P&L'!$C$4:$AG$4,D$4) -> 605.12 | E19: =SUMIFS('Monthly_P&L'!$C$29:$AG$29,'Monthly_P&L'!$C$4:$AG$4,E$4) -> 102.08 | F19: Weighted-average estimated COGS from item-level purchase history; total ballet shoe cost $1,078.75.
A20: Gymnastic Suit COGS | B20: =SUMIFS('Monthly_P&L'!$C$30:$AG$30,'Monthly_P&L'!$C$4:$AG$4,B$4) -> 0 | C20: =SUMIFS('Monthly_P&L'!$C$30:$AG$30,'Monthly_P&L'!$C$4:$AG$4,C$4) -> 1559.38 | D20: =SUMIFS('Monthly_P&L'!$C$30:$AG$30,'Monthly_P&L'!$C$4:$AG$4,D$4) -> 1275 | E20: =SUMIFS('Monthly_P&L'!$C$30:$AG$30,'Monthly_P&L'!$C$4:$AG$4,E$4) -> 300 | F20: Fabric/tailor/chevron/thread costs captured in clean ledger.
A21: TOTAL COGS | B21: =SUMIFS('Monthly_P&L'!$C$31:$AG$31,'Monthly_P&L'!$C$4:$AG$4,B$4) -> 0 | C21: =SUMIFS('Monthly_P&L'!$C$31:$AG$31,'Monthly_P&L'!$C$4:$AG$4,C$4) -> 1930.93 | D21: =SUMIFS('Monthly_P&L'!$C$31:$AG$31,'Monthly_P&L'!$C$4:$AG$4,D$4) -> 1880.12 | E21: =SUMIFS('Monthly_P&L'!$C$31:$AG$31,'Monthly_P&L'!$C$4:$AG$4,E$4) -> 402.08 | F21: COGS shown separately for resale/inventory items.
A23: Operating Expenses
A24: Payroll | B24: =SUMIFS('Monthly_P&L'!$C$34:$AG$34,'Monthly_P&L'!$C$4:$AG$4,B$4) -> 0 | C24: =SUMIFS('Monthly_P&L'!$C$34:$AG$34,'Monthly_P&L'!$C$4:$AG$4,C$4) -> 8792.5 | D24: =SUMIFS('Monthly_P&L'!$C$34:$AG$34,'Monthly_P&L'!$C$4:$AG$4,D$4) -> 19335.63 | E24: =SUMIFS('Monthly_P&L'!$C$34:$AG$34,'Monthly_P&L'!$C$4:$AG$4,E$4) -> 12967.49 | F24: Co-Founder $750/mo fixed + Karate Instructor rev share (40%→50%) + substitutes
A25: Rent | B25: =SUMIFS('Monthly_P&L'!$C$40:$AG$40,'Monthly_P&L'!$C$4:$AG$4,B$4) -> 2775 | C25: =SUMIFS('Monthly_P&L'!$C$40:$AG$40,'Monthly_P&L'!$C$4:$AG$4,C$4) -> 25202.76 | D25: =SUMIFS('Monthly_P&L'!$C$40:$AG$40,'Monthly_P&L'!$C$4:$AG$4,D$4) -> 53421.75 | E25: =SUMIFS('Monthly_P&L'!$C$40:$AG$40,'Monthly_P&L'!$C$4:$AG$4,E$4) -> 28830 | F25: Increased with Hall 2 expansion in early 2021
A26: Utilities | B26: =SUMIFS('Monthly_P&L'!$C$41:$AG$41,'Monthly_P&L'!$C$4:$AG$4,B$4) -> 1264.87 | C26: =SUMIFS('Monthly_P&L'!$C$41:$AG$41,'Monthly_P&L'!$C$4:$AG$4,C$4) -> 2159.17 | D26: =SUMIFS('Monthly_P&L'!$C$41:$AG$41,'Monthly_P&L'!$C$4:$AG$4,D$4) -> 5837.26 | E26: =SUMIFS('Monthly_P&L'!$C$41:$AG$41,'Monthly_P&L'!$C$4:$AG$4,E$4) -> 4174.81
A27: Advertising | B27: =SUMIFS('Monthly_P&L'!$C$42:$AG$42,'Monthly_P&L'!$C$4:$AG$4,B$4) -> 50 | C27: =SUMIFS('Monthly_P&L'!$C$42:$AG$42,'Monthly_P&L'!$C$4:$AG$4,C$4) -> 2320.01 | D27: =SUMIFS('Monthly_P&L'!$C$42:$AG$42,'Monthly_P&L'!$C$4:$AG$4,D$4) -> 3110.75 | E27: =SUMIFS('Monthly_P&L'!$C$42:$AG$42,'Monthly_P&L'!$C$4:$AG$4,E$4) -> 1003.25 | F27: Local print + Facebook. Consistently low
A28: Business Tax | B28: =SUMIFS('Monthly_P&L'!$C$43:$AG$43,'Monthly_P&L'!$C$4:$AG$4,B$4) -> 0 | C28: =SUMIFS('Monthly_P&L'!$C$43:$AG$43,'Monthly_P&L'!$C$4:$AG$4,C$4) -> 204.75 | D28: =SUMIFS('Monthly_P&L'!$C$43:$AG$43,'Monthly_P&L'!$C$4:$AG$4,D$4) -> 1132.86 | E28: =SUMIFS('Monthly_P&L'!$C$43:$AG$43,'Monthly_P&L'!$C$4:$AG$4,E$4) -> 908.34 | F28: Simplified tax. 2020 waived under COVID relief
A29: Class Supplies & Events | B29: =SUMIFS('Monthly_P&L'!$C$35:$AG$35,'Monthly_P&L'!$C$4:$AG$4,B$4)+SUMIFS('Monthly_P&L'!$C$36:$AG$36,'Monthly_P&L'!$C$4:$AG$4,B$4) -> 0 | C29: =SUMIFS('Monthly_P&L'!$C$35:$AG$35,'Monthly_P&L'!$C$4:$AG$4,C$4)+SUMIFS('Monthly_P&L'!$C$36:$AG$36,'Monthly_P&L'!$C$4:$AG$4,C$4) -> 268.75 | D29: =SUMIFS('Monthly_P&L'!$C$35:$AG$35,'Monthly_P&L'!$C$4:$AG$4,D$4)+SUMIFS('Monthly_P&L'!$C$36:$AG$36,'Monthly_P&L'!$C$4:$AG$4,D$4) -> 603.5 | E29: =SUMIFS('Monthly_P&L'!$C$35:$AG$35,'Monthly_P&L'!$C$4:$AG$4,E$4)+SUMIFS('Monthly_P&L'!$C$36:$AG$36,'Monthly_P&L'!$C$4:$AG$4,E$4) -> 100 | F29: Class materials plus competition/event costs
A30: Equipment & Supplies | B30: =SUMIFS('Monthly_P&L'!$C$44:$AG$44,'Monthly_P&L'!$C$4:$AG$4,B$4) -> 200 | C30: =SUMIFS('Monthly_P&L'!$C$44:$AG$44,'Monthly_P&L'!$C$4:$AG$4,C$4) -> 4058.61 | D30: =SUMIFS('Monthly_P&L'!$C$44:$AG$44,'Monthly_P&L'!$C$4:$AG$4,D$4) -> 917.74 | E30: =SUMIFS('Monthly_P&L'!$C$44:$AG$44,'Monthly_P&L'!$C$4:$AG$4,E$4) -> 31.88
A31: Other Operating | B31: =SUMIFS('Monthly_P&L'!$C$45:$AG$45,'Monthly_P&L'!$C$4:$AG$4,B$4) -> 211.25 | C31: =SUMIFS('Monthly_P&L'!$C$45:$AG$45,'Monthly_P&L'!$C$4:$AG$4,C$4) -> 1710.49 | D31: =SUMIFS('Monthly_P&L'!$C$45:$AG$45,'Monthly_P&L'!$C$4:$AG$4,D$4) -> 2584 | E31: =SUMIFS('Monthly_P&L'!$C$45:$AG$45,'Monthly_P&L'!$C$4:$AG$4,E$4) -> 1956.07
A32: TOTAL EXPENSES | B32: =SUMIFS('Monthly_P&L'!$C$31:$AG$31,'Monthly_P&L'!$C$4:$AG$4,B$4)+SUMIFS('Monthly_P&L'!$C$37:$AG$37,'Monthly_P&L'!$C$4:$AG$4,B$4)+SUMIFS('Monthly_P&L'!$C$46:$AG$46,'Monthly_P&L'!$C$4:$AG$4,B$4) -> 4501.12 | C32: =SUMIFS('Monthly_P&L'!$C$31:$AG$31,'Monthly_P&L'!$C$4:$AG$4,C$4)+SUMIFS('Monthly_P&L'!$C$37:$AG$37,'Monthly_P&L'!$C$4:$AG$4,C$4)+SUMIFS('Monthly_P&L'!$C$46:$AG$46,'Monthly_P&L'!$C$4:$AG$4,C$4) -> 46647.97 | D32: =SUMIFS('Monthly_P&L'!$C$31:$AG$31,'Monthly_P&L'!$C$4:$AG$4,D$4)+SUMIFS('Monthly_P&L'!$C$37:$AG$37,'Monthly_P&L'!$C$4:$AG$4,D$4)+SUMIFS('Monthly_P&L'!$C$46:$AG$46,'Monthly_P&L'!$C$4:$AG$4,D$4) -> 88823.61 | E32: =SUMIFS('Monthly_P&L'!$C$31:$AG$31,'Monthly_P&L'!$C$4:$AG$4,E$4)+SUMIFS('Monthly_P&L'!$C$37:$AG$37,'Monthly_P&L'!$C$4:$AG$4,E$4)+SUMIFS('Monthly_P&L'!$C$46:$AG$46,'Monthly_P&L'!$C$4:$AG$4,E$4) -> 50373.92
A34: Profitability
A35: NET OPERATING INCOME | B35: =SUMIFS('Monthly_P&L'!$C$48:$AG$48,'Monthly_P&L'!$C$4:$AG$4,B$4) -> 73.88 | C35: =SUMIFS('Monthly_P&L'!$C$48:$AG$48,'Monthly_P&L'!$C$4:$AG$4,C$4) -> 22589.53 | D35: =SUMIFS('Monthly_P&L'!$C$48:$AG$48,'Monthly_P&L'!$C$4:$AG$4,D$4) -> 32068.49 | E35: =SUMIFS('Monthly_P&L'!$C$48:$AG$48,'Monthly_P&L'!$C$4:$AG$4,E$4) -> 30257.96 | F35: Revenue minus all operating expenses, COGS, and service costs
A36: Net Operating Margin % | B36: =IF(B16<>0,B35/B16,"") -> 0.016148634 | C36: =IF(C16<>0,C35/C16,"") -> 0.32626149 | D36: =IF(D16<>0,D35/D16,"") -> 0.26526539 | E36: =IF(E16<>0,E35/E16,"") -> 0.3752605 | F36: NOI ÷ Total Revenue
A37: Avg Monthly Revenue | B37: =IF(B6<>0,B16/B6,"") -> 2287.5 | C37: =IF(C6<>0,C16/C6,"") -> 6923.75 | D37: =IF(D6<>0,D16/D6,"") -> 10074.342 | E37: =IF(E6<>0,E16/E6,"") -> 11518.84 | F37: Best cross-year comparison metric given partial years
A38: Owner / Partner Distributions | B38: =SUMIFS('Monthly_P&L'!$C$51:$AG$51,'Monthly_P&L'!$C$4:$AG$4,B$4) -> 0 | C38: =SUMIFS('Monthly_P&L'!$C$51:$AG$51,'Monthly_P&L'!$C$4:$AG$4,C$4) -> 15150 | D38: =SUMIFS('Monthly_P&L'!$C$51:$AG$51,'Monthly_P&L'!$C$4:$AG$4,D$4) -> 19356.25 | E38: =SUMIFS('Monthly_P&L'!$C$51:$AG$51,'Monthly_P&L'!$C$4:$AG$4,E$4) -> 21340.5 | F38: Combined Owner + Co-Founder distributions. Equity item — not an operating expense.
A40: Merchandise Unit Economics
A41: Ballet Shoes — Revenue | B41: =SUMIFS('Monthly_P&L'!$C$14:$AG$14,'Monthly_P&L'!$C$4:$AG$4,B$4) -> 0 | C41: =SUMIFS('Monthly_P&L'!$C$14:$AG$14,'Monthly_P&L'!$C$4:$AG$4,C$4) -> 568.75 | D41: =SUMIFS('Monthly_P&L'!$C$14:$AG$14,'Monthly_P&L'!$C$4:$AG$4,D$4) -> 926.25 | E41: =SUMIFS('Monthly_P&L'!$C$14:$AG$14,'Monthly_P&L'!$C$4:$AG$4,E$4) -> 156.25 | F41: 54 pairs sold, 3 price tiers
A42: Ballet Shoes — COGS | B42: =SUMIFS('Monthly_P&L'!$C$29:$AG$29,'Monthly_P&L'!$C$4:$AG$4,B$4) -> 0 | C42: =SUMIFS('Monthly_P&L'!$C$29:$AG$29,'Monthly_P&L'!$C$4:$AG$4,C$4) -> 371.55 | D42: =SUMIFS('Monthly_P&L'!$C$29:$AG$29,'Monthly_P&L'!$C$4:$AG$4,D$4) -> 605.12 | E42: =SUMIFS('Monthly_P&L'!$C$29:$AG$29,'Monthly_P&L'!$C$4:$AG$4,E$4) -> 102.08 | F42: Weighted-average estimated cost allocated by sales-period revenue.
A43: Ballet Shoes — Gross Profit | B43: =B41-B42 -> 0 | C43: =C41-C42 -> 197.2 | D43: =D41-D42 -> 321.13 | E43: =E41-E42 -> 54.17 | F43: All-period GP $572.50; all-period gross margin 34.7%.
A45: Gymnastic Suits — Revenue | B45: =SUMIFS('Monthly_P&L'!$C$15:$AG$15,'Monthly_P&L'!$C$4:$AG$4,B$4) -> 0 | C45: =SUMIFS('Monthly_P&L'!$C$15:$AG$15,'Monthly_P&L'!$C$4:$AG$4,C$4) -> 2075 | D45: =SUMIFS('Monthly_P&L'!$C$15:$AG$15,'Monthly_P&L'!$C$4:$AG$4,D$4) -> 2068.75 | E45: =SUMIFS('Monthly_P&L'!$C$15:$AG$15,'Monthly_P&L'!$C$4:$AG$4,E$4) -> 425 | F45: 53 suits sold
A46: Gymnastic Suits — COGS | B46: =SUMIFS('Monthly_P&L'!$C$30:$AG$30,'Monthly_P&L'!$C$4:$AG$4,B$4) -> 0 | C46: =SUMIFS('Monthly_P&L'!$C$30:$AG$30,'Monthly_P&L'!$C$4:$AG$4,C$4) -> 1559.38 | D46: =SUMIFS('Monthly_P&L'!$C$30:$AG$30,'Monthly_P&L'!$C$4:$AG$4,D$4) -> 1275 | E46: =SUMIFS('Monthly_P&L'!$C$30:$AG$30,'Monthly_P&L'!$C$4:$AG$4,E$4) -> 300 | F46: Materials, tailoring, and sewing supplies
A47: Gymnastic Suits — Gross Profit | B47: =B45-B46 -> 0 | C47: =C45-C46 -> 515.62 | D47: =D45-D46 -> 793.75 | E47: =E45-E46 -> 125 | F47: All-period GP $1,434; all-period gross margin 31.4%.
A49: Key Performance Indicators
A50: Choreography % of revenue | B50: =IF(B$16<>0,B7/B$16,"") -> 0.71038251 | C50: =IF(C$16<>0,C7/C$16,"") -> 0.55118252 | D50: =IF(D$16<>0,D7/D$16,"") -> 0.51956968 | E50: =IF(E$16<>0,E7/E$16,"") -> 0.45368842 | F50: Declining share as karate and hall rental grew
A51: Karate % of revenue | B51: =IF(B$16<>0,B9/B$16,"") -> 0 | C51: =IF(C$16<>0,C9/C$16,"") -> 0.10110128 | D51: =IF(D$16<>0,D9/D$16,"") -> 0.25254959 | E51: =IF(E$16<>0,E9/E$16,"") -> 0.25904766 | F51: Grew from zero to ~18% of revenue
A52: Rent as % of revenue | B52: =IF(B$16<>0,B25/B$16,"") -> 0.60655738 | C52: =IF(C$16<>0,C25/C$16,"") -> 0.36400448 | D52: =IF(D$16<>0,D25/D$16,"") -> 0.44189612 | E52: =IF(E$16<>0,E25/E$16,"") -> 0.35755088 | F52: Primary fixed cost. Increased with Hall 2 expansion
A53: Payroll as % of revenue | B53: =IF(B$16<>0,B24/B$16,"") -> 0 | C53: =IF(C$16<>0,C24/C$16,"") -> 0.12699043 | D53: =IF(D$16<>0,D24/D$16,"") -> 0.15994122 | E53: =IF(E$16<>0,E24/E$16,"") -> 0.16082336 | F53: Low: Owner no salary; Karate Instructor on revenue share (variable)
A54: Best month | B54: 2019-12 | C54: 2020-09 | D54: 2021-12 | E54: 2022-03
A55: Best month revenue | B55: 2775 | C55: 10837.5 | D55: 13297.87 | E55: 14926.25
A56: Worst month | B56: 2019-11 | C56: 2020-02 | D56: 2021-01 | E56: 2022-07
A57: Worst month revenue | B57: 1800 | C57: 4937.5 | D57: 6631.25 | E57: 3987.5
A59: Business Milestones
A60: Studio opens | B60: Nov 2019 | C60: — | D60: — | E60: — | F60: Hall 1. Choreography + gymnastics
A61: COVID closure | B61: — | C61: Apr–May | D61: — | E61: — | F61: Two months zero revenue
A62: Karate launches | B62: — | C62: Sep 2020 | D62: — | E62: — | F62: Karate Instructor, 40% revenue share
A63: Hall 2 expansion | B63: — | C63: — | D63: Early 2021 | E63: — | F63: Subrental income begins
A64: Strong student-count month | B64: — | C64: — | D64: Apr 2021 | E64: — | F64: $12,859 revenue | 53 students
A65: Fitness +50% | B65: — | C65: — | D65: May 2021 | E65: — | F65: $125 → $187.50/month
A66: Choreo/Karate +25% | B66: — | C66: — | D66: Sep 2021 | E66: — | F66: $250 → $312.50 | Instructor revenue share
A67: Business transfer | B67: — | C67: — | D67: — | E67: Jun 2022 | F67: Owner relocated to the United States
A68: Prepared by: Kate Kucherova | Portfolio Project 2026 | Source: Original cash-ledger transaction records, Nov 2019–Jul 2022

Sheet Budget_vs_Actual
A1: Claire Studio — 2021 Budget vs Actual
A2: Amounts shown in $ | Budget based on late-2020 run-rate and planned second hall expansion
A4: Month | B4: Budget Revenue | C4: Actual Revenue | D4: Revenue Var. | E4: Budget Expenses | F4: Actual Expenses | G4: Expense Var. | H4: Budget NOI | I4: Actual NOI | J4: NOI Var.
A5: Jan | B5: =Budget_Assumptions!B46 -> 6762 | C5: =SUMIFS(Model_Data!$P:$P,Model_Data!$B:$B,2021,Model_Data!$C:$C,A5) -> 6631.25 | D5: =C5-B5 -> -130.75 | E5: =Budget_Assumptions!B57 -> 4987 | F5: =SUMIFS(Model_Data!$AB:$AB,Model_Data!$B:$B,2021,Model_Data!$C:$C,A5) -> 3937.45 | G5: =F5-E5 -> -1049.55 | H5: =Budget_Assumptions!B59 -> 1775 | I5: =SUMIFS(Model_Data!$AC:$AC,Model_Data!$B:$B,2021,Model_Data!$C:$C,A5) -> 2693.8 | J5: =I5-H5 -> 918.8
A6: Feb | B6: =Budget_Assumptions!C46 -> 7325.5 | C6: =SUMIFS(Model_Data!$P:$P,Model_Data!$B:$B,2021,Model_Data!$C:$C,A6) -> 6699.24 | D6: =C6-B6 -> -626.26 | E6: =Budget_Assumptions!C57 -> 6194.25 | F6: =SUMIFS(Model_Data!$AB:$AB,Model_Data!$B:$B,2021,Model_Data!$C:$C,A6) -> 6433.59 | G6: =F6-E6 -> 239.34 | H6: =Budget_Assumptions!C59 -> 1131.25 | I6: =SUMIFS(Model_Data!$AC:$AC,Model_Data!$B:$B,2021,Model_Data!$C:$C,A6) -> 265.65 | J6: =I6-H6 -> -865.6
A7: Mar | B7: =Budget_Assumptions!D46 -> 9579.5 | C7: =SUMIFS(Model_Data!$P:$P,Model_Data!$B:$B,2021,Model_Data!$C:$C,A7) -> 11406.87 | D7: =C7-B7 -> 1827.37 | E7: =Budget_Assumptions!D57 -> 7673.25 | F7: =SUMIFS(Model_Data!$AB:$AB,Model_Data!$B:$B,2021,Model_Data!$C:$C,A7) -> 7648.15 | G7: =F7-E7 -> -25.1 | H7: =Budget_Assumptions!D59 -> 1906.25 | I7: =SUMIFS(Model_Data!$AC:$AC,Model_Data!$B:$B,2021,Model_Data!$C:$C,A7) -> 3758.72 | J7: =I7-H7 -> 1852.47
A8: Apr | B8: =Budget_Assumptions!E46 -> 10543 | C8: =SUMIFS(Model_Data!$P:$P,Model_Data!$B:$B,2021,Model_Data!$C:$C,A8) -> 12859.37 | D8: =C8-B8 -> 2316.37 | E8: =Budget_Assumptions!E57 -> 7780.5 | F8: =SUMIFS(Model_Data!$AB:$AB,Model_Data!$B:$B,2021,Model_Data!$C:$C,A8) -> 9310.21 | G8: =F8-E8 -> 1529.71 | H8: =Budget_Assumptions!E59 -> 2762.5 | I8: =SUMIFS(Model_Data!$AC:$AC,Model_Data!$B:$B,2021,Model_Data!$C:$C,A8) -> 3549.16 | J8: =I8-H8 -> 786.66
A9: May | B9: =Budget_Assumptions!F46 -> 10543 | C9: =SUMIFS(Model_Data!$P:$P,Model_Data!$B:$B,2021,Model_Data!$C:$C,A9) -> 10931.25 | D9: =C9-B9 -> 388.25 | E9: =Budget_Assumptions!F57 -> 7780.5 | F9: =SUMIFS(Model_Data!$AB:$AB,Model_Data!$B:$B,2021,Model_Data!$C:$C,A9) -> 8112.33 | G9: =F9-E9 -> 331.83 | H9: =Budget_Assumptions!F59 -> 2762.5 | I9: =SUMIFS(Model_Data!$AC:$AC,Model_Data!$B:$B,2021,Model_Data!$C:$C,A9) -> 2818.92 | J9: =I9-H9 -> 56.42
A10: Jun | B10: =Budget_Assumptions!G46 -> 8852.5 | C10: =SUMIFS(Model_Data!$P:$P,Model_Data!$B:$B,2021,Model_Data!$C:$C,A10) -> 9301.25 | D10: =C10-B10 -> 448.75 | E10: =Budget_Assumptions!G57 -> 7308.75 | F10: =SUMIFS(Model_Data!$AB:$AB,Model_Data!$B:$B,2021,Model_Data!$C:$C,A10) -> 6893.44 | G10: =F10-E10 -> -415.31 | H10: =Budget_Assumptions!G59 -> 1543.75 | I10: =SUMIFS(Model_Data!$AC:$AC,Model_Data!$B:$B,2021,Model_Data!$C:$C,A10) -> 2407.81 | J10: =I10-H10 -> 864.06
A11: Jul | B11: =Budget_Assumptions!H46 -> 8189 | C11: =SUMIFS(Model_Data!$P:$P,Model_Data!$B:$B,2021,Model_Data!$C:$C,A11) -> 7027.5 | D11: =C11-B11 -> -1161.5 | E11: =Budget_Assumptions!H57 -> 7201.5 | F11: =SUMIFS(Model_Data!$AB:$AB,Model_Data!$B:$B,2021,Model_Data!$C:$C,A11) -> 6539.18 | G11: =F11-E11 -> -662.32 | H11: =Budget_Assumptions!H59 -> 987.5 | I11: =SUMIFS(Model_Data!$AC:$AC,Model_Data!$B:$B,2021,Model_Data!$C:$C,A11) -> 488.32 | J11: =I11-H11 -> -499.18
A12: Aug | B12: =Budget_Assumptions!I46 -> 8189 | C12: =SUMIFS(Model_Data!$P:$P,Model_Data!$B:$B,2021,Model_Data!$C:$C,A12) -> 7800 | D12: =C12-B12 -> -389 | E12: =Budget_Assumptions!I57 -> 7251.5 | F12: =SUMIFS(Model_Data!$AB:$AB,Model_Data!$B:$B,2021,Model_Data!$C:$C,A12) -> 7523.62 | G12: =F12-E12 -> 272.12 | H12: =Budget_Assumptions!I59 -> 937.5 | I12: =SUMIFS(Model_Data!$AC:$AC,Model_Data!$B:$B,2021,Model_Data!$C:$C,A12) -> 276.38 | J12: =I12-H12 -> -661.12
A13: Sep | B13: =Budget_Assumptions!J46 -> 11306.5 | C13: =SUMIFS(Model_Data!$P:$P,Model_Data!$B:$B,2021,Model_Data!$C:$C,A13) -> 11250 | D13: =C13-B13 -> -56.5 | E13: =Budget_Assumptions!J57 -> 7937.75 | F13: =SUMIFS(Model_Data!$AB:$AB,Model_Data!$B:$B,2021,Model_Data!$C:$C,A13) -> 8327.79 | G13: =F13-E13 -> 390.04 | H13: =Budget_Assumptions!J59 -> 3368.75 | I13: =SUMIFS(Model_Data!$AC:$AC,Model_Data!$B:$B,2021,Model_Data!$C:$C,A13) -> 2922.21 | J13: =I13-H13 -> -446.54
A14: Oct | B14: =Budget_Assumptions!K46 -> 11406.5 | C14: =SUMIFS(Model_Data!$P:$P,Model_Data!$B:$B,2021,Model_Data!$C:$C,A14) -> 10962.5 | D14: =C14-B14 -> -444 | E14: =Budget_Assumptions!K57 -> 7937.75 | F14: =SUMIFS(Model_Data!$AB:$AB,Model_Data!$B:$B,2021,Model_Data!$C:$C,A14) -> 8564.12 | G14: =F14-E14 -> 626.37 | H14: =Budget_Assumptions!K59 -> 3468.75 | I14: =SUMIFS(Model_Data!$AC:$AC,Model_Data!$B:$B,2021,Model_Data!$C:$C,A14) -> 2398.38 | J14: =I14-H14 -> -1070.37
A15: Nov | B15: =Budget_Assumptions!L46 -> 12170 | C15: =SUMIFS(Model_Data!$P:$P,Model_Data!$B:$B,2021,Model_Data!$C:$C,A15) -> 12725 | D15: =C15-B15 -> 555 | E15: =Budget_Assumptions!L57 -> 7945 | F15: =SUMIFS(Model_Data!$AB:$AB,Model_Data!$B:$B,2021,Model_Data!$C:$C,A15) -> 6388.37 | G15: =F15-E15 -> -1556.63 | H15: =Budget_Assumptions!L59 -> 4225 | I15: =SUMIFS(Model_Data!$AC:$AC,Model_Data!$B:$B,2021,Model_Data!$C:$C,A15) -> 6336.63 | J15: =I15-H15 -> 2111.63
A16: Dec | B16: =Budget_Assumptions!M46 -> 12833.5 | C16: =SUMIFS(Model_Data!$P:$P,Model_Data!$B:$B,2021,Model_Data!$C:$C,A16) -> 13297.87 | D16: =C16-B16 -> 464.37 | E16: =Budget_Assumptions!M57 -> 8052.25 | F16: =SUMIFS(Model_Data!$AB:$AB,Model_Data!$B:$B,2021,Model_Data!$C:$C,A16) -> 9145.36 | G16: =F16-E16 -> 1093.11 | H16: =Budget_Assumptions!M59 -> 4781.25 | I16: =SUMIFS(Model_Data!$AC:$AC,Model_Data!$B:$B,2021,Model_Data!$C:$C,A16) -> 4152.51 | J16: =I16-H16 -> -628.74
A17: Total | B17: =SUM(B5:B16) -> 117700 | C17: =SUM(C5:C16) -> 120892.1 | D17: =SUM(D5:D16) -> 3192.1 | E17: =SUM(E5:E16) -> 88050 | F17: =SUM(F5:F16) -> 88823.61 | G17: =SUM(G5:G16) -> 773.61 | H17: =SUM(H5:H16) -> 29650 | I17: =SUM(I5:I16) -> 32068.49 | J17: =SUM(J5:J16) -> 2418.49
A20: Annual Detail | B20: Budget | C20: Actual | D20: Variance $ | E20: Variance % | F20: F / U | G20: Comment
A21: Total Revenue | B21: =Budget_Assumptions!$D$9 -> 117700 | C21: =SUMIFS(Model_Data!$P:$P,Model_Data!$B:$B,2021) -> 120892.1 | D21: =C21-B21 -> 3192.1 | E21: =IFERROR(D21/B21,0) -> 0.027120646 | F21: =IF(D21>=0,"Favorable","Unfavorable") -> Favorable | G21: Actual revenue exceeded budget.
A22: Choreography Revenue | B22: =Budget_Assumptions!$D$10 -> 60000 | C22: =SUMIFS(Model_Data!$D:$D,Model_Data!$B:$B,2021) -> 62811.87 | D22: =C22-B22 -> 2811.87 | E22: =IFERROR(D22/B22,0) -> 0.0468645 | F22: =IF(D22>=0,"Favorable","Unfavorable") -> Favorable | G22: Core program performed above plan.
A23: Fitness Revenue | B23: =Budget_Assumptions!$D$11 -> 19200 | C23: =SUMIFS(Model_Data!$F:$F,Model_Data!$B:$B,2021) -> 16656.25 | D23: =C23-B23 -> -2543.75 | E23: =IFERROR(D23/B23,0) -> -0.13248698 | F23: =IF(D23>=0,"Favorable","Unfavorable") -> Unfavorable | G23: Fitness recovered slower than budgeted.
A24: Karate Revenue | B24: =Budget_Assumptions!$D$12 -> 28800 | C24: =SUMIFS(Model_Data!$E:$E,Model_Data!$B:$B,2021) -> 30531.25 | D24: =C24-B24 -> 1731.25 | E24: =IFERROR(D24/B24,0) -> 0.060112847 | F24: =IF(D24>=0,"Favorable","Unfavorable") -> Favorable | G24: Karate performed above plan.
A25: Hall Rental Income | B25: =Budget_Assumptions!$D$13 -> 5000 | C25: =SUMIFS(Model_Data!$H:$H,Model_Data!$B:$B,2021) -> 5829.12 | D25: =C25-B25 -> 829.12 | E25: =IFERROR(D25/B25,0) -> 0.165824 | F25: =IF(D25>=0,"Favorable","Unfavorable") -> Favorable | G25: Second hall created rental income.
A26: Merchandise Revenue | B26: =Budget_Assumptions!$D$14 -> 3200 | C26: =SUMIFS(Model_Data!$K:$K,Model_Data!$B:$B,2021)+SUMIFS(Model_Data!$L:$L,Model_Data!$B:$B,2021)+SUMIFS(Model_Data!$M:$M,Model_Data!$B:$B,2021) -> 2995 | D26: =C26-B26 -> -205 | E26: =IFERROR(D26/B26,0) -> -0.0640625 | F26: =IF(D26>=0,"Favorable","Unfavorable") -> Unfavorable | G26: Small add-on revenue performed near plan.
A27: Events & Other Revenue | B27: =Budget_Assumptions!$D$15 -> 1500 | C27: =SUMIFS(Model_Data!$N:$N,Model_Data!$B:$B,2021)+SUMIFS(Model_Data!$O:$O,Model_Data!$B:$B,2021) -> 2068.61 | D27: =C27-B27 -> 568.61 | E27: =IFERROR(D27/B27,0) -> 0.37907333 | F27: =IF(D27>=0,"Favorable","Unfavorable") -> Favorable | G27: Other income was modest but helpful.
A28: Total Expenses | B28: =Budget_Assumptions!$D$16 -> 88050 | C28: =SUMIFS(Model_Data!$AB:$AB,Model_Data!$B:$B,2021) -> 88823.61 | D28: =C28-B28 -> 773.61 | E28: =IFERROR(D28/B28,0) -> 0.0087860307 | F28: =IF(D28<=0,"Favorable","Unfavorable") -> Unfavorable | G28: Expenses were close to budget.
A29: Rent | B29: =Budget_Assumptions!$D$17 -> 53400 | C29: =SUMIFS(Model_Data!$R:$R,Model_Data!$B:$B,2021) -> 53421.75 | D29: =C29-B29 -> 21.75 | E29: =IFERROR(D29/B29,0) -> 0.00040730337 | F29: =IF(D29<=0,"Favorable","Unfavorable") -> Unfavorable | G29: Rent followed the planned expansion step-up.
A30: Payroll | B30: =Budget_Assumptions!$D$18 -> 19000 | C30: =SUMIFS(Model_Data!$Q:$Q,Model_Data!$B:$B,2021) -> 19335.63 | D30: =C30-B30 -> 335.63 | E30: =IFERROR(D30/B30,0) -> 0.017664737 | F30: =IF(D30<=0,"Favorable","Unfavorable") -> Unfavorable | G30: Payroll was slightly above plan.
A31: Utilities | B31: =Budget_Assumptions!$D$19 -> 5400 | C31: =SUMIFS(Model_Data!$S:$S,Model_Data!$B:$B,2021) -> 5837.26 | D31: =C31-B31 -> 437.26 | E31: =IFERROR(D31/B31,0) -> 0.080974074 | F31: =IF(D31<=0,"Favorable","Unfavorable") -> Unfavorable | G31: Utilities ran higher after expansion.
A32: Advertising | B32: =Budget_Assumptions!$D$20 -> 3600 | C32: =SUMIFS(Model_Data!$T:$T,Model_Data!$B:$B,2021) -> 3110.75 | D32: =C32-B32 -> -489.25 | E32: =IFERROR(D32/B32,0) -> -0.13590278 | F32: =IF(D32<=0,"Favorable","Unfavorable") -> Favorable | G32: Advertising spend was below plan.
A33: Business Tax | B33: =Budget_Assumptions!$D$21 -> 1100 | C33: =SUMIFS(Model_Data!$U:$U,Model_Data!$B:$B,2021) -> 1132.86 | D33: =C33-B33 -> 32.86 | E33: =IFERROR(D33/B33,0) -> 0.029872727 | F33: =IF(D33<=0,"Favorable","Unfavorable") -> Unfavorable | G33: Tax expense tracked business activity.
A34: Merchandise COGS | B34: =Budget_Assumptions!$D$22 -> 1350 | C34: =SUMIFS(Model_Data!$X:$X,Model_Data!$B:$B,2021)+SUMIFS(Model_Data!$Y:$Y,Model_Data!$B:$B,2021) -> 1880.12 | D34: =C34-B34 -> 530.12 | E34: =IFERROR(D34/B34,0) -> 0.39268148 | F34: =IF(D34<=0,"Favorable","Unfavorable") -> Unfavorable | G34: COGS above budget due to estimated weighted-average shoe cost and suit costs; merchandise margin remains positive.
A35: Class Supplies & Events | B35: =Budget_Assumptions!$D$23 -> 900 | C35: =SUMIFS(Model_Data!$V:$V,Model_Data!$B:$B,2021)+SUMIFS(Model_Data!$W:$W,Model_Data!$B:$B,2021) -> 603.5 | D35: =C35-B35 -> -296.5 | E35: =IFERROR(D35/B35,0) -> -0.32944444 | F35: =IF(D35<=0,"Favorable","Unfavorable") -> Favorable | G35: Class and event support costs were below plan.
A36: Equipment & Supplies | B36: =Budget_Assumptions!$D$24 -> 900 | C36: =SUMIFS(Model_Data!$Z:$Z,Model_Data!$B:$B,2021) -> 917.74 | D36: =C36-B36 -> 17.74 | E36: =IFERROR(D36/B36,0) -> 0.019711111 | F36: =IF(D36<=0,"Favorable","Unfavorable") -> Unfavorable | G36: Small operating purchases were near plan.
A37: Other Operating | B37: =Budget_Assumptions!$D$25 -> 2400 | C37: =SUMIFS(Model_Data!$AA:$AA,Model_Data!$B:$B,2021) -> 2584 | D37: =C37-B37 -> 184 | E37: =IFERROR(D37/B37,0) -> 0.076666667 | F37: =IF(D37<=0,"Favorable","Unfavorable") -> Unfavorable | G37: Other costs were slightly above plan.
A38: Net Operating Income | B38: =Budget_Assumptions!$D$26 -> 29650 | C38: =SUMIFS(Model_Data!$AC:$AC,Model_Data!$B:$B,2021) -> 32068.49 | D38: =C38-B38 -> 2418.49 | E38: =IFERROR(D38/B38,0) -> 0.08156796 | F38: =IF(D38>=0,"Favorable","Unfavorable") -> Favorable | G38: NOI beat budget because revenue growth covered fixed costs.

Sheet Variance_Commentary
A1: Claire Studio — 2021 Variance Commentary
A2: Simple management commentary based on 2021 budget vs actual results
A4: Executive Summary | B4: Result | C4: Comment
A5: Revenue | B5: =Budget_vs_Actual!D17 -> 3192.1 | C5: Actual revenue exceeded the management budget.
A6: Expenses | B6: =Budget_vs_Actual!G17 -> 773.61 | C6: Expenses were close to budget despite the second hall expansion.
A7: NOI | B7: =Budget_vs_Actual!J17 -> 2418.49 | C7: Profitability beat budget because revenue growth covered the higher fixed-cost base.
A8: Expansion Decision | B8: Qualitative | C8: The second hall increased rent and utilities, but also created capacity and hall rental income.
A11: Key Driver | B11: Budget vs Actual | C11: Impact | D11: Management Takeaway
A12: Choreography | B12: =Budget_vs_Actual!D22 -> 2811.87 | C12: Revenue upside | D12: Core recurring program was stronger than expected.
A13: Karate | B13: =Budget_vs_Actual!D24 -> 1731.25 | C13: Revenue upside | D13: Growth program benefited from stronger enrollment.
A14: Fitness | B14: =Budget_vs_Actual!D23 -> -2543.75 | C14: Revenue pressure | D14: Fitness recovered slower than planned and should be watched separately.
A15: Hall Rental | B15: =Budget_vs_Actual!D25 -> 829.12 | C15: Revenue upside | D15: Second hall created additional income beyond classes.
A16: Rent | B16: =Budget_vs_Actual!D29 -> 21.75 | C16: Fixed cost step-up | D16: Rent was planned as the main expansion cost and stayed close to budget.
A17: Utilities | B17: =Budget_vs_Actual!D31 -> 437.26 | C17: Expense pressure | D17: Utilities were higher than planned after the larger space.
A18: NOI | B18: =Budget_vs_Actual!D38 -> 2418.49 | C18: Profitability | D18: The expansion was financially supported by revenue growth and controlled costs.
A22: Conclusion
A23: The 2021 budget shows a practical recovery-and-expansion plan. Actual results were stronger than budget mainly because class revenue and hall rental income covered the higher rent and utility base.
A24: This supports the business case that the second hall expansion improved capacity and helped protect profitability.

Sheet Second_Hall_BreakEven
A1: Claire Studio — Second Hall Break-Even Analysis
A2: Simple recurring break-even view | Amounts in $ | Blue font = editable assumption
A4: 1. Methodology
A5: Expansion timing | B5: Transition began in February 2021; full two-hall run-rate begins March 2021.
A6: Business use | B6: Old hall: fitness, karate, fitting/locker room. New hall: choreography, subrent, events, photos, and workshops.
A7: Analysis method | B7: Compare late-2020 exit run-rate to full two-hall 2021 run-rate, then estimate recurring break-even revenue needed for Hall 2.
A10: 2. Expansion Inputs
A11: Input | B11: Value | C11: Formula / Source | D11: Comment
A12: Hall 2 Rent | B12: 1875 | C12: Management rent structure | D12: Incremental monthly rent
A13: Baseline Avg Utilities | B13: =AVERAGE(Model_Data!S12:S15) -> 135.955 | C13: Sep–Dec 2020 average | D13: Before second hall
A14: Two-Hall Avg Utilities | B14: =AVERAGE(Model_Data!S18:S27) -> 518.716 | C14: Mar–Dec 2021 average | D14: After full two-hall run-rate
A15: Incremental Utilities | B15: =B14-B13 -> 382.761 | C15: Two-hall avg - baseline avg | D15: Estimated recurring utility increase
A16: Incremental Fixed Cost | B16: =B12+B15 -> 2257.761 | C16: Hall 2 rent + incremental utilities | D16: Monthly cost to cover
A17: Contribution Margin Assumption | B17: 0.8 | C17: Management assumption; see Cost_Per_Class_Model | D17: Applied only to incremental expansion-related revenue. Fixed rent/utilities are modeled separately; no additional fixed payroll was assumed.
A18: Revenue Needed to Break Even | B18: =B16/B17 -> 2822.2012 | C18: Incremental fixed cost ÷ contribution margin | D18: Recurring monthly revenue target
A19: 3. Expansion-Related Revenue Indicators (supporting view only)
A20: Metric | B20: Amount / Run-Rate | C20: Formula / Source | D20: Comment
A21: Mar-Dec 2021 Related Revenue Run-Rate | B21: =AVERAGE('Monthly_P&L'!Q24:Z24) -> 783.724 | C21: Hall rental + events/photos + other; Mar-Dec average | D21: Below break-even target; supporting indicator only
A22: Nov-Dec 2021 Related Revenue Run-Rate | B22: =AVERAGE('Monthly_P&L'!Y24:Z24) -> 2295.81 | C22: Hall rental + events/photos + other; Nov-Dec average | D22: Close to fixed cost, but below target after contribution margin
A23: 2021 Annual Related Revenue | B23: =B37 -> 7897.73 | C23: Hall rental + events/photos + other | D23: Direct secondary revenue supported by expanded space
A24: Decision Use | C24: Management judgment | D24: Not used as standalone break-even conclusion because the second hall supported total scheduling and capacity across the studio.
A26: 4. Total Business Run-Rate Check
A27: Metric | B27: Total Revenue | C27: Incremental Revenue | D27: Break-Even Revenue Target | E27: Variance to Target | F27: Conclusion
A28: Late-2020 Exit Run-Rate | B28: =AVERAGE('Monthly_P&L'!K26:N26) -> 8854.6875 | C28: 0 | D28: =$B$18 -> 2822.2012 | E28: =C28-D28 -> -2822.2012 | F28: Baseline only
A29: Mar-Dec 2021 Two-Hall Run-Rate | B29: =AVERAGE('Monthly_P&L'!Q26:Z26) -> 10756.161 | C29: =B29-B28 -> 1901.4735 | D29: =$B$18 -> 2822.2012 | E29: =C29-D29 -> -920.72775 | F29: Below target
A30: Nov-Dec 2021 Late-Year Run-Rate | B30: =AVERAGE('Monthly_P&L'!Y26:Z26) -> 13011.435 | C30: =B30-B28 -> 4156.7475 | D30: =$B$18 -> 2822.2012 | E30: =C30-D30 -> 1334.5462 | F30: Covered
A32: 5. Direct Revenue Support
A33: Metric | B33: Amount | C33: Formula / Source | D33: Comment
A34: 2021 Hall Rental Revenue | B34: =SUM('Monthly_P&L'!O20:Z20) -> 5829.12 | C34: Model_Data | D34: Direct revenue created by additional space
A35: 2021 Event / Photo Revenue | B35: =SUM('Monthly_P&L'!O22:Z22) -> 878.11 | C35: Model_Data | D35: Additional activity supported by studio capacity
A36: 2021 Other Revenue | B36: =SUM('Monthly_P&L'!O21:Z21,'Monthly_P&L'!O23:Z23) -> 1190.5 | C36: Model_Data | D36: Small supporting revenue
A37: Total Related Revenue | B37: =B34+B35+B36 -> 7897.73 | C37: Formula | D37: Direct secondary revenue; separate from class capacity
A39: Management Conclusion | B39: Expansion-related revenue indicators alone did not fully cover the recurring break-even target. The total business run-rate is the primary decision view because the second hall supported scheduling, choreography capacity, subrent/events, and use of both halls. By late 2021, total incremental revenue covered the recurring fixed-cost target.

Sheet Management_Financials
A1: Claire Studio — Management Financial Statements
A2: Management view prepared from the cleaned operating model with estimated merchandise COGS where exact inventory matching was unavailable. Amounts shown in $.
A4: Income Statement | B4: 2019 | C4: 2020 | D4: 2021 | E4: 2022 | F4: All Periods
A5: Total Revenue | B5: =SUMIF('Monthly_P&L'!$C$4:$AG$4,B$4,'Monthly_P&L'!$C$26:$AG$26) -> 4575 | C5: =SUMIF('Monthly_P&L'!$C$4:$AG$4,C$4,'Monthly_P&L'!$C$26:$AG$26) -> 69237.5 | D5: =SUMIF('Monthly_P&L'!$C$4:$AG$4,D$4,'Monthly_P&L'!$C$26:$AG$26) -> 120892.1 | E5: =SUMIF('Monthly_P&L'!$C$4:$AG$4,E$4,'Monthly_P&L'!$C$26:$AG$26) -> 80631.88 | F5: =SUM(B5:E5) -> 275336.48
A6: Cost of Goods Sold (incl. estimated shoe COGS) | B6: =Inventory_Rollforward!B16 -> 0 | C6: =Inventory_Rollforward!C16 -> 1930.93 | D6: =Inventory_Rollforward!D16 -> 1880.12 | E6: =Inventory_Rollforward!E16 -> 402.08 | F6: =Inventory_Rollforward!F16 -> 4213.13
A7: Gross Profit | B7: =B5-B6 -> 4575 | C7: =C5-C6 -> 67306.57 | D7: =D5-D6 -> 119011.98 | E7: =E5-E6 -> 80229.8 | F7: =F5-F6 -> 271123.35
A8: Cost of Services | B8: =SUMIF('Monthly_P&L'!$C$4:$AG$4,B$4,'Monthly_P&L'!$C$37:$AG$37) -> 0 | C8: =SUMIF('Monthly_P&L'!$C$4:$AG$4,C$4,'Monthly_P&L'!$C$37:$AG$37) -> 9061.25 | D8: =SUMIF('Monthly_P&L'!$C$4:$AG$4,D$4,'Monthly_P&L'!$C$37:$AG$37) -> 19939.13 | E8: =SUMIF('Monthly_P&L'!$C$4:$AG$4,E$4,'Monthly_P&L'!$C$37:$AG$37) -> 13067.49 | F8: =SUM(B8:E8) -> 42067.87
A9: Operating Expenses | B9: =SUMIF('Monthly_P&L'!$C$4:$AG$4,B$4,'Monthly_P&L'!$C$46:$AG$46) -> 4501.12 | C9: =SUMIF('Monthly_P&L'!$C$4:$AG$4,C$4,'Monthly_P&L'!$C$46:$AG$46) -> 35655.79 | D9: =SUMIF('Monthly_P&L'!$C$4:$AG$4,D$4,'Monthly_P&L'!$C$46:$AG$46) -> 67004.36 | E9: =SUMIF('Monthly_P&L'!$C$4:$AG$4,E$4,'Monthly_P&L'!$C$46:$AG$46) -> 36904.35 | F9: =SUM(B9:E9) -> 144065.62
A10: Total Expenses | B10: =B6+B8+B9 -> 4501.12 | C10: =C6+C8+C9 -> 46647.97 | D10: =D6+D8+D9 -> 88823.61 | E10: =E6+E8+E9 -> 50373.92 | F10: =F6+F8+F9 -> 190346.62
A11: Net Operating Income | B11: =B5-B10 -> 73.88 | C11: =C5-C10 -> 22589.53 | D11: =D5-D10 -> 32068.49 | E11: =E5-E10 -> 30257.96 | F11: =SUM(B11:E11) -> 84989.86
A12: Net Operating Margin | B12: =IFERROR(B11/B5,0) -> 0.016148634 | C12: =IFERROR(C11/C5,0) -> 0.32626149 | D12: =IFERROR(D11/D5,0) -> 0.26526539 | E12: =IFERROR(E11/E5,0) -> 0.3752605 | F12: =IFERROR(F11/F5,0) -> 0.30867635
A15: Cash Flow Statement | B15: 2019 | C15: 2020 | D15: 2021 | E15: 2022 | F15: All Periods
A16: Beginning Cash Position | B16: =0 -> 0 | C16: =B21 -> 73.88 | D16: =C21 -> 13388.41 | E16: =D21 -> 26100.65 | F16: =0 -> 0
A17: Operating Cash Flow | B17: =B11 -> 73.88 | C17: =C11 -> 22589.53 | D17: =D11 -> 32068.49 | E17: =E11 -> 30257.96 | F17: =F11 -> 84989.86
A18: Owner Contributions | B18: =SUMIF('Monthly_P&L'!$C$4:$AG$4,B$15,'Monthly_P&L'!$C$52:$AG$52) -> 0 | C18: =SUMIF('Monthly_P&L'!$C$4:$AG$4,C$15,'Monthly_P&L'!$C$52:$AG$52) -> 5875 | D18: =SUMIF('Monthly_P&L'!$C$4:$AG$4,D$15,'Monthly_P&L'!$C$52:$AG$52) -> 0 | E18: =SUMIF('Monthly_P&L'!$C$4:$AG$4,E$15,'Monthly_P&L'!$C$52:$AG$52) -> 0 | F18: =SUM(B18:E18) -> 5875
A19: Owner / Partner Distributions | B19: =SUMIF('Monthly_P&L'!$C$4:$AG$4,B$15,'Monthly_P&L'!$C$51:$AG$51) -> 0 | C19: =SUMIF('Monthly_P&L'!$C$4:$AG$4,C$15,'Monthly_P&L'!$C$51:$AG$51) -> 15150 | D19: =SUMIF('Monthly_P&L'!$C$4:$AG$4,D$15,'Monthly_P&L'!$C$51:$AG$51) -> 19356.25 | E19: =SUMIF('Monthly_P&L'!$C$4:$AG$4,E$15,'Monthly_P&L'!$C$51:$AG$51) -> 21340.5 | F19: =SUM(B19:E19) -> 55846.75
A20: Net Cash Movement | B20: =B17+B18-B19 -> 73.88 | C20: =C17+C18-C19 -> 13314.53 | D20: =D17+D18-D19 -> 12712.24 | E20: =E17+E18-E19 -> 8917.46 | F20: =SUM(B20:E20) -> 35018.11
A21: Ending Cash Position | B21: =B16+B20 -> 73.88 | C21: =C16+C20 -> 13388.41 | D21: =D16+D20 -> 26100.65 | E21: =E16+E20 -> 35018.11 | F21: =E21 -> 35018.11
A24: Financial Position Snapshot | B24: 2019 | C24: 2020 | D24: 2021 | E24: 2022 | F24: Current View
A25: Cash Position | B25: =B21 -> 73.88 | C25: =C21 -> 13388.41 | D25: =D21 -> 26100.65 | E25: =E21 -> 35018.11 | F25: =E25 -> 35018.11
A26: Ending Inventory (not separately counted) | B26: =Inventory_Rollforward!B20 -> 0 | C26: =Inventory_Rollforward!C20 -> 0 | D26: =Inventory_Rollforward!D20 -> 0 | E26: =Inventory_Rollforward!E20 -> 0 | F26: =E26 -> 0
A27: Fixed Assets, Net | B27: =Fixed_Asset_Depreciation!B11 -> 4039.4 | C27: =Fixed_Asset_Depreciation!C11 -> 3267.8 | D27: =Fixed_Asset_Depreciation!D11 -> 2496.2 | E27: =Fixed_Asset_Depreciation!E11 -> 2046.1 | F27: =E27 -> 2046.1
A28: Estimated Net Asset Position | B28: =SUM(B25:B27) -> 4113.28 | C28: =SUM(C25:C27) -> 16656.21 | D28: =SUM(D25:D27) -> 28596.85 | E28: =SUM(E25:E27) -> 37064.21 | F28: =E28 -> 37064.21
A30: Memo: Owner Contributions, Cumulative | B30: =B18 -> 0 | C30: =B18+C18 -> 5875 | D30: =B18+C18+D18 -> 5875 | E30: =B18+C18+D18+E18 -> 5875 | F30: =E30 -> 5875
A31: Memo: Owner / Partner Distributions, Cumulative | B31: =B19 -> 0 | C31: =B19+C19 -> 15150 | D31: =B19+C19+D19 -> 34506.25 | E31: =B19+C19+D19+E19 -> 55846.75 | F31: =E31 -> 55846.75
A32: Memo: Operating Income, Cumulative | B32: =B17 -> 73.88 | C32: =B17+C17 -> 22663.41 | D32: =B17+C17+D17 -> 54731.9 | E32: =B17+C17+D17+E17 -> 84989.86 | F32: =E32 -> 84989.86
A34: Note | B34: The financial position snapshot is a management view using available cash, inventory, and fixed-asset information. It does not include a full AR/AP schedule.
A35: Inventory Cross-Reference | B35: Ending inventory is shown as $0 / not separately counted because physical ending quantities were not separately counted. See Inventory_Rollforward for weighted-average estimated ballet shoe COGS and merchandise margin analysis.
A36: Fixed Asset Cross-Reference | B36: Net fixed assets are summarized from the Fixed_Asset_Depreciation support schedule.

Sheet Cost_Per_Class_Model
A1: Claire Studio — Unit Economics & Cost-Per-Class Model
A2: Reference period: April 2021 | Amounts in $ | Blue font = editable assumptions
A4: 1. April 2021 Actuals and Core Inputs
A5: Metric | B5: Formula / Source | C5: Amount | D5: Notes
A6: Total Revenue | B6: Model_Data | C6: =Model_Data!P19 -> 12859.37 | D6: April 2021 revenue
A7: Class Revenue | B7: Choreography + Fitness + Karate | C7: =SUM(Model_Data!D19:F19) -> 11428.12 | D7: Core class revenue
A8: Hall / Event / Other Revenue | B8: Hall rental + event/photo + other | C8: =SUM(Model_Data!H19,Model_Data!N19:O19) -> 731.25 | D8: Second-hall support revenue
A9: Merchandise Revenue | B9: Ballet shoes + gymnastic suits + other | C9: =SUM(Model_Data!K19:M19) -> 700 | D9: Merchandise add-on revenue
A10: Operating Expenses | B10: Model_Data | C10: =Model_Data!AB19 -> 9310.21 | D10: Excludes owner distributions
A11: Operating Expenses Excl. Merchandise COGS | B11: Operating expenses - merchandise COGS | C11: =C10-SUM(Model_Data!X19:Y19) -> 8714.38 | D11: Used for class cost view
A12: Total Sessions per Month | B12: Editable schedule assumption | C12: =SUM(E18:E20) -> 76 | D12: Choreo + fitness + karate
A13: Cost per Session | B13: Operating expenses excl. COGS ÷ sessions | C13: =C11/C12 -> 114.66289 | D13: Blended studio view
A14: Cost per Student-Session | B14: Operating expenses excl. COGS ÷ student-sessions | C14: =C11/SUM(H18:H20) -> 15.024793 | D14: Blended attendance view
A16: 2. Program Unit Economics
A17: Program | B17: Primary Hall Use | C17: Actual Revenue | D17: Estimated Students | E17: Sessions / Month | F17: Revenue / Student | G17: Revenue / Session | H17: Student-Sessions | I17: Comment
A18: Choreography | B18: New hall | C18: =Model_Data!D19 -> 5953.12 | D18: 27 | E18: 36 | F18: =C18/D18 -> 220.48593 | G18: =C18/E18 -> 165.36444 | H18: =D18*(E18/3) -> 324 | I18: Main children’s program
A19: Fitness | B19: Old hall | C19: =Model_Data!F19 -> 2475 | D19: 14 | E19: 16 | F19: =C19/D19 -> 176.78571 | G19: =C19/E19 -> 154.6875 | H19: =D19*(E19/2) -> 112 | I19: Parent/adult fitness classes
A20: Karate | B20: Old hall | C20: =Model_Data!E19 -> 3000 | D20: 12 | E20: 24 | F20: =C20/D20 -> 250 | G20: =C20/E20 -> 125 | H20: =D20*(E20/2) -> 144 | I20: Revenue-share instructor model
A21: Total | B21: Studio | C21: =SUM(C18:C20) -> 11428.12 | D21: =SUM(D18:D20) -> 53 | E21: =SUM(E18:E20) -> 76 | F21: =C21/D21 -> 215.62491 | G21: =C21/E21 -> 150.37 | H21: =SUM(H18:H20) -> 580
A23: 3. Break-Even by Program
A24: Program | B24: Monthly Revenue | C24: Direct Variable Cost | D24: Shared Overhead Allocated | E24: Contribution / Student | F24: Break-Even Students | G24: Actual Students | H24: Above / (Below) BE | I24: Comment
A25: Choreography | B25: =C18 -> 5953.12 | C25: =0 -> 0 | D25: =(Model_Data!R19+Model_Data!S19+Model_Data!T19+Model_Data!U19+Model_Data!Z19+Model_Data!AA19)*(E18/$C$12) -> 2919.3774 | E25: =(B25-C25)/G25 -> 220.48593 | F25: =D25/E25 -> 13.240652 | G25: =D18 -> 27 | H25: =G25-F25 -> 13.759348 | I25: Healthy margin after shared overhead
A26: Fitness | B26: =C19 -> 2475 | C26: =0 -> 0 | D26: =(Model_Data!R19+Model_Data!S19+Model_Data!T19+Model_Data!U19+Model_Data!Z19+Model_Data!AA19)*(E19/$C$12) -> 1297.5011 | E26: =(B26-C26)/G26 -> 176.78571 | F26: =D26/E26 -> 7.3393999 | G26: =D19 -> 14 | H26: =G26-F26 -> 6.6606001 | I26: Profitable with modest enrollment
A27: Karate | B27: =C20 -> 3000 | C27: =B27*40% -> 1200 | D27: =(Model_Data!R19+Model_Data!S19+Model_Data!T19+Model_Data!U19+Model_Data!Z19+Model_Data!AA19)*(E20/$C$12) -> 1946.2516 | E27: =(B27-C27)/G27 -> 150 | F27: =D27/E27 -> 12.975011 | G27: =D20 -> 12 | H27: =G27-F27 -> -0.97501053 | I27: Close to break-even after instructor share
A28: Total / Studio | B28: =SUM(B25:B27) -> 11428.12 | C28: =SUM(C25:C27) -> 1200 | D28: =SUM(D25:D27) -> 6163.13 | E28: =(B28-C28)/G28 -> 192.9834 | F28: =D28/E28 -> 31.936064 | G28: =D21 -> 53 | H28: =G28-F28 -> 21.063936 | I28: Studio view includes shared cost structure
A31: 4. Management Takeaway
A32: Cost-per-class model | B32: Break-even students now use monthly contribution, not per-class contribution. This keeps the analysis realistic.
A33: April 2021 result | B33: April class revenue covered the studio cost structure, with added support from hall rental, merchandise, and other small revenue.
A34: Scheduling insight | B34: The two-hall setup improved scheduling: old hall for fitness/karate and new hall for choreography/subrent activity.

Sheet Accounting_Treatment
A1: Claire Studio — Accounting Treatment Summary
A2: Simple bridge from cash ledger categories to financial statement treatment. Amounts shown in $.
A4: Business Activity | B4: Account / Category | C4: Statement | D4: Treatment | E4: Model Logic | F4: Bridge Job Skill | G4: Notes
A5: Class subscriptions | B5: Revenue — Classes | C5: Income Statement | D5: Recognize as revenue when classes are delivered | E5: Included in Total Revenue | F5: Revenue reporting | G5: Core recurring revenue stream
A6: Hall rental | B6: Revenue — Hall Rental | C6: Income Statement | D6: Recognize as other operating revenue | E6: Included in Other Revenue | F6: Revenue classification | G6: Connected to second hall decision
A7: Ballet shoes / suits sold | B7: Merchandise Revenue | C7: Income Statement | D7: Recognize sale revenue and related COGS | E7: Revenue less item-level COGS | F7: Inventory / margin analysis | G7: Small resale activity
A8: Merchandise purchase / cost | B8: Inventory / COGS | C8: Income Statement / Support Schedule | D8: Track cost by item and release to COGS when sold | E8: Inventory_Rollforward | F8: COGS review | G8: No separate ending count beyond model assumptions
A9: Rent | B9: Rent Expense | C9: Income Statement | D9: Record as operating expense in the related business period | E9: Fixed cost in Monthly P&L | F9: Fixed-cost analysis | G9: Main capacity cost
A10: Utilities | B10: Utilities Expense | C10: Income Statement | D10: Record separately from base rent | E10: Operating expense | F10: Expense classification | G10: Important rent/utilities cleanup area
A11: Payroll | B11: Payroll / Instructor Cost | C11: Income Statement | D11: Record salary and instructor share as service cost | E11: Cost of services | F11: Payroll review | G11: Owner distributions excluded
A12: Owner contribution | B12: Owner Equity | C12: Cash Flow / Equity | D12: Treat as capital contribution, not revenue | E12: Owner contribution line | F12: Equity classification | G12: Supports clean operating results
A13: Owner / partner distribution | B13: Owner Draw / Distribution | C13: Cash Flow / Equity | D13: Treat as equity distribution, not expense | E13: Distribution line | F13: Close support | G13: Removed from operating expenses
A14: Equipment purchases | B14: Fixed Assets / Supplies | C14: Financial Position / Support Schedule | D14: Capitalize major items; expense small supplies | E14: Fixed_Asset_Depreciation | F14: Fixed asset tracking | G14: Simple management view
A15: Depreciation | B15: Depreciation Expense | C15: Income Statement / Support Schedule | D15: Allocate asset cost over useful life | E15: Supplemental accounting schedule | F15: Month-end adjustment logic | G15: Non-cash expense
A16: Taxes | B16: Business Tax Expense | C16: Income Statement | D16: Record as operating expense based on activity | E16: Operating expense | F16: Tax/accrual awareness | G16: Simplified small-business tax

Sheet Journal_Entries
A1: Claire Studio — Representative Journal Entries
A2: Representative entries only | Not a full transaction ledger | Amounts in $
A4: JE # | B4: Date | C4: Activity | D4: Debit Account | E4: Debit | F4: Credit Account | G4: Credit | H4: Balance Check | I4: Accounting Point
A5: JE-01 | I5: Class revenue recognized when services are provided.
A6: JE-02 | B6: 2021-04-30 | C6: Record hall rental / event / other revenue | D6: Cash | E6: 731.25 | F6: Other Operating Revenue | G6: 731.25 | H6: =E6-G6 -> 0 | I6: Subrent and small event income support second-hall utilization.
A7: JE-03 | B7: 2021-04-30 | C7: Record merchandise revenue | D7: Cash | E7: 700 | F7: Merchandise Revenue | G7: 700 | H7: =E7-G7 -> 0 | I7: Ballet shoes and gymnastic suits are tracked separately from class revenue.
A8: JE-04 | B8: 2021-04-30 | C8: Record rent expense | D8: Rent Expense | E8: 4675 | F8: Cash | G8: 4675 | H8: =E8-G8 -> 0 | I8: Rent is an operating expense; owner draws are not included.
A9: JE-05 | B9: 2021-04-30 | C9: Record utilities expense | D9: Utilities Expense | E9: 672.5 | F9: Cash | G9: 672.5 | H9: =E9-G9 -> 0 | I9: Utilities are classified separately from base rent.
A10: JE-06 | B10: 2021-04-30 | C10: Record payroll and instructor payments | D10: Payroll / Instructor Expense | E10: 2551.25 | F10: Cash | G10: 2551.25 | H10: =E10-G10 -> 0 | I10: Payroll and instructor payments are operating expenses.
A11: JE-07 | B11: 2021-04-30 | C11: Record advertising expense | D11: Advertising Expense | E11: 324.88 | F11: Cash | G11: 324.88 | H11: =E11-G11 -> 0 | I11: Marketing spend supports enrollment and retention.
A12: JE-08 | B12: 2021-04-30 | C12: Record merchandise cost of goods sold | D12: COGS — Merchandise | E12: 595.83 | F12: Inventory | G12: 595.83 | H12: =E12-G12 -> 0 | I12: COGS is matched to merchandise sales.
A13: JE-09 | B13: 2021-04-30 | C13: Record other operating expenses | D13: Other Operating Expense | E13: 490.75 | F13: Cash | G13: 490.75 | H13: =E13-G13 -> 0 | I13: Equipment/supplies and other operating costs are grouped for this example.
A14: JE-10 | B14: 2021-04-30 | C14: Record monthly depreciation | D14: Depreciation Expense | E14: 64.3 | F14: Accumulated Depreciation | G14: 64.3 | H14: =E14-G14 -> 0 | I14: Non-cash month-end adjustment.
A15: JE-11 | B15: 2021-04-30 | C15: Record owner / partner distribution | D15: Owner / Partner Distribution | E15: 3181.25 | F15: Cash | G15: 3181.25 | H15: =E15-G15 -> 0 | I15: Distribution is equity activity, not an operating expense.
A16: JE-12 | B16: 2020-09-30 | C16: Record owner contribution | D16: Cash | E16: 5875 | F16: Owner Capital | G16: 5875 | H16: =E16-G16 -> 0 | I16: Owner contribution is equity funding, not revenue.
A18: Control Check | D18: Total Debits | E18: =SUM(E5:E16) -> 19862.01 | F18: Total Credits | G18: =SUM(G5:G16) -> 19862.01 | H18: =E18-G18 -> 0
A20: Note: These entries demonstrate accounting treatment and month-end logic. The workbook is not intended to recreate every transaction-level journal entry.

Sheet Budget_Assumptions
A1: Claire Studio — 2021 Management Operating Budget
A2: Amounts shown in $ | Method: 2020 exit run-rate adjusted for planned second hall expansion
A4: Budget Type | B4: Historical Baseline | C4: Planning Adjustment | D4: Budget Purpose | E4: Key Business Question
A5: Management operating budget | B5: Sep–Dec 2020 exit run-rate | C5: Second hall expansion in 2021 | D5: Budget vs actual and variance explanation | E5: Did higher fixed cost support profitable growth?
A8: Category | B8: 2020 Exit Avg / Month | C8: 2020 Exit Annualized | D8: 2021 Budget | E8: Assumption / Rationale | F8: Type
A9: Total Revenue | B9: =SUMIFS(Model_Data!$P:$P,Model_Data!$A:$A,">=2020-09",Model_Data!$A:$A,"<=2020-12")/4 -> 8854.6875 | C9: =B9*12 -> 106256.25 | D9: =SUM(D10:D15) -> 117700 | E9: Sum of revenue lines | F9: Formula
A10: Choreography Revenue | B10: =SUMIFS(Model_Data!$D:$D,Model_Data!$A:$A,">=2020-09",Model_Data!$A:$A,"<=2020-12")/4 -> 4764.0625 | C10: =B10*12 -> 57168.75 | D10: 60000 | E10: Core program; modest growth | F10: Input
A11: Fitness Revenue | B11: =SUMIFS(Model_Data!$F:$F,Model_Data!$A:$A,">=2020-09",Model_Data!$A:$A,"<=2020-12")/4 -> 2073.4375 | C11: =B11*12 -> 24881.25 | D11: 19200 | E11: Recovery below late-2020 peak | F11: Input
A12: Karate Revenue | B12: =SUMIFS(Model_Data!$E:$E,Model_Data!$A:$A,">=2020-09",Model_Data!$A:$A,"<=2020-12")/4 -> 1750 | C12: =B12*12 -> 21000 | D12: 28800 | E12: Growth program; more space | F12: Input
A13: Hall Rental Income | B13: =SUMIFS(Model_Data!$H:$H,Model_Data!$A:$A,">=2020-09",Model_Data!$A:$A,"<=2020-12")/4 -> 0 | C13: =B13*12 -> 0 | D13: 5000 | E13: New rental opportunity | F13: Input
A14: Merchandise Revenue | B14: =(SUMIFS(Model_Data!$K:$K,Model_Data!$A:$A,">=2020-09",Model_Data!$A:$A,"<=2020-12")+SUMIFS(Model_Data!$L:$L,Model_Data!$A:$A,">=2020-09",Model_Data!$A:$A,"<=2020-12")+SUMIFS(Model_Data!$M:$M,Model_Data!$A:$A,">=2020-09",Model_Data!$A:$A,"<=2020-12"))/4 -> 262.5 | C14: =B14*12 -> 3150 | D14: 3200 | E14: Shoes and suits | F14: Input
A15: Events & Other Revenue | B15: =(SUMIFS(Model_Data!$N:$N,Model_Data!$A:$A,">=2020-09",Model_Data!$A:$A,"<=2020-12")+SUMIFS(Model_Data!$O:$O,Model_Data!$A:$A,">=2020-09",Model_Data!$A:$A,"<=2020-12"))/4 -> 4.6875 | C15: =B15*12 -> 56.25 | D15: 1500 | E15: Events and miscellaneous income | F15: Input
A16: Total Expenses | B16: =SUMIFS(Model_Data!$AB:$AB,Model_Data!$A:$A,">=2020-09",Model_Data!$A:$A,"<=2020-12")/4 -> 5741.6325 | C16: =B16*12 -> 68899.59 | D16: =SUM(D17:D25) -> 88050 | E16: Sum of expense lines | F16: Formula
A17: Rent | B17: =SUMIFS(Model_Data!$R:$R,Model_Data!$A:$A,">=2020-09",Model_Data!$A:$A,"<=2020-12")/4 -> 2800 | C17: =B17*12 -> 33600 | D17: 53400 | E17: Fixed cost step-up | F17: Input
A18: Payroll | B18: =SUMIFS(Model_Data!$Q:$Q,Model_Data!$A:$A,">=2020-09",Model_Data!$A:$A,"<=2020-12")/4 -> 1382.5 | C18: =B18*12 -> 16590 | D18: 19000 | E18: Salary and activity-linked cost | F18: Input
A19: Utilities | B19: =SUMIFS(Model_Data!$S:$S,Model_Data!$A:$A,">=2020-09",Model_Data!$A:$A,"<=2020-12")/4 -> 135.955 | C19: =B19*12 -> 1631.46 | D19: 5400 | E19: Higher usage after expansion | F19: Input
A20: Advertising | B20: =SUMIFS(Model_Data!$T:$T,Model_Data!$A:$A,">=2020-09",Model_Data!$A:$A,"<=2020-12")/4 -> 390.94 | C20: =B20*12 -> 4691.28 | D20: 3600 | E20: Enrollment marketing | F20: Input
A21: Business Tax | B21: =SUMIFS(Model_Data!$U:$U,Model_Data!$A:$A,">=2020-09",Model_Data!$A:$A,"<=2020-12")/4 -> 31.125 | C21: =B21*12 -> 373.5 | D21: 1100 | E21: Based on business activity | F21: Input
A22: Merchandise COGS | B22: =(SUMIFS(Model_Data!$X:$X,Model_Data!$A:$A,">=2020-09",Model_Data!$A:$A,"<=2020-12")+SUMIFS(Model_Data!$Y:$Y,Model_Data!$A:$A,">=2020-09",Model_Data!$A:$A,"<=2020-12"))/4 -> 203.645 | C22: =B22*12 -> 2443.74 | D22: 1350 | E22: Cost of shoes and suits sold | F22: Input
A23: Class Supplies & Events | B23: =(SUMIFS(Model_Data!$V:$V,Model_Data!$A:$A,">=2020-09",Model_Data!$A:$A,"<=2020-12")+SUMIFS(Model_Data!$W:$W,Model_Data!$A:$A,">=2020-09",Model_Data!$A:$A,"<=2020-12"))/4 -> 0 | C23: =B23*12 -> 0 | D23: 900 | E23: Class and event support | F23: Input
A24: Equipment & Supplies | B24: =SUMIFS(Model_Data!$Z:$Z,Model_Data!$A:$A,">=2020-09",Model_Data!$A:$A,"<=2020-12")/4 -> 599.3725 | C24: =B24*12 -> 7192.47 | D24: 900 | E24: Small replacement purchases | F24: Input
A25: Other Operating | B25: =SUMIFS(Model_Data!$AA:$AA,Model_Data!$A:$A,">=2020-09",Model_Data!$A:$A,"<=2020-12")/4 -> 198.095 | C25: =B25*12 -> 2377.14 | D25: 2400 | E25: Miscellaneous operating costs | F25: Input
A26: Net Operating Income | B26: =B9-B16 -> 3113.055 | C26: =C9-C16 -> 37356.66 | D26: =D9-D16 -> 29650 | E26: Revenue minus expenses | F26: Formula
A29: Monthly Phasing Assumptions
A30: Month | B30: Jan | C30: Feb | D30: Mar | E30: Apr | F30: May | G30: Jun | H30: Jul | I30: Aug | J30: Sep | K30: Oct | L30: Nov | M30: Dec | N30: Check
A31: Revenue Weight | B31: 0.06 | C31: 0.065 | D31: 0.085 | E31: 0.09 | F31: 0.09 | G31: 0.075 | H31: 0.07 | I31: 0.07 | J31: 0.095 | K31: 0.095 | L31: 0.1 | M31: 0.105 | N31: =SUM(B31:M31) -> 1
A32: Hall Rental Weight | B32: 0 | C32: 0 | D32: 0 | E32: 0.08 | F32: 0.08 | G32: 0.08 | H32: 0.06 | I32: 0.06 | J32: 0.12 | K32: 0.14 | L32: 0.18 | M32: 0.2 | N32: =SUM(B32:M32) -> 1
A33: Rent Plan | B33: 2800 | C33: 3850 | D33: 4675 | E33: 4675 | F33: 4675 | G33: 4675 | H33: 4675 | I33: 4675 | J33: 4675 | K33: 4675 | L33: 4675 | M33: 4675 | N33: =SUM(B33:M33) -> 53400
A34: Utilities Plan | B34: 300 | C34: 350 | D34: 475 | E34: 475 | F34: 475 | G34: 475 | H34: 475 | I34: 475 | J34: 475 | K34: 475 | L34: 475 | M34: 475 | N34: =SUM(B34:M34) -> 5400
A35: Advertising Plan | B35: 250 | C35: 250 | D35: 350 | E35: 350 | F35: 350 | G35: 200 | H35: 200 | I35: 250 | J35: 400 | K35: 400 | L35: 300 | M35: 300 | N35: =SUM(B35:M35) -> 3600
A38: Monthly Budget by Category
A39: Category | B39: Jan | C39: Feb | D39: Mar | E39: Apr | F39: May | G39: Jun | H39: Jul | I39: Aug | J39: Sep | K39: Oct | L39: Nov | M39: Dec | N39: Total
A40: Choreography Revenue | B40: =$D$10*B$31 -> 3600 | C40: =$D$10*C$31 -> 3900 | D40: =$D$10*D$31 -> 5100 | E40: =$D$10*E$31 -> 5400 | F40: =$D$10*F$31 -> 5400 | G40: =$D$10*G$31 -> 4500 | H40: =$D$10*H$31 -> 4200 | I40: =$D$10*I$31 -> 4200 | ... M40: =$D$10*M$31 -> 6300 | N40: =SUM(B40:M40) -> 60000
A41: Fitness Revenue | B41: =$D$11*B$31 -> 1152 | C41: =$D$11*C$31 -> 1248 | D41: =$D$11*D$31 -> 1632 | E41: =$D$11*E$31 -> 1728 | F41: =$D$11*F$31 -> 1728 | G41: =$D$11*G$31 -> 1440 | H41: =$D$11*H$31 -> 1344 | I41: =$D$11*I$31 -> 1344 | ... M41: =$D$11*M$31 -> 2016 | N41: =SUM(B41:M41) -> 19200
A42: Karate Revenue | B42: =$D$12*B$31 -> 1728 | C42: =$D$12*C$31 -> 1872 | D42: =$D$12*D$31 -> 2448 | E42: =$D$12*E$31 -> 2592 | F42: =$D$12*F$31 -> 2592 | G42: =$D$12*G$31 -> 2160 | H42: =$D$12*H$31 -> 2016 | I42: =$D$12*I$31 -> 2016 | ... M42: =$D$12*M$31 -> 3024 | N42: =SUM(B42:M42) -> 28800
A43: Hall Rental Income | B43: =$D$13*B$32 -> 0 | C43: =$D$13*C$32 -> 0 | D43: =$D$13*D$32 -> 0 | E43: =$D$13*E$32 -> 400 | F43: =$D$13*F$32 -> 400 | G43: =$D$13*G$32 -> 400 | H43: =$D$13*H$32 -> 300 | I43: =$D$13*I$32 -> 300 | ... M43: =$D$13*M$32 -> 1000 | N43: =SUM(B43:M43) -> 5000
A44: Merchandise Revenue | B44: =$D$14*B$31 -> 192 | C44: =$D$14*C$31 -> 208 | D44: =$D$14*D$31 -> 272 | E44: =$D$14*E$31 -> 288 | F44: =$D$14*F$31 -> 288 | G44: =$D$14*G$31 -> 240 | H44: =$D$14*H$31 -> 224 | I44: =$D$14*I$31 -> 224 | ... M44: =$D$14*M$31 -> 336 | N44: =SUM(B44:M44) -> 3200
A45: Events & Other Revenue | B45: =$D$15*B$31 -> 90 | C45: =$D$15*C$31 -> 97.5 | D45: =$D$15*D$31 -> 127.5 | E45: =$D$15*E$31 -> 135 | F45: =$D$15*F$31 -> 135 | G45: =$D$15*G$31 -> 112.5 | H45: =$D$15*H$31 -> 105 | I45: =$D$15*I$31 -> 105 | ... M45: =$D$15*M$31 -> 157.5 | N45: =SUM(B45:M45) -> 1500
A46: Total Revenue | B46: =SUM(B40:B45) -> 6762 | C46: =SUM(C40:C45) -> 7325.5 | D46: =SUM(D40:D45) -> 9579.5 | E46: =SUM(E40:E45) -> 10543 | F46: =SUM(F40:F45) -> 10543 | G46: =SUM(G40:G45) -> 8852.5 | H46: =SUM(H40:H45) -> 8189 | I46: =SUM(I40:I45) -> 8189 | ... M46: =SUM(M40:M45) -> 12833.5 | N46: =SUM(B46:M46) -> 117700
A48: Payroll | B48: =$D$18*B$31 -> 1140 | C48: =$D$18*C$31 -> 1235 | D48: =$D$18*D$31 -> 1615 | E48: =$D$18*E$31 -> 1710 | F48: =$D$18*F$31 -> 1710 | G48: =$D$18*G$31 -> 1425 | H48: =$D$18*H$31 -> 1330 | I48: =$D$18*I$31 -> 1330 | ... M48: =$D$18*M$31 -> 1995 | N48: =SUM(B48:M48) -> 19000
A49: Rent | B49: =B$33 -> 2800 | C49: =C$33 -> 3850 | D49: =D$33 -> 4675 | E49: =E$33 -> 4675 | F49: =F$33 -> 4675 | G49: =G$33 -> 4675 | H49: =H$33 -> 4675 | I49: =I$33 -> 4675 | ... M49: =M$33 -> 4675 | N49: =SUM(B49:M49) -> 53400
A50: Utilities | B50: =B$34 -> 300 | C50: =C$34 -> 350 | D50: =D$34 -> 475 | E50: =E$34 -> 475 | F50: =F$34 -> 475 | G50: =G$34 -> 475 | H50: =H$34 -> 475 | I50: =I$34 -> 475 | ... M50: =M$34 -> 475 | N50: =SUM(B50:M50) -> 5400
A51: Advertising | B51: =B$35 -> 250 | C51: =C$35 -> 250 | D51: =D$35 -> 350 | E51: =E$35 -> 350 | F51: =F$35 -> 350 | G51: =G$35 -> 200 | H51: =H$35 -> 200 | I51: =I$35 -> 250 | ... M51: =M$35 -> 300 | N51: =SUM(B51:M51) -> 3600
A52: Business Tax | B52: =$D$21*B$31 -> 66 | C52: =$D$21*C$31 -> 71.5 | D52: =$D$21*D$31 -> 93.5 | E52: =$D$21*E$31 -> 99 | F52: =$D$21*F$31 -> 99 | G52: =$D$21*G$31 -> 82.5 | H52: =$D$21*H$31 -> 77 | I52: =$D$21*I$31 -> 77 | ... M52: =$D$21*M$31 -> 115.5 | N52: =SUM(B52:M52) -> 1100
A53: Merchandise COGS | B53: =$D$22*B$31 -> 81 | C53: =$D$22*C$31 -> 87.75 | D53: =$D$22*D$31 -> 114.75 | E53: =$D$22*E$31 -> 121.5 | F53: =$D$22*F$31 -> 121.5 | G53: =$D$22*G$31 -> 101.25 | H53: =$D$22*H$31 -> 94.5 | I53: =$D$22*I$31 -> 94.5 | ... M53: =$D$22*M$31 -> 141.75 | N53: =SUM(B53:M53) -> 1350
A54: Class Supplies & Events | B54: =$D$23/12 -> 75 | C54: =$D$23/12 -> 75 | D54: =$D$23/12 -> 75 | E54: =$D$23/12 -> 75 | F54: =$D$23/12 -> 75 | G54: =$D$23/12 -> 75 | H54: =$D$23/12 -> 75 | I54: =$D$23/12 -> 75 | ... M54: =$D$23/12 -> 75 | N54: =SUM(B54:M54) -> 900
A55: Equipment & Supplies | B55: =$D$24/12 -> 75 | C55: =$D$24/12 -> 75 | D55: =$D$24/12 -> 75 | E55: =$D$24/12 -> 75 | F55: =$D$24/12 -> 75 | G55: =$D$24/12 -> 75 | H55: =$D$24/12 -> 75 | I55: =$D$24/12 -> 75 | ... M55: =$D$24/12 -> 75 | N55: =SUM(B55:M55) -> 900
A56: Other Operating | B56: =$D$25/12 -> 200 | C56: =$D$25/12 -> 200 | D56: =$D$25/12 -> 200 | E56: =$D$25/12 -> 200 | F56: =$D$25/12 -> 200 | G56: =$D$25/12 -> 200 | H56: =$D$25/12 -> 200 | I56: =$D$25/12 -> 200 | ... M56: =$D$25/12 -> 200 | N56: =SUM(B56:M56) -> 2400
A57: Total Expenses | B57: =SUM(B48:B56) -> 4987 | C57: =SUM(C48:C56) -> 6194.25 | D57: =SUM(D48:D56) -> 7673.25 | E57: =SUM(E48:E56) -> 7780.5 | F57: =SUM(F48:F56) -> 7780.5 | G57: =SUM(G48:G56) -> 7308.75 | H57: =SUM(H48:H56) -> 7201.5 | I57: =SUM(I48:I56) -> 7251.5 | ... M57: =SUM(M48:M56) -> 8052.25 | N57: =SUM(B57:M57) -> 88050
A59: Net Operating Income | B59: =B46-B57 -> 1775 | C59: =C46-C57 -> 1131.25 | D59: =D46-D57 -> 1906.25 | E59: =E46-E57 -> 2762.5 | F59: =F46-F57 -> 2762.5 | G59: =G46-G57 -> 1543.75 | H59: =H46-H57 -> 987.5 | I59: =I46-I57 -> 937.5 | ... N59: =N46-N57 -> 29650

Sheet Inventory_Rollforward
A1: Claire Studio — Inventory & Merchandise Margin
A2: Simple support schedule for merchandise revenue and recorded/estimated costs. Amounts shown in $.
A4: Inventory / Merchandise View | B4: 2019 | C4: 2020 | D4: 2021 | E4: 2022 | F4: All Periods
A5: Ballet Shoes Revenue | B5: =Annual_KPIs!B41 -> 0 | C5: =Annual_KPIs!C41 -> 568.75 | D5: =Annual_KPIs!D41 -> 926.25 | E5: =Annual_KPIs!E41 -> 156.25 | F5: =SUM(B5:E5) -> 1651.25
A6: Ballet Shoes Estimated COGS (weighted-average) | B6: =Annual_KPIs!B42 -> 0 | C6: =Annual_KPIs!C42 -> 371.55 | D6: =Annual_KPIs!D42 -> 605.12 | E6: =Annual_KPIs!E42 -> 102.08 | F6: =SUM(B6:E6) -> 1078.75
A7: Ballet Shoes Gross Profit (before inventory adjustment) | B7: =B5-B6 -> 0 | C7: =C5-C6 -> 197.2 | D7: =D5-D6 -> 321.13 | E7: =E5-E6 -> 54.17 | F7: =F5-F6 -> 572.5
A8: Ballet Shoes Gross Margin | B8: =IFERROR(B7/B5,0) -> 0 | C8: =IFERROR(C7/C5,0) -> 0.34672527 | D8: =IFERROR(D7/D5,0) -> 0.34669906 | E8: =IFERROR(E7/E5,0) -> 0.346688 | F8: =IFERROR(F7/F5,0) -> 0.34670704
A10: Gymnastic Suits Revenue | B10: =Annual_KPIs!B45 -> 0 | C10: =Annual_KPIs!C45 -> 2075 | D10: =Annual_KPIs!D45 -> 2068.75 | E10: =Annual_KPIs!E45 -> 425 | F10: =SUM(B10:E10) -> 4568.75
A11: Gymnastic Suits COGS | B11: =Annual_KPIs!B46 -> 0 | C11: =Annual_KPIs!C46 -> 1559.38 | D11: =Annual_KPIs!D46 -> 1275 | E11: =Annual_KPIs!E46 -> 300 | F11: =SUM(B11:E11) -> 3134.38
A12: Gymnastic Suits Gross Profit | B12: =B10-B11 -> 0 | C12: =C10-C11 -> 515.62 | D12: =D10-D11 -> 793.75 | E12: =E10-E11 -> 125 | F12: =F10-F11 -> 1434.37
A13: Gymnastic Suits Gross Margin | B13: =IFERROR(B12/B10,0) -> 0 | C13: =IFERROR(C12/C10,0) -> 0.24849157 | D13: =IFERROR(D12/D10,0) -> 0.3836858 | E13: =IFERROR(E12/E10,0) -> 0.29411765 | F13: =IFERROR(F12/F10,0) -> 0.31395239
A15: Total Merchandise Revenue | B15: =B5+B10 -> 0 | C15: =C5+C10 -> 2643.75 | D15: =D5+D10 -> 2995 | E15: =E5+E10 -> 581.25 | F15: =SUM(B15:E15) -> 6220
A16: Total Merchandise COGS | B16: =B6+B11 -> 0 | C16: =C6+C11 -> 1930.93 | D16: =D6+D11 -> 1880.12 | E16: =E6+E11 -> 402.08 | F16: =F6+F11 -> 4213.13
A17: Total Merchandise Gross Profit | B17: =B15-B16 -> 0 | C17: =C15-C16 -> 712.82 | D17: =D15-D16 -> 1114.88 | E17: =E15-E16 -> 179.17 | F17: =F15-F16 -> 2006.87
A18: Total Merchandise Gross Margin | B18: =IFERROR(B17/B15,0) -> 0 | C18: =IFERROR(C17/C15,0) -> 0.26962459 | D18: =IFERROR(D17/D15,0) -> 0.37224708 | E18: =IFERROR(E17/E15,0) -> 0.30824946 | F18: =IFERROR(F17/F15,0) -> 0.32264791
A20: Ending Inventory (not separately counted) | B20: 0 | C20: 0 | D20: 0 | E20: 0 | F20: =E20 -> 0
A21: Inventory Note | B21: COGS and margin are supported by item-level revenue and cost records. Ending inventory is not separately counted in this model.
A22: Clarifying Notes
A23: Ballet Shoes COGS Method | B23: Weighted-average estimated COGS is used because exact sale-by-sale inventory matching was not fully documented. Total recorded purchase cost of $1,078.75 is allocated by sales-period revenue.
A24: Inventory Treatment | B24: Ending inventory was not separately counted, so ending inventory remains $0 / not separately counted in the model.
A25: Use in Model | B25: This schedule supports merchandise margin analysis and Management_Financials; the clean cash ledger remains the detailed audit trail.

Sheet Fixed_Asset_Depreciation
A1: Claire Studio — Fixed Asset Depreciation
A2: Simple straight-line depreciation support schedule for management reporting. Amounts shown in $.
A4: Asset Group | B4: In Service | C4: Cost | D4: Useful Life (Months) | E4: Monthly Depreciation | F4: Accumulated Depreciation | G4: Net Book Value | H4: Year-End NBV
A5: Studio Equipment | B5: 2019-11 | C5: 3646 | D5: 73 | E5: 49.8 | F5: =E5*33 -> 1643.4 | G5: =C5-F5 -> 2002.6 | H5: =G5 -> 2002.6
A6: Leasehold Improvements | B6: 2019-11 | C6: 522 | D6: 36 | E6: 14.5 | F6: =MIN(C6,E6*33) -> 478.5 | G6: =C6-F6 -> 43.5 | H6: =G6 -> 43.5
A8: Total Fixed Assets | C8: =SUM(C5:C6) -> 4168 | E8: =SUM(E5:E6) -> 64.3 | F8: =SUM(F5:F6) -> 2121.9 | G8: =SUM(G5:G6) -> 2046.1 | H8: =SUM(H5:H6) -> 2046.1
A10: Year-End Net Book Value | B10: 2019 | C10: 2020 | D10: 2021 | E10: 2022
A11: Ending NBV | B11: =MAX(0,SUM($C$5:$C$6)-($E$5+$E$6)*2) -> 4039.4 | C11: =MAX(0,SUM($C$5:$C$6)-($E$5+$E$6)*14) -> 3267.8 | D11: =MAX(0,SUM($C$5:$C$6)-($E$5+$E$6)*26) -> 2496.2 | E11: =MAX(0,SUM($C$5:$C$6)-($E$5+$E$6)*33) -> 2046.1
A13: Depreciation Note | B13: Useful lives are simplified management assumptions. Depreciation continues monthly during closure periods.
A14: Schedule Scope Note | B14: This schedule summarizes supported asset groups and uses point-in-time NBV calculations based on elapsed depreciation months. It is a management support schedule, not a full fixed-asset subledger.
A15: Cross-Reference | B15: Net fixed assets from this tab feed the Financial Position Snapshot in Management_Financials.

Sheet Model_Data
A1: Claire Studio — Model Data (Structured Source) | Feeds Monthly_PL and all downstream tabs | Source: Cleaned cash-ledger transaction records; weighted-average ballet shoe COGS applied
A2: Source: Original cash-ledger transaction records, Nov 2019–Jul 2022 | Amounts shown in $ | Ballet shoe costs use weighted-average estimated COGS for consistency with Inventory_Rollforward.
A3: Period | B3: Year | C3: Month | D3: Revenue - Choreography | E3: Revenue - Karate | F3: Revenue - Fitness | G3: Revenue - Gymnastics | H3: Revenue - Hall Rental Income | I3: Revenue - Utilities Reimbursement | J3: Revenue - Merchandise and Supplies Sales | K3: Revenue - Ballet Shoes | L3: Revenue - Gymnastic Suits | M3: Revenue - Merchandise - Other | N3: Revenue - Event / Photo Revenue | O3: Revenue - Other | P3: Total Revenue | Q3: Expense - Payroll | R3: Expense - Rent | S3: Expense - Utilities | T3: Expense - Advertising | U3: Expense - Taxes | V3: Expense - Events and Competitions | W3: Expense - Class Supplies | X3: Expense - Gymnastic Suit Cost | Y3: Expense - Ballet Shoe Cost | Z3: Equipment / Supplies Purchase | AA3: Expense - Other Operating Expense | AB3: Total Operating Expenses | AC3: Net Operating Cash Flow | AD3: Owner Contribution | AE3: Owner / Partner Distribution | AF3: Distribution Notes | AG3: Net Cash Movement Including Owners
A4: 2019-11 | B4: 2019 | C4: Nov | D4: 1375 | E4: 0 | F4: 0 | G4: 300 | H4: 0 | I4: 0 | J4: 0 | K4: 0 | L4: 0 | M4: 0 | N4: 0 | O4: 125 | P4: 1800 | Q4: 0 | R4: 0 | S4: 562.6 | T4: 0 | U4: 0 | V4: 0 | W4: 0 | X4: 0 | Y4: 0 | Z4: 0 | AA4: 0 | AB4: 562.6 | AC4: 1237.4 | AD4: 0 | AE4: 0 | AG4: 1237.4
A5: 2019-12 | B5: 2019 | C5: Dec | D5: 1875 | E5: 0 | F5: 0 | G5: 900 | H5: 0 | I5: 0 | J5: 0 | K5: 0 | L5: 0 | M5: 0 | N5: 0 | O5: 0 | P5: 2775 | Q5: 0 | R5: 2775 | S5: 702.27 | T5: 50 | U5: 0 | V5: 0 | W5: 0 | X5: 0 | Y5: 0 | Z5: 200 | AA5: 211.25 | AB5: 3938.52 | AC5: -1163.52 | AD5: 0 | AE5: 0 | AG5: -1163.52
A6: 2020-01 | B6: 2020 | C6: Jan | D6: 3237.5 | E6: 0 | F6: 0 | G6: 1437.5 | H6: 0 | I6: 0 | J6: 0 | K6: 225 | L6: 375 | M6: 0 | N6: 0 | O6: 200 | P6: 5475 | Q6: 462.5 | R6: 2800 | S6: 399 | T6: 75 | U6: 0 | V6: 0 | W6: 0 | X6: 234.38 | Y6: 146.99 | Z6: 0 | AA6: 117.12 | AB6: 4234.99 | AC6: 1240.01 | AD6: 0 | AE6: 150 | AG6: 1090.01
A7: 2020-02 | B7: 2020 | C7: Feb | D7: 3162.5 | E7: 0 | F7: 0 | G7: 1075 | H7: 0 | I7: 0 | J7: 0 | K7: 50 | L7: 250 | M7: 0 | N7: 0 | O7: 400 | P7: 4937.5 | Q7: 412.5 | R7: 2800 | S7: 299.5 | T7: 112.5 | U7: 0 | V7: 0 | W7: 50 | X7: 0 | Y7: 32.66 | Z7: 0 | AA7: 199.75 | AB7: 3906.91 | AC7: 1030.59 | AD7: 0 | AE7: 537.5 | AG7: 493.09
A8: 2020-03 | B8: 2020 | C8: Mar | D8: 2775 | E8: 0 | F8: 656.25 | G8: 1475 | H8: 0 | I8: 0 | J8: 0 | K8: 50 | L8: 312.5 | M8: 0 | N8: 0 | O8: 0 | P8: 5268.75 | Q8: 150 | R8: 2800 | S8: 612 | T8: 125 | U8: 57.75 | V8: 0 | W8: 131.25 | X8: 81.25 | Y8: 32.66 | Z8: 974.25 | AA8: 98.75 | AB8: 5062.91 | AC8: 205.84 | AD8: 0 | AE8: 150 | AG8: 55.84
A9: 2020-06 | B9: 2020 | C9: Jun | D9: 3612.5 | E9: 0 | F9: 1037.5 | G9: 593.75 | H9: 0 | I9: 0 | J9: 0 | K9: 0 | L9: 0 | M9: 0 | N9: 0 | O9: 0 | P9: 5243.75 | Q9: 625 | R9: 1401.38 | S9: 183.27 | T9: 150 | U9: 22.5 | V9: 0 | W9: 0 | X9: 0 | Y9: 0 | Z9: 686.87 | AA9: 461.12 | AB9: 3530.14 | AC9: 1713.61 | AD9: 0 | AE9: 625 | AF9: Distribution total set per owner review: $625.00 | AG9: 1088.61
A10: 2020-07 | B10: 2020 | C10: Jul | D10: 3312.5 | E10: 0 | F10: 1762.5 | G10: 1162.5 | H10: 0 | I10: 0 | J10: 0 | K10: 87.5 | L10: 0 | M10: 0 | N10: 0 | O10: 225 | P10: 6550 | Q10: 862.5 | R10: 1401.38 | S10: 30.45 | T10: 125 | U10: 0 | V10: 0 | W10: 0 | X10: 531.25 | Y10: 57.16 | Z10: 0 | AA10: 41.37 | AB10: 3049.11 | AC10: 3500.89 | AD10: 0 | AE10: 1750 | AG10: 1750.89
A11: 2020-08 | B11: 2020 | C11: Aug | D11: 3006.25 | E11: 0 | F11: 2206.25 | G11: 875 | H11: 0 | I11: 0 | J11: 0 | K11: 0 | L11: 243.75 | M11: 0 | N11: 0 | O11: 12.5 | P11: 6343.75 | Q11: 750 | R11: 2800 | S11: 91.13 | T11: 168.75 | U11: 0 | V11: 0 | W11: 87.5 | X11: 0 | Y11: 0 | Z11: 0 | AA11: 0 | AB11: 3897.38 | AC11: 2446.37 | AD11: 0 | AE11: 5312.5 | AF11: Distribution total set per owner review: $5,312.50. | AG11: -2866.13
A12: 2020-09 | B12: 2020 | C12: Sep | D12: 6037.5 | E12: 2000 | F12: 2037.5 | G12: 0 | H12: 0 | I12: 0 | J12: 0 | K12: 93.75 | L12: 650 | M12: 0 | N12: 0 | O12: 18.75 | P12: 10837.5 | Q12: 1867.5 | R12: 2800 | S12: 103 | T12: 467.5 | U12: 0 | V12: 0 | W12: 0 | X12: 400 | Y12: 61.25 | Z12: 1909.99 | AA12: 408.13 | AB12: 8017.37 | AC12: 2820.13 | AD12: 5875 | AE12: 1625 | AF12: Distribution total set per owner review: $1,625.00 | AG12: 7070.13
A13: 2020-10 | B13: 2020 | C13: Oct | D13: 5012.5 | E13: 1250 | F13: 2306.25 | G13: 0 | H13: 0 | I13: 0 | J13: 0 | K13: 0 | L13: 0 | M13: 0 | N13: 0 | O13: 0 | P13: 8568.75 | Q13: 562.5 | R13: 2800 | S13: 76.88 | T13: 320.75 | U13: 0 | V13: 0 | W13: 0 | X13: 0 | Y13: 0 | Z13: 0 | AA13: 106.25 | AB13: 3866.38 | AC13: 4702.37 | AD13: 0 | AE13: 0 | AF13: Distribution total set per owner review: $0.00 | AG13: 4702.37
A14: 2020-11 | B14: 2020 | C14: Nov | D14: 3612.5 | E14: 1750 | F14: 2018.75 | G14: 0 | H14: 0 | I14: 0 | J14: 0 | K14: 62.5 | L14: 0 | M14: 0 | N14: 0 | O14: 0 | P14: 7443.75 | Q14: 1550 | R14: 2800 | S14: 95.19 | T14: 660.76 | U14: 0 | V14: 0 | W14: 0 | X14: 0 | Y14: 40.83 | Z14: 300 | AA14: 45 | AB14: 5491.78 | AC14: 1951.97 | AD14: 0 | AE14: 2625 | AG14: -673.03
A15: 2020-12 | B15: 2020 | C15: Dec | D15: 4393.75 | E15: 2000 | F15: 1931.25 | G15: 0 | H15: 0 | I15: 0 | J15: 0 | K15: 0 | L15: 243.75 | M15: 0 | N15: 0 | O15: 0 | P15: 8568.75 | Q15: 1550 | R15: 2800 | S15: 268.75 | T15: 114.75 | U15: 124.5 | V15: 0 | W15: 0 | X15: 312.5 | Y15: 0 | Z15: 187.5 | AA15: 233 | AB15: 5591 | AC15: 2977.75 | AD15: 0 | AE15: 2375 | AG15: 602.75
A16: 2021-01 | B16: 2021 | C16: Jan | D16: 3512.5 | E16: 1312.5 | F16: 1806.25 | G16: 0 | H16: 0 | I16: 0 | J16: 0 | K16: 0 | L16: 0 | M16: 0 | N16: 0 | O16: 0 | P16: 6631.25 | Q16: 400 | R16: 2802.5 | S16: 295.57 | T16: 197.5 | U16: 87.5 | V16: 0 | W16: 0 | X16: 0 | Y16: 0 | Z16: 0 | AA16: 154.38 | AB16: 3937.45 | AC16: 2693.8 | AD16: 0 | AE16: 0 | AG16: 2693.8
A17: 2021-02 | B17: 2021 | C17: Feb | D17: 3362.5 | E17: 2125 | F17: 1056.25 | G17: 0 | H17: 0 | I17: 0 | J17: 0 | K17: 95 | L17: 0 | M17: 0 | N17: 46.24 | O17: 14.25 | P17: 6699.24 | Q17: 1325 | R17: 3856.75 | S17: 354.53 | T17: 91.75 | U17: 75.75 | V17: 97.25 | W17: 237.5 | X17: 0 | Y17: 62.06 | Z17: 170.62 | AA17: 162.38 | AB17: 6433.59 | AC17: 265.65 | AD17: 0 | AE17: 475 | AG17: -209.35
A18: 2021-03 | B18: 2021 | C18: Mar | D18: 6137.5 | E18: 1750 | F18: 2875 | G18: 0 | H18: 0 | I18: 0 | J18: 0 | K18: 125 | L18: 325 | M18: 0 | N18: 194.37 | O18: 0 | P18: 11406.87 | Q18: 900 | R18: 4675 | S18: 666.25 | T18: 350 | U18: 67.12 | V18: 0 | W18: 0 | X18: 250 | Y18: 81.66 | Z18: 500 | AA18: 158.12 | AB18: 7648.15 | AC18: 3758.72 | AD18: 0 | AE18: 175 | AG18: 3583.72
A19: 2021-04 | B19: 2021 | C19: Apr | D19: 5953.12 | E19: 3000 | F19: 2475 | G19: 0 | H19: 506.25 | I19: 0 | J19: 0 | K19: 156.25 | L19: 543.75 | M19: 0 | N19: 87.5 | O19: 137.5 | P19: 12859.37 | Q19: 2551.25 | R19: 4675 | S19: 672.5 | T19: 324.88 | U19: 0 | V19: 0 | W19: 0 | X19: 493.75 | Y19: 102.08 | Z19: 137.5 | AA19: 353.25 | AB19: 9310.21 | AC19: 3549.16 | AD19: 0 | AE19: 3181.25 | AF19: Distribution total set per owner review: $3,181.25 | AG19: 367.91
A20: 2021-05 | B20: 2021 | C20: May | D20: 5337.5 | E20: 2750 | F20: 1687.5 | G20: 0 | H20: 387.5 | I20: 0 | J20: 0 | K20: 62.5 | L20: 300 | M20: 0 | N20: 12.5 | O20: 393.75 | P20: 10931.25 | Q20: 1975 | R20: 4675 | S20: 452 | T20: 392.38 | U20: 127.12 | V20: 0 | W20: 268.75 | X20: 181.25 | Y20: 40.83 | Z20: 0 | AA20: 0 | AB20: 8112.33 | AC20: 2818.92 | AD20: 0 | AE20: 1750 | AF20: Distribution total set per owner review: $1,750.00 | AG20: 1068.92
A21: 2021-06 | B21: 2021 | C21: Jun | D21: 5350 | E21: 2000 | F21: 900 | G21: 0 | H21: 381.25 | I21: 0 | J21: 0 | K21: 93.75 | L21: 206.25 | M21: 0 | N21: 0 | O21: 370 | P21: 9301.25 | Q21: 1350 | R21: 4675 | S21: 432.85 | T21: 108.59 | U21: 128.25 | V21: 0 | W21: 0 | X21: 100 | Y21: 61.25 | Z21: 0 | AA21: 37.5 | AB21: 6893.44 | AC21: 2407.81 | AD21: 0 | AE21: 812.5 | AG21: 1595.31
A22: 2021-07 | B22: 2021 | C22: Jul | D22: 3883.75 | E22: 1750 | F22: 1175 | G22: 0 | H22: 87.5 | I22: 0 | J22: 0 | K22: 31.25 | L22: 100 | M22: 0 | N22: 0 | O22: 0 | P22: 7027.5 | Q22: 950 | R22: 4675 | S22: 429.25 | T22: 291.88 | U22: 103.88 | V22: 0 | W22: 0 | X22: 50 | Y22: 20.42 | Z22: 0 | AA22: 18.75 | AB22: 6539.18 | AC22: 488.32 | AD22: 0 | AE22: 375 | AG22: 113.32
A23: 2021-08 | B23: 2021 | C23: Aug | D23: 4875 | E23: 2000 | F23: 925 | G23: 0 | H23: 0 | I23: 0 | J23: 0 | K23: 0 | L23: 0 | M23: 0 | N23: 0 | O23: 0 | P23: 7800 | Q23: 1550 | R23: 4675 | S23: 854.62 | T23: 375 | U23: 69 | V23: 0 | W23: 0 | X23: 0 | Y23: 0 | Z23: 0 | AA23: 0 | AB23: 7523.62 | AC23: 276.38 | AD23: 0 | AE23: 0 | AG23: 276.38
A24: 2021-09 | B24: 2021 | C24: Sep | D24: 6662.5 | E24: 3375 | F24: 825 | G24: 0 | H24: 218.75 | I24: 0 | J24: 0 | K24: 62.5 | L24: 106.25 | M24: 0 | N24: 0 | O24: 0 | P24: 11250 | Q24: 2412.5 | R24: 4675 | S24: 329.72 | T24: 200.62 | U24: 94.12 | V24: 0 | W24: 0 | X24: 0 | Y24: 40.83 | Z24: 0 | AA24: 575 | AB24: 8327.79 | AC24: 2922.21 | AD24: 0 | AE24: 1000 | AF24: Distribution total set per owner review: $1,000.00 | AG24: 1922.21
A25: 2021-10 | B25: 2021 | C25: Oct | D25: 5768.75 | E25: 3437.5 | F25: 1000 | G25: 0 | H25: 468.75 | I25: 0 | J25: 0 | K25: 75 | L25: 212.5 | M25: 0 | N25: 0 | O25: 0 | P25: 10962.5 | Q25: 2625 | R25: 4675 | S25: 314.85 | T25: 430.65 | U25: 132.12 | V25: 0 | W25: 0 | X25: 150 | Y25: 49 | Z25: 62.5 | AA25: 125 | AB25: 8564.12 | AC25: 2398.38 | AD25: 0 | AE25: 2750 | AG25: -351.62
A26: 2021-11 | B26: 2021 | C26: Nov | D26: 5981.25 | E26: 3437.5 | F26: 1337.5 | G26: 0 | H26: 1931.25 | I26: 0 | J26: 0 | K26: 37.5 | L26: 0 | M26: 0 | N26: 0 | O26: 0 | P26: 12725 | Q26: 750 | R26: 4675 | S26: 400 | T26: 137.5 | U26: 98.38 | V26: 0 | W26: 0 | X26: 0 | Y26: 24.5 | Z26: 0 | AA26: 302.99 | AB26: 6388.37 | AC26: 6336.63 | AD26: 0 | AE26: 2312.5 | AF26: Distribution total set per owner review: $2,312.50 | AG26: 4024.13
A27: 2021-12 | B27: 2021 | C27: Dec | D27: 5987.5 | E27: 3593.75 | F27: 593.75 | G27: 0 | H27: 1847.87 | I27: 0 | J27: 0 | K27: 187.5 | L27: 275 | M27: 0 | N27: 537.5 | O27: 275 | P27: 13297.87 | Q27: 2546.88 | R27: 4687.5 | S27: 635.12 | T27: 210 | U27: 149.62 | V27: 0 | W27: 0 | X27: 50 | Y27: 122.49 | Z27: 47.12 | AA27: 696.63 | AB27: 9145.36 | AC27: 4152.51 | AD27: 0 | AE27: 6525 | AF27: Co-Founder excess over $750 salary moved to combined Owner / Partner Distribution: $1,375.00. | Distribution total set per owner review: $6,525.00. Includes Owner/Co-Founder distributions and any reclassified payroll amounts where applicable. | AG27: -2372.49
A28: 2022-01 | B28: 2022 | C28: Jan | D28: 6123.75 | E28: 3125 | F28: 1968.75 | G28: 0 | H28: 2625 | I28: 193.75 | J28: 0 | K28: 0 | L28: 0 | M28: 0 | N28: 0 | O28: 31.25 | P28: 14067.5 | Q28: 750 | R28: 4650 | S28: 588.12 | T28: 273.75 | U28: 151.75 | V28: 0 | W28: 0 | X28: 0 | Y28: 0 | Z28: 0 | AA28: 44.38 | AB28: 6458 | AC28: 7609.5 | AD28: 0 | AE28: 6100 | AF28: Distribution total set per owner review: $6,100.00 | AG28: 1509.5
A29: 2022-02 | B29: 2022 | C29: Feb | D29: 5154.25 | E29: 3983.75 | F29: 1500 | G29: 0 | H29: 2318.75 | I29: 0 | J29: 0 | K29: 0 | L29: 212.5 | M29: 0 | N29: 267.63 | O29: 0 | P29: 13436.88 | Q29: 2625 | R29: 4650 | S29: 905.57 | T29: 42 | U29: 134.62 | V29: 100 | W29: 0 | X29: 150 | Y29: 0 | Z29: 31.88 | AA29: 515.51 | AB29: 9154.58 | AC29: 4282.3 | AD29: 0 | AE29: 4490.5 | AG29: -208.2
A30: 2022-03 | B30: 2022 | C30: Mar | D30: 6437.5 | E30: 3281.25 | F30: 1500 | G30: 0 | H30: 3381.25 | I30: 0 | J30: 0 | K30: 81.25 | L30: 106.25 | M30: 0 | N30: 120 | O30: 18.75 | P30: 14926.25 | Q30: 2390.62 | R30: 4882.5 | S30: 738.81 | T30: 0 | U30: 103.38 | V30: 0 | W30: 0 | X30: 100 | Y30: 53.08 | Z30: 0 | AA30: 228.06 | AB30: 8496.45 | AC30: 6429.8 | AD30: 0 | AE30: 4750 | AG30: 1679.8
A31: 2022-04 | B31: 2022 | C31: Apr | D31: 5050 | E31: 3875 | F31: 937.5 | G31: 0 | H31: 3518.75 | I31: 0 | J31: 0 | K31: 37.5 | L31: 106.25 | M31: 0 | N31: 92.5 | O31: 18.75 | P31: 13636.25 | Q31: 2703.12 | R31: 4882.5 | S31: 744.62 | T31: 625 | U31: 165.75 | V31: 0 | W31: 0 | X31: 0 | Y31: 24.5 | Z31: 0 | AA31: 180.62 | AB31: 9326.11 | AC31: 4310.14 | AD31: 0 | AE31: 0 | AG31: 4310.14
A32: 2022-05 | B32: 2022 | C32: May | D32: 6531.25 | E32: 3437.5 | F32: 1000 | G32: 0 | H32: 2087.5 | I32: 0 | J32: 0 | K32: 0 | L32: 0 | M32: 0 | N32: 46.25 | O32: 56.25 | P32: 13158.75 | Q32: 2468.75 | R32: 4882.5 | S32: 482.52 | T32: 62.5 | U32: 128.06 | V32: 0 | W32: 0 | X32: 50 | Y32: 0 | Z32: 0 | AA32: 106.25 | AB32: 8180.58 | AC32: 4978.17 | AD32: 0 | AE32: 4750 | AG32: 228.17
A33: 2022-06 | B33: 2022 | C33: Jun | D33: 3972.5 | E33: 2560 | F33: 406.25 | G33: 0 | H33: 356.25 | I33: 0 | J33: 0 | K33: 37.5 | L33: 0 | M33: 0 | N33: 86.25 | O33: 0 | P33: 7418.75 | Q33: 2030 | R33: 2441.25 | S33: 335.8 | T33: 0 | U33: 139.5 | V33: 0 | W33: 0 | X33: 0 | Y33: 24.5 | Z33: 0 | AA33: 881.25 | AB33: 5852.3 | AC33: 1566.45 | AD33: 0 | AE33: 1250 | AF33: Distribution total set per owner review: $1,250.00 | AG33: 316.45
A34: 2022-07 | B34: 2022 | C34: Jul | D34: 3312.5 | E34: 625 | F34: 0 | G34: 0 | H34: 50 | I34: 0 | J34: 0 | K34: 0 | L34: 0 | M34: 0 | N34: 0 | O34: 0 | P34: 3987.5 | Q34: 0 | R34: 2441.25 | S34: 379.37 | T34: 0 | U34: 85.28 | V34: 0 | W34: 0 | X34: 0 | Y34: 0 | Z34: 0 | AA34: 0 | AB34: 2905.9 | AC34: 1081.6 | AD34: 0 | AE34: 0 | AG34: 1081.6
