Workbook

Sheet CONTRACT SETUP
A1: Company name: | B1: ABC Industrial Solutions
A2: Customer name: | B2: XYZ Manufacturing Corp
A3: Contract description: Custom Equipment Installation: | B3: 18-month fixed-price contract
A4: Contract value: | B4: 5000000
A5: Total estimated costs: | B5: 3800000
A6: Contract start date: | B6: 45839
A7: Contract end date: | B7: 46387
A8: Number of milestones: | B8: 4
A11: Milestone | B11: Event | C11: Billing % | D11: Billing Amount
A12: M1 | B12: Contract Signing | C12: 0.1 | D12: =$B$4*C12 -> 500000
A13: M2 | B13: Design Approval | C13: 0.2 | D13: =$B$4*C13 -> 1000000
A14: M3 | B14: Testing Complete | C14: 0.4 | D14: =$B$4*C14 -> 2000000
A15: M4 | B15: Final Delivery | C15: 0.3 | D15: =$B$4*C15 -> 1500000
A16: Total billing, %: | C16: =IF(SUM(C12:C15)=100%, "VALID", "ERROR") -> VALID | D16: =SUM(D12:D15) -> 5000000

Sheet REVENUE RECOGNITION SCHEDULE
A1: Month | B1: Planned Cost Incurred This Month | C1: Cumulative Costs Incurred | D1: % Complete | E1: Cumulative Revenue to Recognize | F1: Revenue Recognized This Month | G1: Amount Billed This Month | H1: Cumulative Billings | I1: Contract Asset / (Liability) | J1: Label
A2: 45839 | B2: 75000 | C2: =SUM($B$2:B2) -> 75000 | D2: =C2/'CONTRACT SETUP'!$B$5 -> 0.019736842 | E2: =D2*'CONTRACT SETUP'!$B$4 -> 98684.211 | F2: =E2 -> 98684.211 | G2: ='CONTRACT SETUP'!D12 -> 500000 | H2: =SUM($G$2:G2) -> 500000 | I2: =E2-H2 -> -401315.79 | J2: =IF(I2>0,"Contract Asset",IF(I2<0,"Contract Liability", "Balanced")) -> Contract Liability
A3: 45871 | B3: 150000 | C3: =SUM($B$2:B3) -> 225000 | D3: =C3/'CONTRACT SETUP'!$B$5 -> 0.059210526 | E3: =D3*'CONTRACT SETUP'!$B$4 -> 296052.63 | F3: =E3-E2 -> 197368.42 | G3: 0 | H3: =SUM($G$2:G3) -> 500000 | I3: =E3-H3 -> -203947.37 | J3: =IF(I3>0,"Contract Asset",IF(I3<0,"Contract Liability", "Balanced")) -> Contract Liability
A4: 45903 | B4: 173000 | C4: =SUM($B$2:B4) -> 398000 | D4: =C4/'CONTRACT SETUP'!$B$5 -> 0.10473684 | E4: =D4*'CONTRACT SETUP'!$B$4 -> 523684.21 | F4: =E4-E3 -> 227631.58 | G4: 0 | H4: =SUM($G$2:G4) -> 500000 | I4: =E4-H4 -> 23684.211 | J4: =IF(I4>0,"Contract Asset",IF(I4<0,"Contract Liability", "Balanced")) -> Contract Asset
A5: 45935 | B5: 210000 | C5: =SUM($B$2:B5) -> 608000 | D5: =C5/'CONTRACT SETUP'!$B$5 -> 0.16 | E5: =D5*'CONTRACT SETUP'!$B$4 -> 800000 | F5: =E5-E4 -> 276315.79 | G5: 0 | H5: =SUM($G$2:G5) -> 500000 | I5: =E5-H5 -> 300000 | J5: =IF(I5>0,"Contract Asset",IF(I5<0,"Contract Liability", "Balanced")) -> Contract Asset
A6: 45967 | B6: 260000 | C6: =SUM($B$2:B6) -> 868000 | D6: =C6/'CONTRACT SETUP'!$B$5 -> 0.22842105 | E6: =D6*'CONTRACT SETUP'!$B$4 -> 1142105.3 | F6: =E6-E5 -> 342105.26 | G6: 0 | H6: =SUM($G$2:G6) -> 500000 | I6: =E6-H6 -> 642105.26 | J6: =IF(I6>0,"Contract Asset",IF(I6<0,"Contract Liability", "Balanced")) -> Contract Asset
A7: 45999 | B7: 285000 | C7: =SUM($B$2:B7) -> 1153000 | D7: =C7/'CONTRACT SETUP'!$B$5 -> 0.30342105 | E7: =D7*'CONTRACT SETUP'!$B$4 -> 1517105.3 | F7: =E7-E6 -> 375000 | G7: ='CONTRACT SETUP'!D13 -> 1000000 | H7: =SUM($G$2:G7) -> 1500000 | I7: =E7-H7 -> 17105.263 | J7: =IF(I7>0,"Contract Asset",IF(I7<0,"Contract Liability", "Balanced")) -> Contract Asset
A8: 46031 | B8: 350000 | C8: =SUM($B$2:B8) -> 1503000 | D8: =C8/'CONTRACT SETUP'!$B$5 -> 0.39552632 | E8: =D8*'CONTRACT SETUP'!$B$4 -> 1977631.6 | F8: =E8-E7 -> 460526.32 | G8: 0 | H8: =SUM($G$2:G8) -> 1500000 | I8: =E8-H8 -> 477631.58 | J8: =IF(I8>0,"Contract Asset",IF(I8<0,"Contract Liability", "Balanced")) -> Contract Asset
A9: 46063 | B9: 360000 | C9: =SUM($B$2:B9) -> 1863000 | D9: =C9/'CONTRACT SETUP'!$B$5 -> 0.49026316 | E9: =D9*'CONTRACT SETUP'!$B$4 -> 2451315.8 | F9: =E9-E8 -> 473684.21 | G9: 0 | H9: =SUM($G$2:G9) -> 1500000 | I9: =E9-H9 -> 951315.79 | J9: =IF(I9>0,"Contract Asset",IF(I9<0,"Contract Liability", "Balanced")) -> Contract Asset
A10: 46095 | B10: 380000 | C10: =SUM($B$2:B10) -> 2243000 | D10: =C10/'CONTRACT SETUP'!$B$5 -> 0.59026316 | E10: =D10*'CONTRACT SETUP'!$B$4 -> 2951315.8 | F10: =E10-E9 -> 500000 | G10: 0 | H10: =SUM($G$2:G10) -> 1500000 | I10: =E10-H10 -> 1451315.8 | J10: =IF(I10>0,"Contract Asset",IF(I10<0,"Contract Liability", "Balanced")) -> Contract Asset
A11: 46127 | B11: 350000 | C11: =SUM($B$2:B11) -> 2593000 | D11: =C11/'CONTRACT SETUP'!$B$5 -> 0.68236842 | E11: =D11*'CONTRACT SETUP'!$B$4 -> 3411842.1 | F11: =E11-E10 -> 460526.32 | G11: 0 | H11: =SUM($G$2:G11) -> 1500000 | I11: =E11-H11 -> 1911842.1 | J11: =IF(I11>0,"Contract Asset",IF(I11<0,"Contract Liability", "Balanced")) -> Contract Asset
A12: 46159 | B12: 300000 | C12: =SUM($B$2:B12) -> 2893000 | D12: =C12/'CONTRACT SETUP'!$B$5 -> 0.76131579 | E12: =D12*'CONTRACT SETUP'!$B$4 -> 3806578.9 | F12: =E12-E11 -> 394736.84 | G12: ='CONTRACT SETUP'!D14 -> 2000000 | H12: =SUM($G$2:G12) -> 3500000 | I12: =E12-H12 -> 306578.95 | J12: =IF(I12>0,"Contract Asset",IF(I12<0,"Contract Liability", "Balanced")) -> Contract Asset
A13: 46191 | B13: 210000 | C13: =SUM($B$2:B13) -> 3103000 | D13: =C13/'CONTRACT SETUP'!$B$5 -> 0.81657895 | E13: =D13*'CONTRACT SETUP'!$B$4 -> 4082894.7 | F13: =E13-E12 -> 276315.79 | G13: 0 | H13: =SUM($G$2:G13) -> 3500000 | I13: =E13-H13 -> 582894.74 | J13: =IF(I13>0,"Contract Asset",IF(I13<0,"Contract Liability", "Balanced")) -> Contract Asset
A14: 46223 | B14: 180000 | C14: =SUM($B$2:B14) -> 3283000 | D14: =C14/'CONTRACT SETUP'!$B$5 -> 0.86394737 | E14: =D14*'CONTRACT SETUP'!$B$4 -> 4319736.8 | F14: =E14-E13 -> 236842.11 | G14: 0 | H14: =SUM($G$2:G14) -> 3500000 | I14: =E14-H14 -> 819736.84 | J14: =IF(I14>0,"Contract Asset",IF(I14<0,"Contract Liability", "Balanced")) -> Contract Asset
A15: 46255 | B15: 150000 | C15: =SUM($B$2:B15) -> 3433000 | D15: =C15/'CONTRACT SETUP'!$B$5 -> 0.90342105 | E15: =D15*'CONTRACT SETUP'!$B$4 -> 4517105.3 | F15: =E15-E14 -> 197368.42 | G15: 0 | H15: =SUM($G$2:G15) -> 3500000 | I15: =E15-H15 -> 1017105.3 | J15: =IF(I15>0,"Contract Asset",IF(I15<0,"Contract Liability", "Balanced")) -> Contract Asset
A16: 46287 | B16: 140000 | C16: =SUM($B$2:B16) -> 3573000 | D16: =C16/'CONTRACT SETUP'!$B$5 -> 0.94026316 | E16: =D16*'CONTRACT SETUP'!$B$4 -> 4701315.8 | F16: =E16-E15 -> 184210.53 | G16: 0 | H16: =SUM($G$2:G16) -> 3500000 | I16: =E16-H16 -> 1201315.8 | J16: =IF(I16>0,"Contract Asset",IF(I16<0,"Contract Liability", "Balanced")) -> Contract Asset
A17: 46319 | B17: 107000 | C17: =SUM($B$2:B17) -> 3680000 | D17: =C17/'CONTRACT SETUP'!$B$5 -> 0.96842105 | E17: =D17*'CONTRACT SETUP'!$B$4 -> 4842105.3 | F17: =E17-E16 -> 140789.47 | G17: ='CONTRACT SETUP'!D15 -> 1500000 | H17: =SUM($G$2:G17) -> 5000000 | I17: =E17-H17 -> -157894.74 | J17: =IF(I17>0,"Contract Asset",IF(I17<0,"Contract Liability", "Balanced")) -> Contract Liability
A18: 46351 | B18: 70000 | C18: =SUM($B$2:B18) -> 3750000 | D18: =C18/'CONTRACT SETUP'!$B$5 -> 0.98684211 | E18: =D18*'CONTRACT SETUP'!$B$4 -> 4934210.5 | F18: =E18-E17 -> 92105.263 | G18: 0 | H18: =SUM($G$2:G18) -> 5000000 | I18: =E18-H18 -> -65789.474 | J18: =IF(I18>0,"Contract Asset",IF(I18<0,"Contract Liability", "Balanced")) -> Contract Liability
A19: 46383 | B19: 50000 | C19: =SUM($B$2:B19) -> 3800000 | D19: =C19/'CONTRACT SETUP'!$B$5 -> 1 | E19: =D19*'CONTRACT SETUP'!$B$4 -> 5000000 | F19: =E19-E18 -> 65789.474 | G19: 0 | H19: =SUM($G$2:G19) -> 5000000 | I19: =E19-H19 -> 0 | J19: =IF(I19>0,"Contract Asset",IF(I19<0,"Contract Liability", "Balanced")) -> Balanced
A20: Total: | B20: =SUM(B2:B19) -> 3800000 | C20: =C19 -> 3800000 | D20: =D19 -> 1 | E20: =E19 -> 5000000 | F20: =IF(SUM(F2:F19)='CONTRACT SETUP'!B4, "VALID", "ERROR") -> VALID | G20: =IF(SUM(G2:G19)='CONTRACT SETUP'!B4, "VALID", "ERROR") -> VALID | H20: =H19 -> 5000000 | I20: =IF((I19) = 0, "VALID", "ERROR") -> VALID

Sheet COST TRACKING
A1: Month | B1: Planned Cost Incurred This Month | C1: Actual Cost This Month | D1: Variance | E1: RAG status
A2: 45839 | B2: 75000 | C2: 85000 | D2: =C2-B2 -> 10000 | E2: =IF(C2<=B2, "🟢", IF(C2<=B2*1.05, "🟡", "🔴")) -> 🔴
A3: 45871 | B3: 150000 | C3: 140000 | D3: =C3-B3 -> -10000 | E3: =IF(C3<=B3, "🟢", IF(C3<=B3*1.05, "🟡", "🔴")) -> 🟢
A4: 45903 | B4: 173000 | C4: 193000 | D4: =C4-B4 -> 20000 | E4: =IF(C4<=B4, "🟢", IF(C4<=B4*1.05, "🟡", "🔴")) -> 🔴
A5: 45935 | B5: 210000 | C5: 200000 | D5: =C5-B5 -> -10000 | E5: =IF(C5<=B5, "🟢", IF(C5<=B5*1.05, "🟡", "🔴")) -> 🟢
A6: 45967 | B6: 260000 | C6: 250000 | D6: =C6-B6 -> -10000 | E6: =IF(C6<=B6, "🟢", IF(C6<=B6*1.05, "🟡", "🔴")) -> 🟢
A7: 45999 | B7: 285000 | C7: 305000 | D7: =C7-B7 -> 20000 | E7: =IF(C7<=B7, "🟢", IF(C7<=B7*1.05, "🟡", "🔴")) -> 🔴
A8: 46031 | B8: 350000 | C8: 350000 | D8: =C8-B8 -> 0 | E8: =IF(C8<=B8, "🟢", IF(C8<=B8*1.05, "🟡", "🔴")) -> 🟢
A9: 46063 | B9: 360000 | C9: 320000 | D9: =C9-B9 -> -40000 | E9: =IF(C9<=B9, "🟢", IF(C9<=B9*1.05, "🟡", "🔴")) -> 🟢
A10: 46095 | B10: 380000 | C10: 380000 | D10: =C10-B10 -> 0 | E10: =IF(C10<=B10, "🟢", IF(C10<=B10*1.05, "🟡", "🔴")) -> 🟢
A11: 46127 | B11: 350000 | C11: 360000 | D11: =C11-B11 -> 10000 | E11: =IF(C11<=B11, "🟢", IF(C11<=B11*1.05, "🟡", "🔴")) -> 🟡
A12: 46159 | B12: 300000 | C12: 310000 | D12: =C12-B12 -> 10000 | E12: =IF(C12<=B12, "🟢", IF(C12<=B12*1.05, "🟡", "🔴")) -> 🟡
A13: 46191 | B13: 210000 | C13: 220000 | D13: =C13-B13 -> 10000 | E13: =IF(C13<=B13, "🟢", IF(C13<=B13*1.05, "🟡", "🔴")) -> 🟡
... A19: 46383 | B19: 50000 | C19: 27000 | D19: =C19-B19 -> -23000 | E19: =IF(C19<=B19, "🟢", IF(C19<=B19*1.05, "🟡", "🔴")) -> 🟢
A20: Total | B20: =SUM(B2:B19) -> 3800000 | C20: =SUM(C2:C19) -> 3800000 | D20: =C20-B20 -> 0 | E20: =IF(C20<=B20, "🟢", IF(C20<=B20*1.05, "🟡", "🔴")) -> 🟢

Sheet ASC 606 SUMMARY
A1: ASC 606 — Five-Step Revenue Recognition Model | ABC Industrial Solutions × XYZ Manufacturing Corp
A2: STEP 1 — IDENTIFY THE CONTRACT
A3: Fixed-price contract between ABC Industrial Solutions (Supplier) and XYZ Manufacturing Corp (Customer) for custom equipment installation. Contract is legally enforceable with defined payment terms and commercial substance.
A4: Customer | B4: Supplier | C4: Contract Value | D4: Start Date | E4: End Date | F4: Duration
A5: ='CONTRACT SETUP'!B2 -> XYZ Manufacturing Corp | B5: =Table1[[#Headers],[ABC Industrial Solutions]] -> ABC Industrial Solutions | C5: ='CONTRACT SETUP'!B4 -> 5000000 | D5: ='CONTRACT SETUP'!B6 -> 45839 | E5: ='CONTRACT SETUP'!B7 -> 46387 | F5: 18 months
A8: STEP 2 — IDENTIFY PERFORMANCE OBLIGATIONS
A9: The contract contains four distinct performance obligations. Each milestone represents a separately identifiable deliverable that transfers control to the customer.
A10: Milestone | B10: Description | C10: % of contract
A11: ='CONTRACT SETUP'!A12 -> M1 | B11: ='CONTRACT SETUP'!B12 -> Contract Signing | C11: ='CONTRACT SETUP'!C12 -> 0.1
A12: ='CONTRACT SETUP'!A13 -> M2 | B12: ='CONTRACT SETUP'!B13 -> Design Approval | C12: ='CONTRACT SETUP'!C13 -> 0.2
A13: ='CONTRACT SETUP'!A14 -> M3 | B13: ='CONTRACT SETUP'!B14 -> Testing Complete | C13: ='CONTRACT SETUP'!C14 -> 0.4
A14: M4 | B14: ='CONTRACT SETUP'!B15 -> Final Delivery | C14: ='CONTRACT SETUP'!C15 -> 0.3
A15: Total | C15: =SUM(C11:C14) -> 1
A18: STEP 3 — DETERMINE THE TRANSACTION PRICE
A19: The transaction price is fixed at contract signing. There is no variable consideration, significant financing component, non-cash consideration, or amounts payable to the customer.
A20: Contract Value | B20: Contract Type | C20: Currency | D20: Variable Consideration
A21: ='CONTRACT SETUP'!B4 -> 5000000 | B21: Fixed-Price | C21: USD | D21: None
A24: STEP 4 — ALLOCATE THE TRANSACTION PRICE
A25: The transaction price is allocated to each performance obligation based on relative standalone selling price. For this fixed-price contract, allocation follows the milestone billing schedule agreed at contract inception.
A26: Milestone | B26: Description | C26: Allocation % | D26: Allocated Amount
A27: ='CONTRACT SETUP'!A12 -> M1 | B27: ='CONTRACT SETUP'!B12 -> Contract Signing | C27: ='CONTRACT SETUP'!C12 -> 0.1 | D27: ='CONTRACT SETUP'!D12 -> 500000
A28: ='CONTRACT SETUP'!A13 -> M2 | B28: ='CONTRACT SETUP'!B13 -> Design Approval | C28: ='CONTRACT SETUP'!C13 -> 0.2 | D28: ='CONTRACT SETUP'!D13 -> 1000000
A29: ='CONTRACT SETUP'!A14 -> M3 | B29: ='CONTRACT SETUP'!B14 -> Testing Complete | C29: ='CONTRACT SETUP'!C14 -> 0.4 | D29: ='CONTRACT SETUP'!D14 -> 2000000
A30: ='CONTRACT SETUP'!A15 -> M4 | B30: ='CONTRACT SETUP'!B15 -> Final Delivery | C30: ='CONTRACT SETUP'!C15 -> 0.3 | D30: ='CONTRACT SETUP'!D15 -> 1500000
A31: Total | C31: =SUM(C27:C30) -> 1 | D31: =SUM(D27:D30) -> 5000000
A34: STEP 5 — RECOGNIZE REVENUE
A35: Revenue is recognized over time using the cost-to-cost input method. The percentage of completion is calculated as cumulative costs incurred to date divided by total estimated contract costs. This method faithfully depicts the transfer of control to the customer as work progresses.
A36: % Complete = Cumulative Costs Incurred ÷ Total Estimated Costs
A37: % Complete | B37: Cumulative Revenue Recognized | C37: Cumulative Billings | D37: Contract Asset / (Liability)
A38: ='REVENUE RECOGNITION SCHEDULE'!D19 -> 1 | B38: ='REVENUE RECOGNITION SCHEDULE'!E19 -> 5000000 | C38: ='REVENUE RECOGNITION SCHEDULE'!H19 -> 5000000 | D38: ='REVENUE RECOGNITION SCHEDULE'!I19 -> 0
A42: =IF(I19>0,"Contract Asset — Revenue recognized exceeds billings. Customer owes outstanding balance.",IF(X1<0,"Contract Liability — Billings exceed revenue recognized. Performance obligation outstanding.","Balanced — Revenue recognized equals billings. Contract fully settled.")) -> Balanced — Revenue recognized equals billings. Contract fully settled.
A43: Methodology: ASC 606 — Revenue from Contracts with Customers (FASB) | Cost-to-Cost Input Method | Built by Ekaterina Kucherova | May 2026 | Independent portfolio project — fictional data
